Workbook
Name EVT_HAI: #REF!
Name RA_NRO: #REF!
Name AK_SER: #REF!
Name NL_LOU: #REF!
Name EP_ROO: #REF!
Name EVT_VAL: #REF!
Name ACC_TAGS: REF_CODES!$J$187:$J$189
Name RA_DNA: #REF!
Name EVT_ANE: #REF!
Name AU_ELI: #REF!
Name TR_BEL: #REF!
Name SE_SUR: #REF!
Name NL_LIV: #REF!
Name EVT_BRB: #REF!
Name KD_ACT: #REF!
Name EP_GAL: #REF!
Name EVT_PHO: #REF!
Name EP_BIV: #REF!
Name LAB_TBL: #REF!
Name NPS_PASSI: #REF!
Name KD_KFR: #REF!
Name SECURITE: REF_CODES!$J$62:$J$66
Name EVT_CHE: #REF!
Name EVT_MIX: #REF!
Name LAB_LHW: #REF!
Name LIEU_LIB: REF_CODES!$C$142:$C$157
Name EVT_SOU: #REF!
Name ACTIVITE: REF_CODES!$J$27:$J$33
Name EVT_FXS: #REF!
Name EVT_MAS: #REF!
Name EP_POL: #REF!
Name AU_EXC: #REF!
Name EVT_PYR: #REF!
Name EVT_ARC: #REF!
Name EVT_HAM: #REF!
Name EP_BEA: #REF!
Name SE_ETU: #REF!
Name EP_PAL: #REF!
Name TRANSPORT_LIB: REF_CODES!$C$250:$C$261
Name LAB_RC: #REF!
Name TRANSPORT: REF_CODES!$J$58:$J$61
Name LAB_SLH: #REF!
Name AK_NAT: #REF!
Name EVT_NAI: #REF!
Name SE_FEM: #REF!
Name LAB_CN: #REF!
Name NL_IMM: #REF!
Name EP_RES: #REF!
Name TR_SUV: #REF!
Name EVT_FLO: #REF!
Name FID_HOT: #REF!
Name FID_AMB: #REF!
Name EVENEMENTIEL: REF_CODES!$J$87:$J$132
Name AMB_ROM: #REF!
Name NL_SHO: #REF!
Name ST_ULT: #REF!
Name RA_NFE: #REF!
Name EVT_DJ: #REF!
Name RA_NVE: #REF!
Name AMB_FAM: #REF!

Sheet 🌐 PAGE WEB · PARCOURS
A1: 🌐 PAGE WEB · PARCOURS CLIENT
A2: Source de vérité du parcours utilisateur SOLYVENTS · 5 étapes · de la configuration à la confirmation
A3: ✅ V1 · vérifié · aligné sur 🔖 CODES DE RÉFÉRENCE
B4: 📌 SOURCE DE VÉRITÉ DU PARCOURS CLIENT
B5: Cet onglet décrit l'expérience client (ce qu'il VOIT, ce qu'il CHOISIT, et les RÈGLES MÉTIER de chaque saisie). Les CODES et LIBELLÉS font foi dans 🔖 CODES DE RÉFÉRENCE (Bible data → CRM) : le référentiel s'aligne sur le dictionnaire, pas l'inverse. Parcours et dictionnaire sont complémentaires : l'un définit l'expérience, l'autre l'identité des codes.
B10: ⚙️ DOCTRINE FONDAMENTALE · STRUCTURE vs CONTENU
B11: Les éléments listés dans cet onglet (codes AU-*, RA-D*, RA-N*, NL-*, AK-*) ne sont PAS figés dans le référentiel : ce sont des STRUCTURES. La VÉRITÉ vient du CRM SOLYVENTS : • Le RÉFÉRENTIEL définit la STRUCTURE (catégories / sous-catégories / codes) • Le CRM contient le CONTENU (prestations concrètes de fiches presta validées en statut QUA ou DER) • Le MOTEUR orchestre le MATCHING client ↔ presta À chaque slot du parcours, les éléments affichés au client sont DÉVERSÉS depuis le CRM (fiches presta disponibles au moment de la consultation).
B17: ═══ ÉTAPE 1 · CONFIGURATION DU SÉJOUR ═══
B19: 1.1 · 📅 DATES DU SÉJOUR
B20: Saisie | C20: Date d'arrivée + Date de départ
B21: Déduit auto | C21: • Nombre de nuits • Nombre de jours à programmer en ÉTAPE 2
B23: 1.2 · 👥 COMPOSITION DU GROUPE
B24: Saisie | C24: • Compteur Nombre d'ADULTES • Compteur Nombre d'ENFANTS • ÂGE de chaque enfant (nécessaire pour pré-calc chambres et slot Enfants)
B25: ⚙️ Règle | C25: IF nb_enfants > 0 → afficher slot "ENFANTS" en ÉTAPE 2
B27: 1.3 · 🚉 MODE D'ARRIVÉE À MARRAKECH
B28: Saisie | C28: Question single-select : Par quel moyen vous rendrez-vous à Marrakech ?
B29: ✈️ Avion | C29: Message auto : "Je confie à SOLY le soin de gérer l'ensemble de mes déplacements" → gestion_transport = SOLY_GERE (forcé)
B30: 🚄 Train | C30: Message auto : idem AVION → gestion_transport = SOLY_GERE (forcé)
B31: 🚗 Voiture | C31: Deux cases à cocher proposées : ☐ "Je gère seul mes déplacements" → gestion_transport = CLIENT_GERE ☐ "Je confie à SOLY le soin de gérer l'ensemble de mes déplacements" → gestion_transport = SOLY_GERE
B32: Variables | C32: • mode_arrivee (enum : AVION / TRAIN / VOITURE) → NIVEAU 1 • gestion_transport (enum : SOLY_GERE / CLIENT_GERE) → NIVEAU 1 PAS de famille de codes dédiée · simple champ technique
B34: 1.4 · 🎨 ESPRIT DU SÉJOUR · OR-*
B35: Affichage | C35: 5 cartes visuelles · single-select obligatoire
B36: OR-ZEN | C36: ZEN & BIEN-ÊTRE
B37: OR-ROM | C37: ROMANTIQUE
B38: OR-FAM | C38: FAMILIAL
B39: OR-FES | C39: FESTIF
B40: OR-PRO | C40: PROFESSIONNEL
B42: 1.5 · 🏨 PRISE EN CHARGE HÉBERGEMENT PAR SOLYVENTS
B43: Question | C43: Oui / Non
B44: ⚙️ Si NON | C44: Pas de questions 1.5.1/1.5.2/1.5.3 · passage direct à ÉTAPE 2
B45: ⚙️ Si OUI | C45: Sous-questions 1.5.1 + 1.5.2 + 1.5.3 obligatoires
B47: 1.5.1 · 🛏️ | C47: NOMBRE DE CHAMBRES
B48: Algorithme | C48: Compteur PRÉ-CALCULÉ par défaut selon règle : • 2 adultes / chambre par défaut • Enfants < 12 ans → dans chambre des parents (avec les parents en hôtel) • Enfants ≥ 12 ans → 1 chambre supplémentaire Ajustement possible par le client (peut augmenter ou diminuer)
B49: Exemples | C49: • 2 adultes + 1 enfant 5 ans = 1 chambre • 2 adultes + 2 enfants 7 et 10 ans = 1 chambre • 2 adultes + 1 enfant 14 ans = 2 chambres • 4 adultes = 2 chambres • 4 adultes + 1 ado 15 ans = 3 chambres
B51: 1.5.2 · 🏛️ | C51: ATMOSPHÈRE DU SÉJOUR · HB-*
B52: Affichage | C52: 6 cartes · single-select
B53: HB-HOT | C53: HOTEL & RESORT
B54: HB-INC | C54: INCONTOURNABLE
B55: HB-RIA | C55: RIAD & PATRIMOINE
B56: HB-COL | C56: COLLECTION PRIVÉE
... B68: Fin ÉTAPE 1 | C68: Message client : "Le devis hébergement vous sera posté sous 24h dans votre espace SOLYVENTS" → Passage à ÉTAPE 2
B71: ═══ ÉTAPE 2 · VOTRE EXPÉRIENCE ═══
B73: 2.1 · 🎉 ÉVÉNEMENT À CÉLÉBRER
B74: Question | C74: Avez-vous un événement à célébrer durant votre séjour ? Oui / Non
B75: ⚙️ Si OUI | C75: Sous-question 2.1.1 : choix EV-*
B76: ⚙️ Si NON | C76: Passage direct au programme jour par jour
B78: 2.1.1 | C78: Choix de l'événement EV-* · QUOTAS MINIMUM par type · NB : ANNIVERSAIRE est une catégorie PARENTE à 2 sous-choix (festif / familial)
B79: EV-AFE | C79: ↓ ANNIVERSAIRE · FESTIF (EV-AFE) · MINIMUM 5 participants (obligatoire) · contexte adultes
B80: EV-AFA | C80: ↓ ANNIVERSAIRE · FAMILIAL (EV-AFA) · MINIMUM 5 participants (obligatoire) · SEUL événement ouvrant le choix du nb d'enfants (compteur étape 1 inchangé par ailleurs)
B82: EV-DEM | C82: DEMANDE EN MARIAGE · 2 adultes · SEULE EXCEPTION à la règle des 5 (pas de minimum)
B83: EV-EVJF | C83: EVJF · MINIMUM 5 participants (obligatoire)
B84: EV-EVG | C84: EVG · MINIMUM 5 participants (obligatoire)
B85: EV-AUT | C85: AUTRE · champ libre "à décrire" · seuils à clarifier au cas par cas
B86: ⚙️ Règle moteur | C86: ACCÈS ÉVÉNEMENT · MINIMUM 5 PARTICIPANTS obligatoire pour TOUS les EV-* — SEULE EXCEPTION : EV-DEM (demande en mariage = 2 adultes). IF nb_participants (étape 1) < 5 et EV ≠ EV-DEM → PACK INDISPONIBLE : l'événement est masqué/désactivé, message « Événement accessible à partir de 5 participants » (blocage dur). EV-AUT : seuils au cas par cas SOLY.
B87: 🎁 PACK ÉVÉNEMENT | C87: V1 · doctrine PACK ÉVÉNEMENT (déversement CRM) Quand un EV-* est coché (sauf EV-AUT), le moteur déverse depuis le CRM SOLYVENTS 2 PACKS ÉVÉNEMENT pour ce type d'événement : • PACK 1 · niveau d'entrée • PACK 2 · niveau supérieur Chaque PACK contient (défini dans la fiche CRM · ajusté selon le NOMBRE DE PARTICIPANTS) : • Créneau séjour réservé (jour + slots) — grise les activités 2.4→2.8 du créneau · 2.9 (activité enfant) reste disponible • Activité (AU-*) • Repas (RA-D* / RA-N*) • Animation (EVT-*) • Prestataires événementiels (EVT-* : DJ, traiteur, déco, fleuriste…) • Sécurité événementielle (SE-ESC / SE-EVE / SE-MUL selon le nombre de personnes) • Espaces privatisables (EP-*) • Transport (TR-*) • Budget total du pack (prix de revient + honoraires SOLY) Le client voit les 2 PACKS · 2 cartes · DÉTAIL COMPLET visible (transparence luxe) · single-select obligatoire entre les 2. ⚠️ PACK FERMÉ · à prendre tel quel · pas de personnalisation. Besoin spécifique → bascule EV-AUT (cas par cas SOLY). ⚙️ Cas EV-AUT (Autre événement) : • Pas de PACKS CRM prédéfinis • Message client : « Un conseiller SOLY vous contactera sous 24h » • Le client CONTINUE le parcours normalement (2.2 → 2.11) • SOLY ASSISTANCE personnalise en parallèle 📌 STRUCTURE vs CONTENU : • Le RÉFÉRENTIEL définit la doctrine (2 packs · client choisit · pack fermé) • Le CRM contient le détail chiffré des fiches PACK → onglet 🎁 PACKS ÉVÉNEMENT • Le MOTEUR orchestre le déversement (règles d'inclusion par type EV-* dans ⚙️ MOTEUR)
B89: 2.2 · 📅 PROGRAMME JOUR PAR JOUR
B90: Génération | C90: Onglets auto-générés selon les dates 1.1 : • JOUR 1 · [date] • JOUR 2 · [date] • ... • JOUR N · [date]
B91: ⚙️ Règle min activités | C91: V1 · Chaque journée du séjour doit comporter au minimum 2 sélections parmi les expériences proposées (AU, AK, RA, NL) Une journée comportant moins de 2 sélections ne peut pas être validée.
B92: 💬 Accroche client (page web) | C92: Composez chaque journée selon vos envies Quelques choix suffisent pour enclencher SOLÝ. Sélectionnez au minimum 2 expériences par jour, nous orchestrerons le reste.
B93: 2.3 · 📍 LIEU (menu déroulant)
B94: Valeurs | C94: • Marrakech (seul lieu actuellement) • Menu extensible à d'autres villes (référentiel mondial cible)
B95: ⚙️ Doctrine V1 | C95: V1 · LIEU = destination UNIQUE pour tout le séjour. Tout le programme jour par jour se déroule dans cette ville. (Pas de combo multi-villes dans un même séjour · 1 lieu = 1 séjour)
B97: ⚙️ DOCTRINE V1 · MULTI-SELECT SUR LES SLOTS
B98: Sur chaque slot horaire (2.4 / 2.5 / 2.6 / 2.7 / 2.8 / 2.9), le MULTI-SELECT est activé : • Le client coche autant d'univers qu'il veut (AU-* / RA-D* / RA-N* / NL-* / AK-*) • Le moteur déverse les options du CRM correspondantes aux univers cochés • Le client choisit librement parmi les options déversées • Le devis somme automatiquement les expériences en y integrant le transport TR • SOLY orchestre la répartition entre les voyageurs derrière (en post-paiement) Pourquoi multi-select : un séjour SOLYVENTS peut avoir plusieurs voyageurs avec des préférences différentes sur un même slot. Le parcours ne demande PAS d'identifier nominativement chaque voyageur · SOLY gère cette répartition en backoffice.
B100: 2.4 · 🌅 MATINÉE (slot 1) · codes AU-* (univers d'activité)
B101: AU-EXC | C101: EXCURSION À LA JOURNÉE · ⚠️ EXCLUSIF · contenu déversé depuis CRM
B102: AU-BIE | C102: BIEN-ÊTRE & RELAXATION · contenu déversé depuis CRM
B103: AU-DES | C103: DÉSERT & HORIZONS · contenu déversé depuis CRM
B104: AU-SPO | C104: SPORT & ÉNERGIE · contenu déversé depuis CRM
B105: AU-CUL | C105: CULTURE & IMMERSION · contenu déversé depuis CRM
B106: AU-ELI | C106: ÉLITE & SIGNATURE · contenu déversé depuis CRM
B107: ⚙️ RÈGLE EXCLU | C107: IF AU-EXC coché : désactive slots 2.5 DÉJEUNER + 2.6 APRÈS-MIDI · seuls DÎNER et SOIRÉE accessibles
B109: 2.5 · 🍽️ DÉJEUNER (slot 2) · codes RA-D* (Restauration · Déjeuner)
B110: RA-DBR | C110: Brunch · contenu déversé depuis CRM RESTAURANTS
B111: RA-DLE | C111: Déjeuner léger & élégant · contenu déversé depuis CRM RESTAURANTS
B112: RA-DMA | C112: Déjeuner marocain d'exception · contenu déversé depuis CRM RESTAURANTS
B113: RA-DPO | C113: Poolside & Lifestyle · contenu déversé depuis CRM RESTAURANTS
B114: RA-DNA | C114: Nature & Évasion · contenu déversé depuis CRM RESTAURANTS
B115: RA-DSI | C115: Expérience signature · contenu déversé depuis CRM RESTAURANTS
B116: ⚙️ RG-* | C116: Régimes alimentaires cochables ici (RG-VEG / RG-ALG)
B118: 2.6 · 🌴 APRÈS-MIDI (slot 3) · codes AU-* (univers d'activité)
B119: AU-DES | C119: DÉSERT & HORIZONS · contenu déversé depuis CRM
B120: AU-SPO | C120: SPORT & ÉNERGIE · contenu déversé depuis CRM
B121: AU-CUL | C121: CULTURE & IMMERSION · contenu déversé depuis CRM
B122: AU-BIE | C122: BIEN-ÊTRE & RELAXATION · contenu déversé depuis CRM
B123: AU-ELI | C123: ÉLITE & SIGNATURE · contenu déversé depuis CRM
B124: AU-FES | C124: FESTIF & LIFESTYLE · contenu déversé depuis CRM · transition vers soirée
B126: 2.7 · 🍷 DÎNER (slot 4) · codes RA-N* (Restauration · Nuit/Dîner)
B127: RA-NRO | C127: Dîner romantique · contenu déversé depuis CRM RESTAURANTS
B128: RA-NGA | C128: Dîner gastronomique · contenu déversé depuis CRM RESTAURANTS
B129: RA-NSP | C129: Dîner spectacle · contenu déversé depuis CRM RESTAURANTS
B130: RA-NFE | C130: Dîner festif · contenu déversé depuis CRM RESTAURANTS
B131: RA-NAM | C131: Dîner ambiance marocaine · contenu déversé depuis CRM RESTAURANTS
B132: RA-NVE | C132: Dîner vue & évasion · contenu déversé depuis CRM RESTAURANTS
B133: ⚙️ RG-* | C133: Régimes alimentaires cochables ici (RG-VEG / RG-ALG)
B135: 2.8 · ✨ SOIRÉE (slot 5) · codes NL-* (5 codes V1)
B136: NL-CLU | C136: Club / boîte de nuit · contenu déversé depuis CRM
B137: NL-LOU | C137: Lounge / bar à cocktails · contenu déversé depuis CRM
B138: NL-SHO | C138: Show / cabaret · contenu déversé depuis CRM
B139: NL-LIV | C139: Live Music · concert live · contenu déversé depuis CRM
...

Sheet 🔖 CODES DE RÉFÉRENCE
A1: 🔖 CODES DE RÉFÉRENCE — ✅ V1 vérifié (BIBLE) · réordonné selon le PARCOURS WEB · 4 systèmes : WEB · ONB · MOTEUR/CRM · APP
A2: 📜 DOCTRINE · Le MOTEUR/CRM ne génère jamais une donnée ex nihilo : ses algorithmes s'appuient sur les données récoltées à l'ONBOARDING. Onboarding = matière première · Moteur = transformation.
A3: ━━━━━ ▼ BLOC CLIENT · familles du PARCOURS WEB (WEB ✓) ━━━━━
A4: ━━ OR · ORIENTATION CLIENT (5 codes) ━━ ESPRIT DU SEJOUR
A5: FAMILLE | B5: CODE | C5: LIBELLÉ | D5: DESCRIPTION | E5: WEB | F5: ONB | G5: MOTEUR/CRM | H5: APP | I5: STATUT | J5: USAGE
A6: OR | B6: OR-ZEN | C6: ZEN & BIEN-ÊTRE | D6: Boost spa/yoga/healing · sérénité | E6: ✓ | F6: ✓ | G6: ✓ | H6: – | I6: ✅ V1 | J6: Parcours web · Matching
A7: OR | B7: OR-ROM | C7: ROMANTIQUE | D7: Boost suite privée · rooftop sunset · dîner désert | E7: ✓ | F7: ✓ | G7: ✓ | H7: – | I7: ✅ V1 | J7: Parcours web · Matching
A8: OR | B8: OR-FAM | C8: FAMILIAL | D8: Boost resort · villa · kids club | E8: ✓ | F8: ✓ | G8: ✓ | H8: – | I8: ✅ V1 | J8: Parcours web · Matching
A9: OR | B9: OR-FES | C9: FESTIF | D9: Boost villa privatisable · rooftop · DJ · nightlife | E9: ✓ | F9: ✓ | G9: ✓ | H9: – | I9: ✅ V1 | J9: Parcours web · Matching
A10: OR | B10: OR-PRO | C10: PROFESSIONNEL | D10: Boost hôtel 5⁎ · palace · lounge business | E10: ✓ | F10: ✓ | G10: ✓ | H10: – | I10: ✅ V1 | J10: Parcours web · Matching
A11: ━━ HB · HÉBERGEMENT (6 codes) ━━ TYPE HEBERGEMENT
A12: FAMILLE | B12: CODE | C12: LIBELLÉ | D12: DESCRIPTION | E12: WEB | F12: ONB | G12: MOTEUR/CRM | H12: APP | I12: STATUT | J12: USAGE
A13: HB | B13: HB-HOT | C13: HOTEL & RESORT | D13: Hôtel 4⁎ · Hôtel 5⁎ · Resort | E13: ✓ | F13: ✓ | G13: ✓ | H13: – | I13: ✅ V1 | J13: Parcours web · Matching
A14: HB | B14: HB-INC | C14: INCONTOURNABLE | D14: Palace · Relais & Châteaux · Boutique hôtel | E14: ✓ | F14: ✓ | G14: ✓ | H14: – | I14: ✅ V1 | J14: Parcours web · Matching
A15: HB | B15: HB-RIA | C15: RIAD & PATRIMOINE | D15: Riad · Palais d'hôtes | E15: ✓ | F15: ✓ | G15: ✓ | H15: – | I15: ✅ V1 | J15: Parcours web · Matching
A16: HB | B16: HB-COL | C16: COLLECTION PRIVÉE | D16: Riad privatisable · Villa privée · Domaine privé | E16: ✓ | F16: ✓ | G16: ✓ | H16: – | I16: ✅ V1 | J16: Parcours web · Matching
A17: HB | B17: HB-NAT | C17: NATURE & HORIZON | D17: Desert Camp · Desert Resort · Lodge | E17: ✓ | F17: ✓ | G17: ✓ | H17: – | I17: ✅ V1 | J17: Parcours web · Matching
A18: HB | B18: HB-SUR | C18: SUR MESURE ABSOLU | D18: MODE COMBINAISON : le client assemble 2 types d'hébergement OU PLUS sur le séjour (ex : riad médina + camp désert). N'est PAS un 6e type — voyage multi-lieux composé par SOLY. · IMPOSE automatiquement BG-LIBRE (le client ne choisit pas de tranche BG1–BG5). | E18: ✓ | F18: ✓ | G18: ✓ | H18: – | I18: ✅ V1 | J18: Parcours web · Matching
A19: ━━ BG · BUDGET (6 codes) ━━ BUDGET HEBERGEMENT PAR NUIT ET PAR CHAMBRE
A20: FAMILLE | B20: CODE | C20: LIBELLÉ | D20: DESCRIPTION | E20: WEB | F20: ONB | G20: MOTEUR/CRM | H20: APP | I20: STATUT | J20: USAGE
A21: BG | B21: BG1 | C21: Moins de 300 € | D21: Budget moyen / nuit / chambre | E21: ✓ | F21: ✓ | G21: ✓ | H21: – | I21: ✅ V1 | J21: Parcours web · Onboarding · Matching
A22: BG | B22: BG2 | C22: 300 – 500 € | D22: Budget moyen / nuit / chambre | E22: ✓ | F22: ✓ | G22: ✓ | H22: – | I22: ✅ V1 | J22: Parcours web · Onboarding · Matching
A23: BG | B23: BG3 | C23: 500 – 800 € | D23: Budget moyen / nuit / chambre | E23: ✓ | F23: ✓ | G23: ✓ | H23: – | I23: ✅ V1 | J23: Parcours web · Onboarding · Matching
A24: BG | B24: BG4 | C24: 800 – 1 200 € | D24: Budget moyen / nuit / chambre | E24: ✓ | F24: ✓ | G24: ✓ | H24: – | I24: ✅ V1 | J24: Parcours web · Onboarding · Matching
A25: BG | B25: BG5 | C25: 1 200 € et + | D25: Budget moyen / nuit / chambre | E25: ✓ | F25: ✓ | G25: ✓ | H25: – | I25: ✅ V1 | J25: Parcours web · Onboarding · Matching
A26: BG | B26: BG-LIBRE | C26: SUR MESURE | D26: Budget sur mesure (composé) · désactive le filtre · EXCLUSIVEMENT lié à HB-SUR — jamais proposé avec un hébergement classique (HB-HOT/INC/RIA/COL/NAT), qui utilisent BG1–BG5. | E26: ✓ | F26: ✓ | G26: ✓ | H26: – | I26: ✅ V1 | J26: Parcours web · Onboarding · Matching
A27: ━━ EV · ÉVÉNEMENTS (5 standards · V1) ━━ AVEZ-VOUS UN EVENEMENT A CELEBRER DURANT LE SEJOUR
A28: EV | B28: EV-DEM | C28: DEMANDE EN MARIAGE | D28: 2 adultes · pack CRM (PACK1/PACK2) | E28: ✓ | F28: – | G28: ✓ | H28: – | I28: ✅ V1 | J28: Parcours web · Matching
A29: EV | B29: EV-ANN | C29: ANNIVERSAIRE (parent) | D29: Catégorie parente · 2 sous-choix : festif (EV-AFE) / familial (EV-AFA) · seul le familial ouvre le nb d'enfants | E29: ✓ | F29: – | G29: ✓ | H29: – | I29: ✅ V1 | J29: Parcours web · Matching
A30: EV | B30: EV-AFE | C30: ANNIVERSAIRE FESTIF | D30: Ambiance fête · ≥5 adultes · pack CRM | E30: ✓ | F30: – | G30: ✓ | H30: – | I30: ✅ V1 | J30: Parcours web · Matching
A31: EV | B31: EV-AFA | C31: ANNIVERSAIRE FAMILIAL | D31: Cadre intime famille · ≥5 ad · pack CRM | E31: ✓ | F31: – | G31: ✓ | H31: – | I31: ✅ V1 | J31: Parcours web · Matching
A32: EV | B32: EV-EVJF | C32: EVJF | D32: ≥5 adultes · pack CRM | E32: ✓ | F32: – | G32: ✓ | H32: – | I32: ✅ V1 | J32: Parcours web · Matching
A33: EV | B33: EV-EVG | C33: EVG | D33: ≥5 adultes · pack CRM | E33: ✓ | F33: – | G33: ✓ | H33: – | I33: ✅ V1 | J33: Parcours web · Matching
A34: EV | B34: EV-AUT | C34: AUTRE (cas par cas) | D34: Champ libre · SOLY ASSISTANCE 24h · pas de pack CRM | E34: ✓ | F34: – | G34: ✓ | H34: – | I34: ✅ V1 | J34: Parcours web · Matching
A35: 📌 V1 · RAPPEL DOCTRINE • Les codes ci-dessus complètent les familles V1 conservées plus bas • Tous les codes (V1 + V1/V1) sont utilisés dans le PARCOURS · le MOTEUR · le CRM · l'INGESTION • Les codes V1/V1 NL-*/AK-*/TR-* sont multi-select sur les slots du parcours • Les 5 EV-* STANDARDS (DEM/AFE/AFA/EVJF/EVG) déclenchent 2 PACKS CRM (sauf EV-AUT cas par cas) EV-AUT (Autre) → le conseiller SOLY puise dans une bibliothèque interne back-office (13 packs sur-mesure) — liste détaillée dans MASTER_TAGS (famille EV-INTERNE) · référencée aussi dans MATCHING ⚠ EV-* (types d'événement) ≠ EVT-* (prestataires événementiel · voir onglet EVT) — NE PAS CONFONDRE
A36: ━━ AU · ACTIVITÉ · UNIVERS (7 codes) ━━ ACTIVITE AU CHOIX BLOC MATIN BLOC APRES MIDI ET BLOC ENFANTS
A37: FAMILLE | B37: CODE | C37: LIBELLÉ | D37: DESCRIPTION | E37: WEB | F37: ONB | G37: MOTEUR/CRM | H37: APP | I37: STATUT | J37: USAGE
A38: AU | B38: AU-EXC | C38: EXCURSION À LA JOURNÉE | D38: Sortie à la journée hors Marrakech · Destinations : Désert d'Agafay · Vallée de l'Ourika · Cascades d'Ouzoud · Essaouira · Imlil & Atlas · Aït Ben Haddou / Ouarzazate · Lac Lalla Takerkoust · Vallée des 3 Palmiers · 🌅 DÉPART MATINÉE — journée complète · ⚠ EXCLUSIF : désactive automatiquement les blocs DÉJEUNER + APRÈS-MIDI → seuls DÎNER + SOIRÉE restent sélectionnables · Transport + guide selon prestation | E38: ✓ | F38: ✓ | G38: ✓ | H38: – | I38: ✅ V1 | J38: Parcours web · Matching
A39: AU | B39: AU-DES | C39: DÉSERT & HORIZONS | E39: ✓ | F39: ✓ | G39: ✓ | H39: – | I39: ✅ V1 | J39: Parcours web · Matching
A40: AU | B40: AU-SPO | C40: SPORT & ÉNERGIE | D40: Golf · Yoga · Pilates · Padel · Tennis · Surf · Karting · Équitation · VTT · Escalade · Fitness · 🌅🌴 matin + après-midi | E40: ✓ | F40: ✓ | G40: ✓ | H40: – | I40: ✅ V1 | J40: Parcours web · Matching
A41: AU | B41: AU-CUL | C41: CULTURE & IMMERSION | D41: Jardin Majorelle · YSL · Bahia · Médersa · Souks · Cours de cuisine · Calligraphie · Palmeraie · Visite guidée médina · 🌅🌴 matin + après-midi | E41: ✓ | F41: ✓ | G41: ✓ | H41: – | I41: ✅ V1 | J41: Parcours web · Matching
A42: AU | B42: AU-BIE | C42: BIEN-ÊTRE & RELAXATION | D42: Spa · Hammam · Breathwork · Méditation · Massage · Rituel argan · Retraite bien-être · 🌅🌴 matin + après-midi | E42: ✓ | F42: ✓ | G42: ✓ | H42: – | I42: ✅ V1 | J42: Parcours web · Matching
A43: AU | B43: AU-ELI | C43: ÉLITE & SIGNATURE | D43: Montgolfière · hélicoptère · shooting · Jet privé · Yacht · Dîner étoilé privatisé · 🌅🌴 matin + après-midi | E43: ✓ | F43: ✓ | G43: ✓ | H43: – | I43: ✅ V1 | J43: Parcours web · Matching
A44: AU | B44: AU-FES | C44: FESTIF & LIFESTYLE | D44: Pool party · beach club · rooftop · Brunch festif · Sunset lounge · Soirée privée · 🌴 APRÈS-MIDI uniquement · transition vers la soirée | E44: ✓ | F44: ✓ | G44: ✓ | H44: – | I44: ✅ V1 | J44: Parcours web · Matching
A45: ━━ RA-D · RESTAURANT · DÉJEUNER (6 codes) ━━ EXPERIENCE SOUHAITEE
A46: FAMILLE | B46: CODE | C46: LIBELLÉ | D46: DESCRIPTION | E46: WEB | F46: ONB | G46: MOTEUR/CRM | H46: APP | I46: STATUT | J46: USAGE
A47: RA-D | B47: RA-DBR | C47: Brunch & art de vivre | D47: Chic · élégant · sans contrainte | E47: ✓ | F47: ✓ | G47: ✓ | H47: – | I47: ✅ V1 | J47: Parcours web · Matching
A48: RA-D | B48: RA-DLE | C48: Déjeuner léger & élégant | D48: Fluide · raffiné · discret | E48: ✓ | F48: ✓ | G48: ✓ | H48: – | I48: ✅ V1 | J48: Parcours web · Matching
A49: RA-D | B49: RA-DMA | C49: Déjeuner marocain d'exception | D49: Tradition · raffinement · immersion | E49: ✓ | F49: ✓ | G49: ✓ | H49: – | I49: ✅ V1 | J49: Parcours web · Matching
A50: RA-D | B50: RA-DPO | C50: Poolside & Lifestyle | D50: Soleil · détente · ambiance vibrante | E50: ✓ | F50: ✓ | G50: ✓ | H50: – | I50: ✅ V1 | J50: Parcours web · Matching
A51: RA-D | B51: RA-DNA | C51: Nature & Évasion | D51: Calme · nature · déconnexion | E51: ✓ | F51: ✓ | G51: ✓ | H51: – | I51: ✅ V1 | J51: Parcours web · Matching
A52: RA-D | B52: RA-DSI | C52: Expérience signature | D52: Ultra-luxe · service exceptionnel | E52: ✓ | F52: ✓ | G52: ✓ | H52: – | I52: ✅ V1 | J52: Parcours web · Matching
A53: ━━ RA-N · RESTAURANT · DÎNER (6 codes) ━━ EXPERIENCE SOUHAITEE
A54: FAMILLE | B54: CODE | C54: LIBELLÉ | D54: DESCRIPTION | E54: WEB | F54: ONB | G54: MOTEUR/CRM | H54: APP | I54: STATUT | J54: USAGE
A55: RA-N | B55: RA-NRO | C55: Dîner romantique | D55: Intime · lumière douce · moment suspendu | E55: ✓ | F55: ✓ | G55: ✓ | H55: – | I55: ✅ V1 | J55: Parcours web · Matching
A56: RA-N | B56: RA-NGA | C56: Dîner gastronomique | D56: Cuisine d'exception · élégance | E56: ✓ | F56: ✓ | G56: ✓ | H56: – | I56: ✅ V1 | J56: Parcours web · Matching
A57: RA-N | B57: RA-NSP | C57: Dîner spectacle | D57: Culture · animation · immersion | E57: ✓ | F57: ✓ | G57: ✓ | H57: – | I57: ✅ V1 | J57: Parcours web · Matching
A58: RA-N | B58: RA-NFE | C58: Dîner festif | D58: Musique · énergie · ambiance | E58: ✓ | F58: ✓ | G58: ✓ | H58: – | I58: ✅ V1 | J58: Parcours web · Matching
A59: RA-N | B59: RA-NVE | C59: Dîner vue & évasion | D59: Panorama · sunset · magie | E59: ✓ | F59: ✓ | G59: ✓ | H59: – | I59: ✅ V1 | J59: Parcours web · Matching
A60: RA-N | B60: RA-NAM | C60: Dîner ambiance marocaine | D60: Tradition · convivialité · saveurs marocaines | E60: ✓ | F60: ✓ | G60: ✓ | H60: – | I60: ✅ V1 | J60: Parcours web · Matching
A61: ━━ NL · SOIRÉE / NIGHTLIFE (5 codes · V1) ━━ BLOC AU CHOIX
A62: NL | B62: NL-CLU | C62: CLUB | D62: Club / boîte de nuit · ambiance dance · électro · hip-hop | E62: ✓ | F62: ✓ | G62: ✓ | H62: – | I62: ✅ V1 | J62: Parcours web · Matching
A63: NL | B63: NL-LOU | C63: LOUNGE | D63: Lounge / bar à cocktails · ambiance feutrée · mixologie | E63: ✓ | F63: ✓ | G63: ✓ | H63: – | I63: ✅ V1 | J63: Parcours web · Matching
A64: NL | B64: NL-SHO | C64: SHOW & CABARET | D64: Show / cabaret · troupe artistique · contenu CRM | E64: ✓ | F64: ✓ | G64: ✓ | H64: – | I64: ✅ V1 | J64: Parcours web · Matching
A65: NL | B65: NL-LIV | C65: LIVE MUSIC | D65: Concert live · musicien · groupe sur scène · contenu CRM | E65: ✓ | F65: ✓ | G65: ✓ | H65: – | I65: ✅ V1 | J65: Parcours web · Matching
A66: NL | B66: NL-IMM | C66: IMMERSION MAROCAINE | D66: Immersion locale (gnaoua · rituels nocturnes) | E66: ✓ | F66: ✓ | G66: ✓ | H66: – | I66: ✅ V1 | J66: Parcours web · Matching
A67: ━━ AK · ACTIVITÉS KIDS (5 codes · NOUVEAUX V1) ━━
A68: AK | B68: AK-CRE | C68: CRÉATIF & LUDIQUE | D68: Ateliers · artisanat · poterie · arts plastiques · Peinture · Musique · Théâtre | E68: ✓ | F68: ✓ | G68: ✓ | H68: – | I68: ✅ V1 | J68: Parcours web · Matching
A69: AK | B69: AK-DEC | C69: DÉCOUVERTE & APPRENTISSAGE | D69: Cuisine · culture · histoire · sciences ludiques · Ateliers scientifiques · Contes · Langues | E69: ✓ | F69: ✓ | G69: ✓ | H69: – | I69: ✅ V1 | J69: Parcours web · Matching
A70: AK | B70: AK-NAT | C70: NATURE & EXPLORATION | D70: Animaux · plein air · randonnée junior · découverte faune · Ferme pédagogique · Balade poney · Jardin | E70: ✓ | F70: ✓ | G70: ✓ | H70: – | I70: ✅ V1 | J70: Parcours web · Matching
A71: AK | B71: AK-LOI | C71: LOISIRS & ÉNERGIE | D71: Parcs · sports · piscine · jeux d'eau · Accrobranche · Karting junior · Trampoline | E71: ✓ | F71: ✓ | G71: ✓ | H71: – | I71: ✅ V1 | J71: Parcours web · Matching
A72: AK | B72: AK-SER | C72: SÉRÉNITÉ PARENTS | D72: Babysitting premium · garde d'enfants · nounou multilingue · Garde de nuit · Kids club hôtel | E72: ✓ | F72: ✓ | G72: ✓ | H72: – | I72: ✅ V1 | J72: Parcours web · Matching
A73: ━━ RG · RÉGIMES ALIMENTAIRES · contraintes client (2 codes · V1) ━━
A74: FAMILLE | B74: CODE | C74: LIBELLÉ | D74: DESCRIPTION | E74: WEB | F74: ONB | G74: MOTEUR/CRM | H74: APP | I74: STATUT | J74: USAGE
A75: RG | B75: RG-VEG | C75: Cuisine végétarienne | D75: Pas de viande/poisson | E75: ✓ | F75: ✓ | G75: ✓ | H75: – | I75: ✅ V1 | J75: Parcours web · Matching
A76: RG | B76: RG-ALG | C76: Allergies à signaler | D76: Allergènes à signaler au prestataire / au lieu | E76: ✓ | F76: ✓ | G76: ✓ | H76: – | I76: ✅ V1 | J76: Parcours web · Matching
A77: ━━ SE · SÉCURITÉ PRIVÉE (add-on choisi dans le DEVIS · étape 3) ━━
A78: FAMILLE | B78: CODE | C78: LIBELLÉ | D78: DESCRIPTION | E78: WEB | F78: ONB | G78: MOTEUR/CRM | H78: APP | I78: STATUT | J78: USAGE
A79: SE | B79: SE-SUR | C79: Surveillance de votre hébergement | D79: [CLIENT] Profil bas · observation à distance | E79: ✓ | F79: ✓ | G79: ✓ | H79: – | I79: ✓ client | J79: Parcours web · Matching
A80: SE | B80: SE-PRO | C80: Agent de protection discret | D80: [CLIENT] Agent en civil · garde rapprochée discrète | E80: ✓ | F80: ✓ | G80: ✓ | H80: – | I80: ✓ client | J80: Parcours web · Matching
A81: SE | B81: SE-FEM | C81: Agent de protection féminin | D81: [CLIENT] Agent femme · accompagnement discret | E81: ✓ | F81: ✓ | G81: ✓ | H81: – | I81: ✓ client | J81: Parcours web · Matching
A82: SE | B82: SE-24H | C82: Protection renforcée 24h/24 | D82: [CLIENT] Protection continue · roulement 24h/24 | E82: ✓ | F82: ✓ | G82: ✓ | H82: – | I82: ✓ client | J82: Parcours web · Matching
A83: SE | B83: SE-ETU | C83: Étude personnalisée | D83: [CLIENT] Évaluation des besoins · devis sur mesure | E83: ✓ | F83: ✓ | G83: ✓ | H83: – | I83: ✅ V1 | J83: Parcours web · Matching
A84: ━━━━━ ▼ BLOC CLIENT · ESPACE APP (après réservation) ━━━━━
A85: ━━ FID · PROGRAMME FIDÉLITÉ CLIENT (4 codes) ━━
A86: ⚙ DÉRIVÉ MOTEUR · calculé automatiquement · n'est PAS un choix client
A87: FAMILLE | B87: CODE | C87: LIBELLÉ | D87: DESCRIPTION | E87: WEB | F87: ONB | G87: MOTEUR/CRM | H87: APP | I87: STATUT | J87: USAGE
A88: FID | B88: FID-VOY | C88: VOYAGEUR | D88: Entrée libre · 0 pts · 1 demande/jour 9h-17h | E88: – | F88: – | G88: ✓ | H88: ✓ | I88: ✅ V1 | J88: Matching · App client
A89: FID | B89: FID-HAB | C89: HABITUÉ | D89: Automatique · 1 000 pts · 2 demandes/jour 9h-17h | E89: – | F89: – | G89: ✓ | H89: ✓ | I89: ✅ V1 | J89: Matching · App client
A90: FID | B90: FID-HOT | C90: HÔTE | D90: Automatique · 4 000 pts · 3 demandes/jour 9h-20h | E90: – | F90: – | G90: ✓ | H90: ✓ | I90: ✅ V1 | J90: Matching · App client
A91: FID | B91: FID-AMB | C91: AMBASSADEUR | D91: Sur invitation SOLY · 10 000 pts · demandes illimitées · 24h/24 | E91: – | F91: – | G91: ✓ | H91: ✓ | I91: ✅ V1 | J91: Matching · App client
A92: ━━ FB · FEEDBACK CLIENT (4 codes) ━━
A93: FAMILLE | B93: CODE | C93: LIBELLÉ | D93: DESCRIPTION | E93: WEB | F93: ONB | G93: MOTEUR/CRM | H93: APP | I93: STATUT | J93: USAGE
A94: FB | B94: FB-COM | C94: COMMENTAIRE LIBRE | D94: Analyse sémantique IA · détection signaux faibles | E94: – | F94: – | G94: ✓ | H94: ✓ | I94: ✅ V1 | J94: Matching · App client
A95: FB | B95: FB-SUG | C95: SUGGESTION | D95: Proposition d'amélioration | E95: – | F95: – | G95: ✓ | H95: ✓ | I95: ✅ V1 | J95: Matching · App client
A96: FB | B96: FB-PROB | C96: INCIDENT SIGNALÉ | D96: Réclamation ou problème rencontré | E96: – | F96: – | G96: ✓ | H96: ✓ | I96: ✅ V1 | J96: Matching · App client
A97: FB | B97: FB-COUP | C97: COUP DE CŒUR | D97: Moment marquant du séjour | E97: – | F97: – | G97: ✓ | H97: ✓ | I97: ✅ V1 | J97: Matching · App client
A98: ━━ NPS · ÉVALUATION POST-SÉJOUR CLIENT (4 codes) ━━
A99: ⚙ DÉRIVÉ MOTEUR · calculé automatiquement · n'est PAS un choix client
A100: FAMILLE | B100: CODE | C100: LIBELLÉ | D100: DESCRIPTION | E100: WEB | F100: ONB | G100: MOTEUR/CRM | H100: APP | I100: STATUT | J100: USAGE
...

Sheet REF_CODES
A1: 🧩 REF_CODES · MIROIR VIVANT de « 🔖 CODES DE RÉFÉRENCE » · LIBELLÉ (C) + DESCRIPTION (D) + CODE+LIBELLÉ (J) = formules XLOOKUP auto-synchronisées depuis la bible (toute modif de libellé/description dans la bible se répercute ici automatiquement). ⚠️ NE PAS éditer C/D/J à la main. Colonne CODE (B) FIGÉE = ancre des ~1759 lookups · ne pas réordonner/insérer/supprimer de lignes. Ajout/suppression de code dans la bible = resync manuel du code (B) + carte des plages ci-dessous (demandez-moi).
A2: FAMILLE | B2: CODE | C2: LIBELLÉ | D2: DESCRIPTION | E2: WEB | F2: ONB | G2: MOTEUR/CRM | H2: APP | I2: STATUT | J2: CODE + LIBELLÉ
A3: OR | B3: OR-ZEN | C3: {=XLOOKUP($B3,'🔖 CODES DE RÉFÉRENCE'!$B:$B,'🔖 CODES DE RÉFÉRENCE'!$C:$C,"")} -> ZEN & BIEN-ÊTRE | D3: {=XLOOKUP($B3,'🔖 CODES DE RÉFÉRENCE'!$B:$B,'🔖 CODES DE RÉFÉRENCE'!$D:$D,"")} -> Boost spa/yoga/healing · sérénité | E3: ✓ | F3: ✓ | G3: ✓ | H3: – | I3: ✅ V1 | J3: =$B3&" — "&$C3 -> OR-ZEN — ZEN & BIEN-ÊTRE
A4: OR | B4: OR-ROM | C4: {=XLOOKUP($B4,'🔖 CODES DE RÉFÉRENCE'!$B:$B,'🔖 CODES DE RÉFÉRENCE'!$C:$C,"")} -> ROMANTIQUE | D4: {=XLOOKUP($B4,'🔖 CODES DE RÉFÉRENCE'!$B:$B,'🔖 CODES DE RÉFÉRENCE'!$D:$D,"")} -> Boost suite privée · rooftop sunset · dîner désert | E4: ✓ | F4: ✓ | G4: ✓ | H4: – | I4: ✅ V1 | J4: =$B4&" — "&$C4 -> OR-ROM — ROMANTIQUE
A5: OR | B5: OR-FAM | C5: {=XLOOKUP($B5,'🔖 CODES DE RÉFÉRENCE'!$B:$B,'🔖 CODES DE RÉFÉRENCE'!$C:$C,"")} -> FAMILIAL | D5: {=XLOOKUP($B5,'🔖 CODES DE RÉFÉRENCE'!$B:$B,'🔖 CODES DE RÉFÉRENCE'!$D:$D,"")} -> Boost resort · villa · kids club | E5: ✓ | F5: ✓ | G5: ✓ | H5: – | I5: ✅ V1 | J5: =$B5&" — "&$C5 -> OR-FAM — FAMILIAL
A6: OR | B6: OR-FES | C6: {=XLOOKUP($B6,'🔖 CODES DE RÉFÉRENCE'!$B:$B,'🔖 CODES DE RÉFÉRENCE'!$C:$C,"")} -> FESTIF | D6: {=XLOOKUP($B6,'🔖 CODES DE RÉFÉRENCE'!$B:$B,'🔖 CODES DE RÉFÉRENCE'!$D:$D,"")} -> Boost villa privatisable · rooftop · DJ · nightlife | E6: ✓ | F6: ✓ | G6: ✓ | H6: – | I6: ✅ V1 | J6: =$B6&" — "&$C6 -> OR-FES — FESTIF
A7: OR | B7: OR-PRO | C7: {=XLOOKUP($B7,'🔖 CODES DE RÉFÉRENCE'!$B:$B,'🔖 CODES DE RÉFÉRENCE'!$C:$C,"")} -> PROFESSIONNEL | D7: {=XLOOKUP($B7,'🔖 CODES DE RÉFÉRENCE'!$B:$B,'🔖 CODES DE RÉFÉRENCE'!$D:$D,"")} -> Boost hôtel 5⁎ · palace · lounge business | E7: ✓ | F7: ✓ | G7: ✓ | H7: – | I7: ✅ V1 | J7: =$B7&" — "&$C7 -> OR-PRO — PROFESSIONNEL
A8: HB | B8: HB-HOT | C8: {=XLOOKUP($B8,'🔖 CODES DE RÉFÉRENCE'!$B:$B,'🔖 CODES DE RÉFÉRENCE'!$C:$C,"")} -> HOTEL & RESORT | D8: {=XLOOKUP($B8,'🔖 CODES DE RÉFÉRENCE'!$B:$B,'🔖 CODES DE RÉFÉRENCE'!$D:$D,"")} -> Hôtel 4⁎ · Hôtel 5⁎ · Resort | E8: ✓ | F8: ✓ | G8: ✓ | H8: – | I8: ✅ V1 | J8: =$B8&" — "&$C8 -> HB-HOT — HOTEL & RESORT
A9: HB | B9: HB-INC | C9: {=XLOOKUP($B9,'🔖 CODES DE RÉFÉRENCE'!$B:$B,'🔖 CODES DE RÉFÉRENCE'!$C:$C,"")} -> INCONTOURNABLE | D9: {=XLOOKUP($B9,'🔖 CODES DE RÉFÉRENCE'!$B:$B,'🔖 CODES DE RÉFÉRENCE'!$D:$D,"")} -> Palace · Relais & Châteaux · Boutique hôtel | E9: ✓ | F9: ✓ | G9: ✓ | H9: – | I9: ✅ V1 | J9: =$B9&" — "&$C9 -> HB-INC — INCONTOURNABLE
A10: HB | B10: HB-RIA | C10: {=XLOOKUP($B10,'🔖 CODES DE RÉFÉRENCE'!$B:$B,'🔖 CODES DE RÉFÉRENCE'!$C:$C,"")} -> RIAD & PATRIMOINE | D10: {=XLOOKUP($B10,'🔖 CODES DE RÉFÉRENCE'!$B:$B,'🔖 CODES DE RÉFÉRENCE'!$D:$D,"")} -> Riad · Palais d'hôtes | E10: ✓ | F10: ✓ | G10: ✓ | H10: – | I10: ✅ V1 | J10: =$B10&" — "&$C10 -> HB-RIA — RIAD & PATRIMOINE
A11: HB | B11: HB-COL | C11: {=XLOOKUP($B11,'🔖 CODES DE RÉFÉRENCE'!$B:$B,'🔖 CODES DE RÉFÉRENCE'!$C:$C,"")} -> COLLECTION PRIVÉE | D11: {=XLOOKUP($B11,'🔖 CODES DE RÉFÉRENCE'!$B:$B,'🔖 CODES DE RÉFÉRENCE'!$D:$D,"")} -> Riad privatisable · Villa privée · Domaine privé | E11: ✓ | F11: ✓ | G11: ✓ | H11: – | I11: ✅ V1 | J11: =$B11&" — "&$C11 -> HB-COL — COLLECTION PRIVÉE
A12: HB | B12: HB-NAT | C12: {=XLOOKUP($B12,'🔖 CODES DE RÉFÉRENCE'!$B:$B,'🔖 CODES DE RÉFÉRENCE'!$C:$C,"")} -> NATURE & HORIZON | D12: {=XLOOKUP($B12,'🔖 CODES DE RÉFÉRENCE'!$B:$B,'🔖 CODES DE RÉFÉRENCE'!$D:$D,"")} -> Desert Camp · Desert Resort · Lodge | E12: ✓ | F12: ✓ | G12: ✓ | H12: – | I12: ✅ V1 | J12: =$B12&" — "&$C12 -> HB-NAT — NATURE & HORIZON
A13: HB | B13: HB-SUR | C13: {=XLOOKUP($B13,'🔖 CODES DE RÉFÉRENCE'!$B:$B,'🔖 CODES DE RÉFÉRENCE'!$C:$C,"")} -> SUR MESURE ABSOLU | D13: {=XLOOKUP($B13,'🔖 CODES DE RÉFÉRENCE'!$B:$B,'🔖 CODES DE RÉFÉRENCE'!$D:$D,"")} -> MODE COMBINAISON : le client assemble 2 types d'hébergement OU PLUS sur le séjour (ex : riad médina + camp désert). N'est PAS un 6e type — voyage multi-lieux composé par SOLY. · IMPOSE automatiquement BG-LIBRE (le client ne choisit pas de tranche BG1–BG5). | E13: ✓ | F13: ✓ | G13: ✓ | H13: – | I13: ✅ V1 | J13: =$B13&" — "&$C13 -> HB-SUR — SUR MESURE ABSOLU
A14: BG | B14: BG1 | C14: {=XLOOKUP($B14,'🔖 CODES DE RÉFÉRENCE'!$B:$B,'🔖 CODES DE RÉFÉRENCE'!$C:$C,"")} -> Moins de 300 € | D14: {=XLOOKUP($B14,'🔖 CODES DE RÉFÉRENCE'!$B:$B,'🔖 CODES DE RÉFÉRENCE'!$D:$D,"")} -> Budget moyen / nuit / chambre | E14: ✓ | F14: ✓ | G14: ✓ | H14: – | I14: ✅ V1 | J14: =$B14&" — "&$C14 -> BG1 — Moins de 300 €
... A214: ZONE | B214: Z020 | C214: {=XLOOKUP($B214,'🔖 CODES DE RÉFÉRENCE'!$B:$B,'🔖 CODES DE RÉFÉRENCE'!$C:$C,"")} -> Aéroport Menara · Terminal 1 | D214: {=XLOOKUP($B214,'🔖 CODES DE RÉFÉRENCE'!$B:$B,'🔖 CODES DE RÉFÉRENCE'!$D:$D,"")} -> Aéroport | E214: – | F214: ✓ | G214: ✓ | H214: – | I214: 🆕 V1 | J214: =$B214&" — "&$C214 -> Z020 — Aéroport Menara · Terminal 1
A217: 🔒 CARTE DES PLAGES FIGÉES (ex-onglet PLAGES_REF_CODES) · ⚠️ ~1759 INDEX/MATCH pointent sur ces plages absolues · ne PAS insérer/supprimer de lignes dans REF_CODES sans resynchroniser cette carte. | G217: LISTE DÉROULANT ACTIVITES · D (AU 7 + AK 5 = 12)
A218: FAMILLE | B218: LIGNES | C218: NB CODES | D218: PLAGE CODE (col B) | E218: PLAGE LIBELLÉ (col C) | G218: =C27 -> DÉSERT & HORIZONS | H218: –
A219: OR | B219: 3-7 | C219: 5 | D219: $B$3:$B$7 | E219: $C$3:$C$7 | G219: =C28 -> SPORT & ÉNERGIE | H219: –
A220: HB | B220: 8-13 | C220: 6 | D220: $B$8:$B$13 | E220: $C$8:$C$13 | G220: =C29 -> CULTURE & IMMERSION | H220: –
A221: BG | B221: 14-19 | C221: 6 | D221: $B$14:$B$19 | E221: $C$14:$C$19 | G221: =C30 -> BIEN-ÊTRE & RELAXATION | H221: –
A222: EV | B222: 20-26 | C222: 7 | D222: $B$20:$B$26 | E222: $C$20:$C$26 | G222: =C31 -> ÉLITE & SIGNATURE | H222: –
A223: AU | B223: 27-33 | C223: 7 | D223: $B$27:$B$33 | E223: $C$27:$C$33 | G223: =C32 -> EXCURSION À LA JOURNÉE | H223: –
A224: RA-D | B224: 34-39 | C224: 6 | D224: $B$34:$B$39 | E224: $C$34:$C$39 | G224: =C33 -> FESTIF & LIFESTYLE | H224: –
A225: RA-N | B225: 40-45 | C225: 6 | D225: $B$40:$B$45 | E225: $C$40:$C$45 | G225: =C51 -> CRÉATIF & LUDIQUE | H225: –
A226: NL | B226: 46-50 | C226: 5 | D226: $B$46:$B$50 | E226: $C$46:$C$50 | G226: =C52 -> DÉCOUVERTE & APPRENTISSAGE | H226: –
A227: AK | B227: 51-55 | C227: 5 | D227: $B$51:$B$55 | E227: $C$51:$C$55 | G227: =C53 -> NATURE & EXPLORATION | H227: –
A228: RG | B228: 56-57 | C228: 2 | D228: $B$56:$B$57 | E228: $C$56:$C$57 | G228: =C54 -> LOISIRS & ÉNERGIE | H228: –
A229: TR | B229: 58-61 | C229: 4 | D229: $B$58:$B$61 | E229: $C$58:$C$61 | G229: =C55 -> SÉRÉNITÉ PARENTS | H229: –
A230: SE | B230: 62-66 | C230: 5 | D230: $B$62:$B$66 | E230: $C$62:$C$66 | G230: ✓ | H230: –
A231: FID | B231: 67-70 | C231: 4 | D231: $B$67:$B$70 | E231: $C$67:$C$70 | G231: ✓ | H231: –
A232: NPS | B232: 71-74 | C232: 4 | D232: $B$71:$B$74 | E232: $C$71:$C$74 | G232: ✓ | H232: –
A233: ST | B233: 75-77 | C233: 3 | D233: $B$75:$B$77 | E233: $C$75:$C$77 | G233: ✓ | H233: –
A234: AMB | B234: 78-82 | C234: 5 | D234: $B$78:$B$82 | E234: $C$78:$C$82 | G234: ✓ | H234: –
A235: KD | B235: 83-86 | C235: 4 | D235: $B$83:$B$86 | E235: $C$83:$C$86 | G235: ✓ | H235: –
A236: EVT | B236: 87-132 | C236: 46 | D236: $B$87:$B$132 | E236: $C$87:$C$132 | G236: ✓ | H236: –
A237: LABEL | B237: 133-141 | C237: 9 | D237: $B$133:$B$141 | E237: $C$133:$C$141 | G237: ✓ | H237: –
A238: EP | B238: 142-157 | C238: 16 | D238: $B$142:$B$157 | E238: $C$142:$C$157 | G238: ✓ | H238: –
A239: TV | B239: 158-160 | C239: 3 | D239: $B$158:$B$160 | E239: $C$158:$C$160 | G239: ✓ | H239: –
A240: ANC | B240: 161-162 | C240: 2 | D240: $B$161:$B$162 | E240: $C$161:$C$162 | G240: ✓ | H240: –
A241: LVL | B241: 163-167 | C241: 5 | D241: $B$163:$B$167 | E241: $C$163:$C$167 | G241: ✓ | H241: –
... A249: ZONE | B249: 195-214 | C249: 20 | D249: $B$195:$B$214 | E249: $C$195:$C$214 | G249: ✓ | H249: –
A250: TR | B250: TR-BER-TI | C250: {=XLOOKUP($B250,'🔖 CODES DE RÉFÉRENCE'!$B:$B,'🔖 CODES DE RÉFÉRENCE'!$C:$C,"")} -> Berline standard · Transfert interville | D250: {=XLOOKUP($B250,'🔖 CODES DE RÉFÉRENCE'!$B:$B,'🔖 CODES DE RÉFÉRENCE'!$D:$D,"")} -> Tarif indicatif : 25 € · par véhicule | G250: ✓ | H250: – | J250: =$B250&" — "&$C250 -> TR-BER-TI — Berline standard · Transfert interville
A251: TR | B251: TR-BER-DM | C251: {=XLOOKUP($B251,'🔖 CODES DE RÉFÉRENCE'!$B:$B,'🔖 CODES DE RÉFÉRENCE'!$C:$C,"")} -> Berline standard · Demi-journée | D251: {=XLOOKUP($B251,'🔖 CODES DE RÉFÉRENCE'!$B:$B,'🔖 CODES DE RÉFÉRENCE'!$D:$D,"")} -> Tarif indicatif : 80 € · par véhicule | G251: ✓ | H251: – | J251: =$B251&" — "&$C251 -> TR-BER-DM — Berline standard · Demi-journée
A252: TR | B252: TR-BER-JC | C252: {=XLOOKUP($B252,'🔖 CODES DE RÉFÉRENCE'!$B:$B,'🔖 CODES DE RÉFÉRENCE'!$C:$C,"")} -> Berline standard · Journée complète | D252: {=XLOOKUP($B252,'🔖 CODES DE RÉFÉRENCE'!$B:$B,'🔖 CODES DE RÉFÉRENCE'!$D:$D,"")} -> Tarif indicatif : 150 € · par véhicule | G252: ✓ | H252: – | J252: =$B252&" — "&$C252 -> TR-BER-JC — Berline standard · Journée complète
A253: TR | B253: TR-BEL-TI | C253: {=XLOOKUP($B253,'🔖 CODES DE RÉFÉRENCE'!$B:$B,'🔖 CODES DE RÉFÉRENCE'!$C:$C,"")} -> Berline luxe · Transfert interville | D253: {=XLOOKUP($B253,'🔖 CODES DE RÉFÉRENCE'!$B:$B,'🔖 CODES DE RÉFÉRENCE'!$D:$D,"")} -> Tarif indicatif : 45 € · par véhicule | G253: ✓ | H253: – | J253: =$B253&" — "&$C253 -> TR-BEL-TI — Berline luxe · Transfert interville
A254: TR | B254: TR-BEL-DM | C254: {=XLOOKUP($B254,'🔖 CODES DE RÉFÉRENCE'!$B:$B,'🔖 CODES DE RÉFÉRENCE'!$C:$C,"")} -> Berline luxe · Demi-journée | D254: {=XLOOKUP($B254,'🔖 CODES DE RÉFÉRENCE'!$B:$B,'🔖 CODES DE RÉFÉRENCE'!$D:$D,"")} -> Tarif indicatif : 150 € · par véhicule | G254: ✓ | H254: – | J254: =$B254&" — "&$C254 -> TR-BEL-DM — Berline luxe · Demi-journée
A255: TR | B255: TR-BEL-JC | C255: {=XLOOKUP($B255,'🔖 CODES DE RÉFÉRENCE'!$B:$B,'🔖 CODES DE RÉFÉRENCE'!$C:$C,"")} -> Berline luxe · Journée complète | D255: {=XLOOKUP($B255,'🔖 CODES DE RÉFÉRENCE'!$B:$B,'🔖 CODES DE RÉFÉRENCE'!$D:$D,"")} -> Tarif indicatif : 280 € · par véhicule | G255: ✓ | H255: – | J255: =$B255&" — "&$C255 -> TR-BEL-JC — Berline luxe · Journée complète
A256: TR | B256: TR-VAN-TI | C256: {=XLOOKUP($B256,'🔖 CODES DE RÉFÉRENCE'!$B:$B,'🔖 CODES DE RÉFÉRENCE'!$C:$C,"")} -> Van premium · Transfert interville | D256: {=XLOOKUP($B256,'🔖 CODES DE RÉFÉRENCE'!$B:$B,'🔖 CODES DE RÉFÉRENCE'!$D:$D,"")} -> Tarif indicatif : 45 € · par véhicule | G256: ✓ | H256: – | J256: =$B256&" — "&$C256 -> TR-VAN-TI — Van premium · Transfert interville
A257: TR | B257: TR-VAN-DM | C257: {=XLOOKUP($B257,'🔖 CODES DE RÉFÉRENCE'!$B:$B,'🔖 CODES DE RÉFÉRENCE'!$C:$C,"")} -> Van premium · Demi-journée | D257: {=XLOOKUP($B257,'🔖 CODES DE RÉFÉRENCE'!$B:$B,'🔖 CODES DE RÉFÉRENCE'!$D:$D,"")} -> Tarif indicatif : 120 € · par véhicule | G257: ✓ | H257: – | J257: =$B257&" — "&$C257 -> TR-VAN-DM — Van premium · Demi-journée
A258: TR | B258: TR-VAN-JC | C258: {=XLOOKUP($B258,'🔖 CODES DE RÉFÉRENCE'!$B:$B,'🔖 CODES DE RÉFÉRENCE'!$C:$C,"")} -> Van premium · Journée complète | D258: {=XLOOKUP($B258,'🔖 CODES DE RÉFÉRENCE'!$B:$B,'🔖 CODES DE RÉFÉRENCE'!$D:$D,"")} -> Tarif indicatif : 220 € · par véhicule | G258: ✓ | H258: – | J258: =$B258&" — "&$C258 -> TR-VAN-JC — Van premium · Journée complète
A259: TR | B259: TR-SUV-TI | C259: {=XLOOKUP($B259,'🔖 CODES DE RÉFÉRENCE'!$B:$B,'🔖 CODES DE RÉFÉRENCE'!$C:$C,"")} -> SUV luxe · Transfert interville | D259: {=XLOOKUP($B259,'🔖 CODES DE RÉFÉRENCE'!$B:$B,'🔖 CODES DE RÉFÉRENCE'!$D:$D,"")} -> Tarif indicatif : 60 € · par véhicule | G259: ✓ | H259: – | J259: =$B259&" — "&$C259 -> TR-SUV-TI — SUV luxe · Transfert interville
A260: TR | B260: TR-SUV-DM | C260: {=XLOOKUP($B260,'🔖 CODES DE RÉFÉRENCE'!$B:$B,'🔖 CODES DE RÉFÉRENCE'!$C:$C,"")} -> SUV luxe · Demi-journée | D260: {=XLOOKUP($B260,'🔖 CODES DE RÉFÉRENCE'!$B:$B,'🔖 CODES DE RÉFÉRENCE'!$D:$D,"")} -> Tarif indicatif : 180 € · par véhicule | G260: ✓ | H260: – | J260: =$B260&" — "&$C260 -> TR-SUV-DM — SUV luxe · Demi-journée
A261: TR | B261: TR-SUV-JC | C261: {=XLOOKUP($B261,'🔖 CODES DE RÉFÉRENCE'!$B:$B,'🔖 CODES DE RÉFÉRENCE'!$C:$C,"")} -> SUV luxe · Journée complète | D261: {=XLOOKUP($B261,'🔖 CODES DE RÉFÉRENCE'!$B:$B,'🔖 CODES DE RÉFÉRENCE'!$D:$D,"")} -> Tarif indicatif : 350 € · par véhicule | G261: ✓ | H261: – | J261: =$B261&" — "&$C261 -> TR-SUV-JC — SUV luxe · Journée complète
A262: TR | B262: TR-MIN | C262: {=XLOOKUP($B262,'🔖 CODES DE RÉFÉRENCE'!$B:$B,'🔖 CODES DE RÉFÉRENCE'!$C:$C,"")} -> Minibus (type Sprinter · ~15 pax) | D262: {=XLOOKUP($B262,'🔖 CODES DE RÉFÉRENCE'!$B:$B,'🔖 CODES DE RÉFÉRENCE'!$D:$D,"")} -> Minibus avec chauffeur pour groupes · tarifs à valider (code créé en V2 sur validation) | G262: ✓ | H262: – | I262: ✅ V2 | J262: =$B262&" — "&$C262 -> TR-MIN — Minibus (type Sprinter · ~15 pax)

Sheet MASTER_TAGS
A1: 🏷️ MASTER_TAGS · tags de matching mutualisés · alignés sur 🔖 CODES DE RÉFÉRENCE (bible) · ✅ V1 vérifié
A2: FAMILLE | B2: NOM FAMILLE | C2: CODE | D2: LIBELLÉ | E2: TYPE MATCHING | F2: ONGLETS | G2: CODE + LIBELLÉ | H2: → ÉQUIV. BIBLE / ARBITRAGE
A3: PUBLIC | B3: Occupation cible / publics | C3: PUB-ADU | D3: Adultes uniquement | E3: filtre + tri | F3: TOUS | G3: PUB-ADU · Adultes uniquement
A4: PUBLIC | B4: Occupation cible / publics | C4: PUB-CPL | D4: Couple | E4: filtre + tri | F4: TOUS | G4: PUB-CPL · Couple
A5: PUBLIC | B5: Occupation cible / publics | C5: PUB-FAM | D5: Famille | E5: filtre + tri | F5: TOUS | G5: PUB-FAM · Famille
A6: PUBLIC | B6: Occupation cible / publics | C6: PUB-GRP | D6: Groupe | E6: filtre + tri | F6: TOUS | G6: PUB-GRP · Groupe
A7: PUBLIC | B7: Occupation cible / publics | C7: PUB-PRO | D7: Professionnel | E7: filtre + tri | F7: TOUS | G7: PUB-PRO · Professionnel
A8: PUBLIC | B8: Occupation cible / publics | C8: PUB-SOL | D8: Solo | E8: filtre + tri | F8: TOUS | G8: PUB-SOL · Solo
A9: AMB | B9: Ambiance | C9: AMB-ROM | D9: ROMANTIQUE | E9: tri (scoring) | F9: HEB·RES·ACT·ESP·POI | G9: AMB-ROM · ROMANTIQUE
A10: AMB | B10: Ambiance | C10: AMB-ZEN | D10: ZEN & BIEN-ÊTRE | E10: tri (scoring) | F10: HEB·RES·ACT·ESP·POI | G10: AMB-ZEN · ZEN & BIEN-ÊTRE | H10: ✕ Incompatible avec AMB-FES (zen vs festif) · règle reportée de la bible
A11: AMB | B11: Ambiance | C11: AMB-FES | D11: FESTIF | E11: tri (scoring) | F11: HEB·RES·ACT·ESP·POI | G11: AMB-FES · FESTIF | H11: ✕ Incompatible avec AMB-ZEN (festif vs zen) · règle reportée de la bible
A12: AMB | B12: Ambiance | C12: AMB-PRO | D12: PROFESSIONNEL | E12: tri (scoring) | F12: HEB·RES·ACT·ESP·POI | G12: AMB-PRO · PROFESSIONNEL
A13: AMB | B13: Ambiance | C13: AMB-FAM | D13: FAMILIAL | E13: tri (scoring) | F13: HEB·RES·ACT·ESP·POI | G13: AMB-FAM · FAMILIAL
A14: OR | B14: Esprit du séjour (client) | C14: OR-ZEN | D14: ZEN & BIEN-ÊTRE | E14: tri (scoring) | F14: HEB·RES·ACT·POI | G14: OR-ZEN · ZEN & BIEN-ÊTRE
A15: OR | B15: Esprit du séjour (client) | C15: OR-ROM | D15: ROMANTIQUE | E15: tri (scoring) | F15: HEB·RES·ACT·POI | G15: OR-ROM · ROMANTIQUE
A16: OR | B16: Esprit du séjour (client) | C16: OR-FAM | D16: FAMILIAL | E16: tri (scoring) | F16: HEB·RES·ACT·POI | G16: OR-FAM · FAMILIAL
A17: OR | B17: Esprit du séjour (client) | C17: OR-FES | D17: FESTIF | E17: tri (scoring) | F17: HEB·RES·ACT·POI | G17: OR-FES · FESTIF
A18: OR | B18: Esprit du séjour (client) | C18: OR-PRO | D18: PROFESSIONNEL | E18: tri (scoring) | F18: HEB·RES·ACT·POI | G18: OR-PRO · PROFESSIONNEL
A19: BG | B19: Budget | C19: BG1 | D19: Moins de 300 € | E19: filtre dur | F19: HEB·HB-COL·RES·ESP | G19: BG1 · Moins de 300 €
A20: BG | B20: Budget | C20: BG2 | D20: 300 – 500 € | E20: filtre dur | F20: HEB·HB-COL·RES·ESP | G20: BG2 · 300 – 500 €
A21: BG | B21: Budget | C21: BG3 | D21: 500 – 800 € | E21: filtre dur | F21: HEB·HB-COL·RES·ESP | G21: BG3 · 500 – 800 €
A22: BG | B22: Budget | C22: BG4 | D22: 800 – 1 200 € | E22: filtre dur | F22: HEB·HB-COL·RES·ESP | G22: BG4 · 800 – 1 200 €
A23: BG | B23: Budget | C23: BG5 | D23: 1 200 € et + | E23: filtre dur | F23: HEB·HB-COL·RES·ESP | G23: BG5 · 1 200 € et +
... A30: ACCÈS | B30: Type d'accès au lieu | C30: ACC-PRV | D30: Privatisable / sur demande | E30: filtre | F30: HEBERGEMENT·RESTAURANT·ACTIVITES·POI·SOIREE·ESPACES | G30: ACC-PRV · Privatisable / sur demande
A31: CONTRAINTE | B31: Contraintes opérationnelles | C31: NO_SMOKING | D31: Non-fumeur strict | E31: filtre dur | F31: HEB·RES·ESP | G31: NO_SMOKING · Non-fumeur strict | H31: Attribut lieu (moteur) · hors bible · pas d'équivalent client
A32: CONTRAINTE | B32: Contraintes opérationnelles | C32: NO_ALCOHOL_PUB | D32: Alcool en privé uniquement | E32: filtre dur | F32: HEB·RES·ESP | G32: NO_ALCOHOL_PUB · Alcool en privé uniquement | H32: Attribut lieu : le lieu sert de l'alcool en privé uniquement (le client ne le voit pas en public).
A33: CONTRAINTE | B33: Contraintes opérationnelles | C33: NO_LATE_MUSIC | D33: Musique limitée après 23h | E33: filtre dur | F33: HEB·RES·ESP | G33: NO_LATE_MUSIC · Musique limitée après 23h | H33: Attribut lieu (moteur) · hors bible · contrainte sonore
A34: CONTRAINTE | B34: Contraintes opérationnelles | C34: NPH | D34: Politique « no photo » | E34: filtre dur | F34: HEB·RES·ESP | G34: NPH · Politique « no photo » | H34: Attribut lieu (moteur) · hors bible · politique discrétion
A35: CONTRAINTE | B35: Contraintes opérationnelles | C35: NEIGH_SENSITIVE | D35: Voisinage sensible | E35: filtre dur | F35: HEB·RES·ESP | G35: NEIGH_SENSITIVE · Voisinage sensible | H35: Attribut lieu (moteur) · hors bible · contrainte voisinage
A36: CONTRAINTE | B36: Contraintes opérationnelles | C36: ACC_PMR | D36: Accès PMR / Handicap | E36: filtre dur | F36: HEB·RES·ESP | G36: ACC_PMR · Accès PMR / Handicap | H36: Attribut lieu (moteur) · hors bible · accessibilité PMR (candidat filtre futur)
A37: USAGE_EVT | B37: Usages événementiels | C37: ANNIV_FAM | D37: Anniversaire familial | E37: filtre | F37: HEB·ESP·EVT | G37: ANNIV_FAM · Anniversaire familial | H37: EV-AFA · Anniversaire familial (client)
A38: USAGE_EVT | B38: Usages événementiels | C38: ANNIV_FES | D38: Anniversaire festif | E38: filtre | F38: HEB·ESP·EVT | G38: ANNIV_FES · Anniversaire festif | H38: EV-AFE · Anniversaire festif (client)
A39: USAGE_EVT | B39: Usages événementiels | C39: ART_EVT | D39: Événement artistique | E39: filtre | F39: HEB·ESP·EVT | G39: ART_EVT · Événement artistique | H39: EV-AUT · cas par cas (pas de standard)
A40: USAGE_EVT | B40: Usages événementiels | C40: COCKTAIL | D40: Cocktail & réception | E40: filtre | F40: HEB·ESP·EVT | G40: COCKTAIL · Cocktail & réception | H40: EV-NET · Networking (back-office)
A41: USAGE_EVT | B41: Usages événementiels | C41: COHESION | D41: Cohésion d'équipe | E41: filtre | F41: HEB·ESP·EVT | G41: COHESION · Cohésion d'équipe | H41: EV-SEM · Séminaire (back-office)
A42: USAGE_EVT | B42: Usages événementiels | C42: DEFILE | D42: Défilé / présentation | E42: filtre | F42: HEB·ESP·EVT | G42: DEFILE · Défilé / présentation | H42: EV-AUT · cas par cas
... A55: USAGE_EVT | B55: Usages événementiels | C55: TOURNAGE | D55: Tournage & production | E55: filtre | F55: HEB·ESP·EVT | G55: TOURNAGE · Tournage & production | H55: EV-AUT · cas par cas
A56: CANAL | B56: Canaux de réservation | C56: DIRECT | D56: Direct | E56: info | F56: TOUS | G56: DIRECT · Direct
A57: CANAL | B57: Canaux de réservation | C57: BOOKING | D57: Booking.com | E57: info | F57: TOUS | G57: BOOKING · Booking.com
A58: CANAL | B58: Canaux de réservation | C58: AIRBNB | D58: Airbnb | E58: info | F58: TOUS | G58: AIRBNB · Airbnb
A59: CANAL | B59: Canaux de réservation | C59: EXPEDIA | D59: Expedia | E59: info | F59: TOUS | G59: EXPEDIA · Expedia
A60: CANAL | B60: Canaux de réservation | C60: BKG_AIR | D60: Booking + Airbnb | E60: info | F60: TOUS | G60: BKG_AIR · Booking + Airbnb
A61: LVL | B61: Qualification · cloches | C61: LVL-1 | D61: 🔔 UNE CLOCHE | E61: tri | F61: TOUS | G61: LVL-1 · 🔔 UNE CLOCHE
A62: LVL | B62: Qualification · cloches | C62: LVL-2 | D62: 🔔🔔 DEUX CLOCHES | E62: tri | F62: TOUS | G62: LVL-2 · 🔔🔔 DEUX CLOCHES
A63: LVL | B63: Qualification · cloches | C63: LVL-3 | D63: 🔔🔔🔔 TROIS CLOCHES | E63: tri | F63: TOUS | G63: LVL-3 · 🔔🔔🔔 TROIS CLOCHES
A64: LVL | B64: Qualification · cloches | C64: LVL-4 | D64: 🔔🔔🔔🔔 QUATRE CLOCHES | E64: tri | F64: TOUS | G64: LVL-4 · 🔔🔔🔔🔔 QUATRE CLOCHES
A65: LVL | B65: Qualification · cloches | C65: LVL-5 | D65: 🔔🔔🔔🔔🔔 CINQ CLOCHES | E65: tri | F65: TOUS | G65: LVL-5 · 🔔🔔🔔🔔🔔 CINQ CLOCHES
A66: STATUT | B66: Cycle de vie prestataire | C66: STATUT-DEV | D66: DÉVERSÉ | E66: gestion | F66: TOUS | G66: STATUT-DEV · DÉVERSÉ
A67: STATUT | B67: Cycle de vie prestataire | C67: STATUT-EVA | D67: EN ÉVALUATION | E67: gestion | F67: TOUS | G67: STATUT-EVA · EN ÉVALUATION
... A156: EV-INTERNE | B156: Pack interne back-office (déclenché par EV-AUT · puisé par le conseiller SOLY) | C156: EV-VOW | D156: Renouvellement vœux | E156: back-office CRM (sur-mesure · pas de tag de tri) | F156: CRM · conseiller (hors onglets data) | G156: EV-VOW · Renouvellement vœux
A157: SE-OPER | B157: Sécurité opérationnelle (auto-injectée par le PACK ÉVÉNEMENT · grille tarifs) | C157: SE-ESC | D157: Escorte / accompagnement rapproché | E157: back-office / opérationnel (pas de tag de tri) | F157: Pack CRM · devis (hors onglets data) | G157: SE-ESC · Escorte / accompagnement rapproché | H157: Hors bible (couche opérationnelle) · auto-injecté si EV-* coché
A158: SE-OPER | B158: Sécurité opérationnelle (auto-injectée par le PACK ÉVÉNEMENT · grille tarifs) | C158: SE-EVE | D158: Sécurité événementielle | E158: back-office / opérationnel (pas de tag de tri) | F158: Pack CRM · devis (hors onglets data) | G158: SE-EVE · Sécurité événementielle | H158: Hors bible (couche opérationnelle) · auto-injecté si EV-* coché
A159: SE-OPER | B159: Sécurité opérationnelle (auto-injectée par le PACK ÉVÉNEMENT · grille tarifs) | C159: SE-MUL | D159: Dispositif multi-sites | E159: back-office / opérationnel (pas de tag de tri) | F159: Pack CRM · devis (hors onglets data) | G159: SE-MUL · Dispositif multi-sites | H159: Hors bible (couche opérationnelle) · auto-injecté si EV-* coché
A160: HB | B160: Type d'hébergement | C160: =MATCHING!B10 -> HB-HOT | D160: =MATCHING!C10 -> HOTEL & RESORT | E160: filtre (type) | F160: HEBERGEMENT | G160: =C160&" · "&D160 -> HB-HOT · HOTEL & RESORT | H160: ← MATCHING ét.1 (1.5.2) · single-select type hébergement
A161: HB | B161: Type d'hébergement | C161: =MATCHING!B11 -> HB-INC | D161: =MATCHING!C11 -> INCONTOURNABLE | E161: filtre (type) | F161: HEBERGEMENT | G161: =C161&" · "&D161 -> HB-INC · INCONTOURNABLE | H161: ← MATCHING ét.1 (1.5.2)
A162: HB | B162: Type d'hébergement | C162: =MATCHING!B12 -> HB-RIA | D162: =MATCHING!C12 -> RIAD & PATRIMOINE | E162: filtre (type) | F162: HEBERGEMENT | G162: =C162&" · "&D162 -> HB-RIA · RIAD & PATRIMOINE | H162: ← MATCHING ét.1 (1.5.2)
A163: HB | B163: Type d'hébergement | C163: =MATCHING!B13 -> HB-COL | D163: =MATCHING!C13 -> COLLECTION PRIVÉE | E163: filtre (type) | F163: HEBERGEMENT | G163: =C163&" · "&D163 -> HB-COL · COLLECTION PRIVÉE | H163: ← MATCHING ét.1 (1.5.2)
A164: HB | B164: Type d'hébergement | C164: =MATCHING!B14 -> HB-NAT | D164: =MATCHING!C14 -> NATURE & HORIZON | E164: filtre (type) | F164: HEBERGEMENT | G164: =C164&" · "&D164 -> HB-NAT · NATURE & HORIZON | H164: ← MATCHING ét.1 (1.5.2)
A165: HB | B165: Type d'hébergement | C165: =MATCHING!B15 -> HB-SUR | D165: =MATCHING!C15 -> SUR MESURE ABSOLU | E165: filtre (combinaison) | F165: HEBERGEMENT | G165: =C165&" · "&D165 -> HB-SUR · SUR MESURE ABSOLU | H165: ← MATCHING ét.1 · multi-lieux composé par SOLY (pas un 6e type)
A166: EV | B166: Usage événementiel (client) | C166: =MATCHING!B23 -> EV-DEM | D166: =MATCHING!C23 -> DEMANDE EN MARIAGE | E166: filtre + tri + pack | F166: HEB·ESP·EVT | G166: =C166&" · "&D166 -> EV-DEM · DEMANDE EN MARIAGE | H166: → bible DEM_MAR · déverse 2 PACKS CRM
A167: EV | B167: Usage événementiel (client) | C167: =MATCHING!B24 -> EV-AFE | D167: =MATCHING!C24 -> ANNIVERSAIRE FESTIF | E167: filtre + tri + pack | F167: HEB·ESP·EVT | G167: =C167&" · "&D167 -> EV-AFE · ANNIVERSAIRE FESTIF | H167: → bible ANNIV_FES · déverse 2 PACKS CRM
A168: EV | B168: Usage événementiel (client) | C168: =MATCHING!B25 -> EV-AFA | D168: =MATCHING!C25 -> ANNIVERSAIRE FAMILIAL | E168: filtre + tri + pack | F168: HEB·ESP·EVT | G168: =C168&" · "&D168 -> EV-AFA · ANNIVERSAIRE FAMILIAL | H168: → bible ANNIV_FAM · seul EV ouvrant le choix nb d'enfants
A169: EV | B169: Usage événementiel (client) | C169: =MATCHING!B26 -> EV-EVJF | D169: =MATCHING!C26 -> EVJF | E169: filtre + tri + pack | F169: HEB·ESP·EVT | G169: =C169&" · "&D169 -> EV-EVJF · EVJF | H169: → bible EVJF · déverse 2 PACKS CRM
A170: EV | B170: Usage événementiel (client) | C170: =MATCHING!B27 -> EV-EVG | D170: =MATCHING!C27 -> EVG | E170: filtre + tri + pack | F170: HEB·ESP·EVT | G170: =C170&" · "&D170 -> EV-EVG · EVG | H170: → bible EVG · déverse 2 PACKS CRM
A171: EV | B171: Usage événementiel (client) | C171: =MATCHING!B28 -> EV-AUT | D171: =MATCHING!C28 -> AUTRE | E171: filtre (libre) | F171: HEB·ESP·EVT | G171: =C171&" · "&D171 -> EV-AUT · AUTRE | H171: Catégorie parente · pas de pack · conseiller puise biblio EV-* back-office
A172: AU | B172: Activité matinée / après-midi | C172: =MATCHING!B30 -> AU-DES | D172: =MATCHING!C30 -> DÉSERT & HORIZONS | E172: filtre + tri | F172: ACTIVITES·POI | G172: =C172&" · "&D172 -> AU-DES · DÉSERT & HORIZONS | H172: ← MATCHING ét.2 (2.4 matinée) · multi-select
A173: AU | B173: Activité matinée / après-midi | C173: =MATCHING!B31 -> AU-SPO | D173: =MATCHING!C31 -> SPORT & ÉNERGIE | E173: filtre + tri | F173: ACTIVITES·POI | G173: =C173&" · "&D173 -> AU-SPO · SPORT & ÉNERGIE | H173: ← MATCHING ét.2 (2.4)
A174: AU | B174: Activité matinée / après-midi | C174: =MATCHING!B32 -> AU-CUL | D174: =MATCHING!C32 -> CULTURE & IMMERSION | E174: filtre + tri | F174: ACTIVITES·POI | G174: =C174&" · "&D174 -> AU-CUL · CULTURE & IMMERSION | H174: ← MATCHING ét.2 (2.4)
A175: AU | B175: Activité matinée / après-midi | C175: =MATCHING!B33 -> AU-BIE | D175: =MATCHING!C33 -> BIEN-ÊTRE & RELAXATION | E175: filtre + tri | F175: ACTIVITES·POI | G175: =C175&" · "&D175 -> AU-BIE · BIEN-ÊTRE & RELAXATION | H175: ← MATCHING ét.2 (2.4)
A176: AU | B176: Activité matinée / après-midi | C176: =MATCHING!B34 -> AU-ELI | D176: =MATCHING!C34 -> ÉLITE & SIGNATURE | E176: filtre + tri | F176: ACTIVITES·POI | G176: =C176&" · "&D176 -> AU-ELI · ÉLITE & SIGNATURE | H176: ← MATCHING ét.2 (2.4)
A177: AU | B177: Activité matinée / après-midi | C177: =MATCHING!B35 -> AU-EXC | D177: =MATCHING!C35 -> EXCURSION À LA JOURNÉE | E177: filtre + tri · EXCLUSIF | F177: ACTIVITES·POI | G177: =C177&" · "&D177 -> AU-EXC · EXCURSION À LA JOURNÉE | H177: Exclusif : occupe la matinée, désactive 2.5 déjeuner + 2.6 après-midi
A178: AU | B178: Activité matinée / après-midi | C178: =MATCHING!B43 -> AU-FES | D178: =MATCHING!C43 -> FESTIF & LIFESTYLE | E178: filtre + tri | F178: ACTIVITES·POI | G178: =C178&" · "&D178 -> AU-FES · FESTIF & LIFESTYLE | H178: ← MATCHING ét.2 (2.6 après-midi) · transition vers la soirée
A179: RA-D | B179: Restauration · déjeuner | C179: =MATCHING!B36 -> RA-DBR | D179: =MATCHING!C36 -> Brunch & art de vivre | E179: filtre + tri | F179: RESTAURANT | G179: =C179&" · "&D179 -> RA-DBR · Brunch & art de vivre | H179: ← MATCHING ét.2 (2.5 déjeuner) · multi-select
A180: RA-D | B180: Restauration · déjeuner | C180: =MATCHING!B37 -> RA-DLE | D180: =MATCHING!C37 -> Déjeuner léger & élégant | E180: filtre + tri | F180: RESTAURANT | G180: =C180&" · "&D180 -> RA-DLE · Déjeuner léger & élégant | H180: ← MATCHING ét.2 (2.5)
A181: RA-D | B181: Restauration · déjeuner | C181: =MATCHING!B38 -> RA-DMA | D181: =MATCHING!C38 -> Déjeuner marocain d'exception | E181: filtre + tri | F181: RESTAURANT | G181: =C181&" · "&D181 -> RA-DMA · Déjeuner marocain d'exception | H181: ← MATCHING ét.2 (2.5)
A182: RA-D | B182: Restauration · déjeuner | C182: =MATCHING!B39 -> RA-DPO | D182: =MATCHING!C39 -> Poolside & Lifestyle | E182: filtre + tri | F182: RESTAURANT | G182: =C182&" · "&D182 -> RA-DPO · Poolside & Lifestyle | H182: ← MATCHING ét.2 (2.5)
A183: RA-D | B183: Restauration · déjeuner | C183: =MATCHING!B40 -> RA-DNA | D183: =MATCHING!C40 -> Nature & Évasion | E183: filtre + tri | F183: RESTAURANT | G183: =C183&" · "&D183 -> RA-DNA · Nature & Évasion | H183: ← MATCHING ét.2 (2.5)
A184: RA-D | B184: Restauration · déjeuner | C184: =MATCHING!B41 -> RA-DSI | D184: =MATCHING!C41 -> Expérience signature | E184: filtre + tri | F184: RESTAURANT | G184: =C184&" · "&D184 -> RA-DSI · Expérience signature | H184: ← MATCHING ét.2 (2.5)
A185: RA-N | B185: Restauration · dîner | C185: =MATCHING!B44 -> RA-NRO | D185: =MATCHING!C44 -> Dîner romantique | E185: filtre + tri | F185: RESTAURANT | G185: =C185&" · "&D185 -> RA-NRO · Dîner romantique | H185: ← MATCHING ét.2 (2.7 dîner) · multi-select
A186: RA-N | B186: Restauration · dîner | C186: =MATCHING!B45 -> RA-NGA | D186: =MATCHING!C45 -> Dîner gastronomique | E186: filtre + tri | F186: RESTAURANT | G186: =C186&" · "&D186 -> RA-NGA · Dîner gastronomique | H186: ← MATCHING ét.2 (2.7)
A187: RA-N | B187: Restauration · dîner | C187: =MATCHING!B46 -> RA-NSP | D187: =MATCHING!C46 -> Dîner spectacle | E187: filtre + tri | F187: RESTAURANT | G187: =C187&" · "&D187 -> RA-NSP · Dîner spectacle | H187: ← MATCHING ét.2 (2.7)
A188: RA-N | B188: Restauration · dîner | C188: =MATCHING!B47 -> RA-NFE | D188: =MATCHING!C47 -> Dîner festif | E188: filtre + tri | F188: RESTAURANT | G188: =C188&" · "&D188 -> RA-NFE · Dîner festif | H188: ← MATCHING ét.2 (2.7)
A189: RA-N | B189: Restauration · dîner | C189: =MATCHING!B48 -> RA-NAM | D189: =MATCHING!C48 -> Dîner ambiance marocaine | E189: filtre + tri | F189: RESTAURANT | G189: =C189&" · "&D189 -> RA-NAM · Dîner ambiance marocaine | H189: ← MATCHING ét.2 (2.7)
A190: RA-N | B190: Restauration · dîner | C190: =MATCHING!B49 -> RA-NVE | D190: =MATCHING!C49 -> Dîner vue & évasion | E190: filtre + tri | F190: RESTAURANT | G190: =C190&" · "&D190 -> RA-NVE · Dîner vue & évasion | H190: ← MATCHING ét.2 (2.7)
A191: NL | B191: Soirée / nightlife | C191: =MATCHING!B50 -> NL-CLU | D191: =MATCHING!C50 -> CLUB | E191: filtre + tri | F191: SOIREE NIGHTLIFE | G191: =C191&" · "&D191 -> NL-CLU · CLUB | H191: ← MATCHING ét.2 (2.8 soirée) · multi-select
A192: NL | B192: Soirée / nightlife | C192: =MATCHING!B51 -> NL-LOU | D192: =MATCHING!C51 -> LOUNGE | E192: filtre + tri | F192: SOIREE NIGHTLIFE | G192: =C192&" · "&D192 -> NL-LOU · LOUNGE | H192: ← MATCHING ét.2 (2.8)
A193: NL | B193: Soirée / nightlife | C193: =MATCHING!B52 -> NL-SHO | D193: =MATCHING!C52 -> SHOW & CABARET | E193: filtre + tri | F193: SOIREE NIGHTLIFE | G193: =C193&" · "&D193 -> NL-SHO · SHOW & CABARET | H193: ← MATCHING ét.2 (2.8)
A194: NL | B194: Soirée / nightlife | C194: =MATCHING!B53 -> NL-LIV | D194: =MATCHING!C53 -> LIVE MUSIC | E194: filtre + tri | F194: SOIREE NIGHTLIFE | G194: =C194&" · "&D194 -> NL-LIV · LIVE MUSIC | H194: ← MATCHING ét.2 (2.8)
A195: NL | B195: Soirée / nightlife | C195: =MATCHING!B54 -> NL-IMM | D195: =MATCHING!C54 -> IMMERSION MAROCAINE | E195: filtre + tri | F195: SOIREE NIGHTLIFE | G195: =C195&" · "&D195 -> NL-IMM · IMMERSION MAROCAINE | H195: ← MATCHING ét.2 (2.8)
A196: AK | B196: Activité enfants | C196: =MATCHING!B55 -> AK-CRE | D196: =MATCHING!C55 -> CRÉATIF & LUDIQUE | E196: filtre + tri | F196: ACTIVITES | G196: =C196&" · "&D196 -> AK-CRE · CRÉATIF & LUDIQUE | H196: ← MATCHING ét.2 (2.9 enfants) · nb_enfants > 0
... A202: RG | B202: Régime / contrainte alimentaire | C202: =MATCHING!B61 -> RG-ALG | D202: =MATCHING!C61 -> Allergies à signaler | E202: filtre (info) | F202: RESTAURANT | G202: =C202&" · "&D202 -> RG-ALG · Allergies à signaler | H202: Non éliminatoire · signalement au prestataire
A203: TR | B203: Transport (add-on devis) | C203: =MATCHING!B63 -> TR-BER | D203: =MATCHING!C63 -> Berline incluse | E203: suggéré d'office | F203: TRANSPORT | G203: =C203&" · "&D203 -> TR-BER · Berline incluse | H203: ≈ gamme MASTER BER_E · inclus par défaut
A204: TR | B204: Transport (add-on devis) | C204: =MATCHING!B64 -> TR-BEL | D204: =MATCHING!C64 -> Berline luxe (+100 €/j) | E204: upgrade devis | F204: TRANSPORT | G204: =C204&" · "&D204 -> TR-BEL · Berline luxe (+100 €/j) | H204: ≈ gamme MASTER BER_S
A205: TR | B205: Transport (add-on devis) | C205: =MATCHING!B65 -> TR-SUV | D205: =MATCHING!C65 -> SUV premium (+150 €/j) | E205: upgrade devis | F205: TRANSPORT | G205: =C205&" · "&D205 -> TR-SUV · SUV premium (+150 €/j) | H205: ≈ gamme MASTER SUV
A206: TR | B206: Transport (add-on devis) | C206: =MATCHING!B66 -> TR-VAN | D206: =MATCHING!C66 -> Van premium (+200 €/j) | E206: upgrade devis | F206: TRANSPORT | G206: =C206&" · "&D206 -> TR-VAN · Van premium (+200 €/j) | H206: ≈ gamme MASTER VC (V-Class)
A207: POI | B207: Point d'intérêt | C207: ='🔖 CODES DE RÉFÉRENCE'!B253 -> Z007 | D207: ='🔖 CODES DE RÉFÉRENCE'!C253 -> Hivernage · Avenue Mohammed VI | E207: tri | F207: POI | G207: =C207&" · "&D207 -> Z007 · Hivernage · Avenue Mohammed VI | H207: ← 🔖 CODES DE RÉFÉRENCE B261 (BIBLE V1) · famille POI canonique
A208: POI | B208: Point d'intérêt | C208: ='🔖 CODES DE RÉFÉRENCE'!B254 -> Z008 | D208: ='🔖 CODES DE RÉFÉRENCE'!C254 -> Gueliz · Centre-ville | E208: tri | F208: POI | G208: =C208&" · "&D208 -> Z008 · Gueliz · Centre-ville | H208: ← 🔖 CODES DE RÉFÉRENCE B262 (BIBLE V1)
A209: POI | B209: Point d'intérêt | C209: ='🔖 CODES DE RÉFÉRENCE'!B255 -> Z009 | D209: ='🔖 CODES DE RÉFÉRENCE'!C255 -> Gueliz · Hassan II | E209: tri | F209: POI | G209: =C209&" · "&D209 -> Z009 · Gueliz · Hassan II | H209: ← 🔖 CODES DE RÉFÉRENCE B263 (BIBLE V1)
A210: POI | B210: Point d'intérêt | C210: ='🔖 CODES DE RÉFÉRENCE'!B256 -> Z010 | D210: ='🔖 CODES DE RÉFÉRENCE'!C256 -> Palmeraie · Circuit principal | E210: tri | F210: POI | G210: =C210&" · "&D210 -> Z010 · Palmeraie · Circuit principal | H210: ← 🔖 CODES DE RÉFÉRENCE B264 (BIBLE V1)
A211: POI | B211: Point d'intérêt | C211: ='🔖 CODES DE RÉFÉRENCE'!B257 -> Z011 | D211: ='🔖 CODES DE RÉFÉRENCE'!C257 -> Palmeraie · Route de Fès | E211: tri | F211: POI | G211: =C211&" · "&D211 -> Z011 · Palmeraie · Route de Fès | H211: ← 🔖 CODES DE RÉFÉRENCE B265 (BIBLE V1)
...

Sheet MATCHING
A1: 🎯 MATCHING · table remappée sur 🔖 CODES DE RÉFÉRENCE + 🌐 PARCOURS WEB · spécification d'ENTRÉE du futur MOTEUR · tags nus · codes manquants = ⚠ à créer
A2: FAMILLE | B2: CODE CLIENT | C2: LIBELLÉ | D2: TYPE | E2: SLOT / ÉTAPE | F2: FILTRE DUR (élimine) | G2: TAGS DE TRI (scoring · nus) | H2: RÈGLE MÉTIER | I2: Δ vs V1 / NOTE
A3: ═══ ÉTAPE 1 · CONFIGURATION DU SÉJOUR ═══
A4: COMPOSITION | B4: « pour N » | C4: Taille du groupe | D4: filtre dur + tri | E4: 1.2 composition | F4: capacité ≥ N | G4: PUB-SOL / PUB-CPL / PUB-FAM / PUB-GRP (selon compo) | H4: Dérive TV-SOL(1)/TV-CPL(2)/TV-GRP(≥3). PUB-GRP si N≥3. nb_enfants>0 → PUB-FAM + ouvre slot 2.9. | I4: Δ PUB-GRP conditionné au seuil N≥3 (V1: appliqué quel que soit N).
A5: OR · esprit | B5: OR-ZEN | C5: ZEN & BIEN-ÊTRE | D5: tri (scoring global) | E5: 1.4 esprit | F5: — | G5: AMB-ZEN · SPA · HAM_TRA · YOG_OUT | H5: Single-select obligatoire. Boost sur tout le séjour (HEB·RES·ACT·POI). | I5: Δ amenities passées en ⚠ à créer (pas d'attribut lieu dans la bible).
A6: OR · esprit | B6: OR-ROM | C6: ROMANTIQUE | D6: tri (scoring global) | E6: 1.4 esprit | F6: — | G6: AMB-ROM · PUB-CPL · TER · BAR_RTP | H6: Boost global.
A7: OR · esprit | B7: OR-FAM | C7: FAMILIAL | D7: tri (scoring global) | E7: 1.4 esprit | F7: — | G7: AMB-FAM · PUB-FAM · KD-CLB · BAB | H7: Boost global.
A8: OR · esprit | B8: OR-FES | C8: FESTIF | D8: tri (scoring global) | E8: 1.4 esprit | F8: — | G8: AMB-FES · PUB-GRP · DJ · CLU · POO_CLU | H8: Boost global. ⚠ AMB-FES ✕ AMB-ZEN incompatibles (règle bible) → pénalité croisée.
A9: OR · esprit | B9: OR-PRO | C9: PROFESSIONNEL | D9: tri (scoring global) | E9: 1.4 esprit | F9: — | G9: AMB-PRO · PUB-PRO | H9: Boost global.
A10: HB · héberg. | B10: HB-HOT | C10: HOTEL & RESORT | D10: filtre (type) | E10: 1.5.2 atmosphère | F10: type hébergement = HB-HOT | G10: ST-* · AMB-* (selon OR) | H10: Single-select. N'apparaît que si prise en charge héberg. = OUI. | I10: Δ 6 codes complets (V1: 1 seul « HB-HOT… »).
A11: HB · héberg. | B11: HB-INC | C11: INCONTOURNABLE | D11: filtre (type) | E11: 1.5.2 | F11: type hébergement = HB-INC | G11: ST-* · AMB-* (selon OR) | H11: Single-select.
A12: HB · héberg. | B12: HB-RIA | C12: RIAD & PATRIMOINE | D12: filtre (type) | E12: 1.5.2 | F12: type hébergement = HB-RIA | G12: ST-* · AMB-* (selon OR) | H12: Single-select.
A13: HB · héberg. | B13: HB-COL | C13: COLLECTION PRIVÉE | D13: filtre (type) | E13: 1.5.2 | F13: type hébergement = HB-COL | G13: ST-* · AMB-* (selon OR) | H13: Single-select.
A14: HB · héberg. | B14: HB-NAT | C14: NATURE & HORIZON | D14: filtre (type) | E14: 1.5.2 | F14: type hébergement = HB-NAT | G14: ST-* · AMB-* (selon OR) | H14: Single-select.
A15: HB · héberg. | B15: HB-SUR | C15: SUR MESURE ABSOLU | D15: filtre (combinaison) | E15: 1.5.2 | F15: combinaison ≥ 2 types d'hébergement | G15: ST-SIG · ST-ULT · ACC-PRV | H15: Mode multi-lieux (ex : riad médina + camp désert) composé par SOLY. N'est PAS un 6e type. · IMPOSE automatiquement BG-LIBRE (le client ne choisit pas de tranche BG1–BG5).
A16: BG · budget | B16: BG1 | C16: Moins de 300 € | D16: filtre dur | E16: 1.5.3 | F16: prix/nuit/chambre ≤ 300 € | G16: — | H16: Prix/nuit/chambre.
A17: BG · budget | B17: BG2 | C17: 300 – 500 € | D17: filtre dur | E17: 1.5.3 | F17: 300 < prix ≤ 500 | G17: — | H17: Prix/nuit/chambre.
A18: BG · budget | B18: BG3 | C18: 500 – 800 € | D18: filtre dur | E18: 1.5.3 | F18: 500 < prix ≤ 800 | G18: — | H18: Prix/nuit/chambre.
A19: BG · budget | B19: BG4 | C19: 800 – 1 200 € | D19: filtre dur | E19: 1.5.3 | F19: 800 < prix ≤ 1 200 | G19: — | H19: Prix/nuit/chambre.
A20: BG · budget | B20: BG5 | C20: 1 200 € et + | D20: filtre dur | E20: 1.5.3 | F20: prix/nuit/chambre ≥ 1 200 € | G20: ST-SIG · ST-ULT | H20: Prix/nuit/chambre.
A21: BG · budget | B21: BG-LIBRE | C21: SUR MESURE | D21: tri SEULEMENT | E21: 1.5.3 | F21: AUCUNE élimination · disponible UNIQUEMENT si HB-SUR | G21: ST-SIG · ST-ULT · ACC-PRV | H21: RÉSERVÉ à HB-SUR : jamais croisé avec un hébergement classique (HB-HOT/INC/RIA/COL/NAT). Sous HB-SUR, aucun filtre budget — SOLY compose le multi-lieux. Boost premium léger. | I21: Δ RÈGLE — BG-LIBRE ⟺ HB-SUR (couplage exclusif). Classiques → BG1–BG5 obligatoire. Anti-set-vide géré dans le chemin HB-SUR.
A22: ═══ ÉTAPE 2 · VOTRE EXPÉRIENCE ═══
A23: EV · événement | B23: EV-DEM | C23: DEMANDE EN MARIAGE | D23: filtre + tri + pack | E23: 2.1.1 | F23: usage = DEM_MAR · exactement 2 adultes | G23: AMB-ROM · ACC-PRV | H23: Cas exception (pas de mini 5). Déverse 2 PACKS CRM (fermés). Pack injecte SE-/EVT-/EP- via moteur.
A24: EV · événement | B24: EV-AFE | C24: ANNIVERSAIRE FESTIF | D24: filtre + tri + pack | E24: 2.1.1 | F24: usage = ANNIV_FES · ≥ 5 adultes (obligatoire · blocage dur) | G24: AMB-FES | H24: Déverse 2 PACKS CRM. | I24: Δ ajouté (split anniversaire V86).
A25: EV · événement | B25: EV-AFA | C25: ANNIVERSAIRE FAMILIAL | D25: filtre + tri + pack | E25: 2.1.1 | F25: usage = ANNIV_FAM · ≥ 5 adultes (obligatoire · blocage dur) | G25: AMB-FAM | H25: SEUL EV ouvrant le choix du nb d'enfants. Déverse 2 PACKS CRM. | I25: Δ ajouté (split V86).
A26: EV · événement | B26: EV-EVJF | C26: EVJF | D26: filtre + tri + pack | E26: 2.1.1 | F26: usage = EVJF · ≥ 5 adultes (obligatoire · blocage dur) | G26: AMB-FES | H26: Déverse 2 PACKS CRM.
A27: EV · événement | B27: EV-EVG | C27: EVG | D27: filtre + tri + pack | E27: 2.1.1 | F27: usage = EVG · ≥ 5 adultes (obligatoire · blocage dur) | G27: AMB-FES | H27: Déverse 2 PACKS CRM. | I27: Δ ajouté.
A28: EV · événement | B28: EV-AUT | C28: AUTRE | D28: filtre (libre) | E28: 2.1.1 | F28: usage libre (champ « à décrire ») | G28: — | H28: Pas de pack CRM. SOLY Assistance 24h. Conseiller puise biblio interne (EV-SEM/GALA/DES/DIN/NET/BAB/MAR/BAP/FIA/ANV/RET/REU/VOW). Parcours non bloqué. EV-ANN = catégorie parente, pas un choix terminal.
A29: EV · règle | B29: — | C29: Règle moteur quota | D29: règle | E29: 2.1.1 | F29: — | G29: — | H29: IF nb_adultes_étape1 < 5 (hors EV-DEM) → PACK INDISPONIBLE (blocage dur) · événement masqué/désactivé · message « Événement accessible à partir de 5 participants ». SEULE EXCEPTION : EV-DEM = 2 adultes.
A30: AU · matinée | B30: AU-DES | C30: DÉSERT & HORIZONS | D30: filtre + tri | E30: 2.4 matinée | F30: slot = matinée | G30: POI-VUE · QUA · BGY · DRM · AST | H30: Multi-select.
A31: AU · matinée | B31: AU-SPO | C31: SPORT & ÉNERGIE | D31: filtre + tri | E31: 2.4 matinée | F31: slot = matinée | G31: AU-SPO · YOG_OUT | H31: Multi-select. | I31: Δ ajouté (absent V1).
A32: AU · matinée | B32: AU-CUL | C32: CULTURE & IMMERSION | D32: filtre + tri | E32: 2.4 matinée | F32: slot = matinée | G32: AMB-ZEN · POI-VIS · POI-IMM | H32: Multi-select.
A33: AU · matinée | B33: AU-BIE | C33: BIEN-ÊTRE & RELAXATION | D33: filtre + tri | E33: 2.4 matinée | F33: slot = matinée | G33: AMB-ZEN · SPA · HAM_TRA · YOG_OUT | H33: Multi-select.
A34: AU · matinée | B34: AU-ELI | C34: ÉLITE & SIGNATURE | D34: filtre + tri | E34: 2.4 matinée | F34: slot = matinée | G34: ST-SIG · ST-ULT · AU-ELI | H34: Multi-select. | I34: Δ ajouté.
A35: AU · matinée | B35: AU-EXC | C35: EXCURSION À LA JOURNÉE | D35: filtre + tri · EXCLUSIF | E35: 2.4 matinée | F35: slot = matinée · DÉSACTIVE 2.5 + 2.6 | G35: AGA · 4X4 | H35: Exclusif : ne restent accessibles que dîner (2.7) + soirée (2.8). | I35: Δ règle exclusivité précisée.
A36: RA-D · déjeuner | B36: RA-DBR | C36: Brunch & art de vivre | D36: filtre + tri | E36: 2.5 déjeuner | F36: slot = déjeuner | G36: TER · BAR_POO | H36: Multi-select · RESTAURANT.
A37: RA-D · déjeuner | B37: RA-DLE | C37: Déjeuner léger & élégant | D37: filtre + tri | E37: 2.5 | F37: slot = déjeuner | G37: ST-SIG | H37: Multi-select. | I37: Δ ajouté.
A38: RA-D · déjeuner | B38: RA-DMA | C38: Déjeuner marocain d'exception | D38: filtre + tri | E38: 2.5 | F38: slot = déjeuner | G38: AMB-ZEN · RA-DMA | H38: Multi-select.
A39: RA-D · déjeuner | B39: RA-DPO | C39: Poolside & Lifestyle | D39: filtre + tri | E39: 2.5 | F39: slot = déjeuner | G39: POO_CLU · BCH_CLU · BAR_POO | H39: Multi-select.
A40: RA-D · déjeuner | B40: RA-DNA | C40: Nature & Évasion | D40: filtre + tri | E40: 2.5 | F40: slot = déjeuner | G40: POI-VUE · TER | H40: Multi-select. | I40: Δ ajouté.
A41: RA-D · déjeuner | B41: RA-DSI | C41: Expérience signature | D41: filtre + tri | E41: 2.5 | F41: slot = déjeuner | G41: ST-SIG · ST-ULT | H41: Multi-select. | I41: Δ ajouté.
A42: AU · après-midi | B42: AU-DES/SPO/CUL/BIE/ELI | C42: (idem matinée 2.4) | D42: filtre + tri | E42: 2.6 après-midi | F42: slot = après-midi | G42: (mêmes tags que 2.4) | H42: Multi-select. AU-EXC ABSENT ici (matinée only).
A43: AU · après-midi | B43: AU-FES | C43: FESTIF & LIFESTYLE | D43: filtre + tri | E43: 2.6 après-midi | F43: slot = après-midi | G43: POO_CLU · BCH_CLU · BAR_RTP · DJ_LOU | H43: Multi-select. Transition vers la soirée. | I43: Δ ajouté.
A44: RA-N · dîner | B44: RA-NRO | C44: Dîner romantique | D44: filtre + tri | E44: 2.7 dîner | F44: slot = dîner | G44: AMB-ROM · TER · BAR_RTP | H44: Multi-select · RESTAURANT.
A45: RA-N · dîner | B45: RA-NGA | C45: Dîner gastronomique | D45: filtre + tri | E45: 2.7 | F45: slot = dîner | G45: ST-SIG · ST-ULT | H45: Multi-select. | I45: Δ ajouté.
A46: RA-N · dîner | B46: RA-NSP | C46: Dîner spectacle | D46: filtre + tri | E46: 2.7 | F46: slot = dîner | G46: NL-SHO | H46: Multi-select. | I46: Δ ajouté.
A47: RA-N · dîner | B47: RA-NFE | C47: Dîner festif | D47: filtre + tri | E47: 2.7 | F47: slot = dîner | G47: AMB-FES · DJ | H47: Multi-select. | I47: Δ ajouté.
A48: RA-N · dîner | B48: RA-NAM | C48: Dîner ambiance marocaine | D48: filtre + tri | E48: 2.7 | F48: slot = dîner | G48: AMB-ZEN · RA-NAM | H48: Multi-select. | I48: Δ ajouté (V86).
A49: RA-N · dîner | B49: RA-NVE | C49: Dîner vue & évasion | D49: filtre + tri | E49: 2.7 | F49: slot = dîner | G49: POI-VUE · BAR_RTP · TER | H49: Multi-select.
A50: NL · soirée | B50: NL-CLU | C50: CLUB | D50: filtre + tri | E50: 2.8 soirée | F50: slot = soirée | G50: AMB-FES · CLU · DJ | H50: Multi-select.
A51: NL · soirée | B51: NL-LOU | C51: LOUNGE | D51: filtre + tri | E51: 2.8 | F51: slot = soirée | G51: AMB-ROM · BAR_LOU · DJ_LOU | H51: Multi-select.
A52: NL · soirée | B52: NL-SHO | C52: SHOW & CABARET | D52: filtre + tri | E52: 2.8 | F52: slot = soirée | G52: NL-SHO | H52: Multi-select. | I52: Δ ajouté.
A53: NL · soirée | B53: NL-LIV | C53: LIVE MUSIC | D53: filtre + tri | E53: 2.8 | F53: slot = soirée | G53: NL-LIV | H53: Multi-select. | I53: Δ ajouté.
A54: NL · soirée | B54: NL-IMM | C54: IMMERSION MAROCAINE | D54: filtre + tri | E54: 2.8 | F54: slot = soirée | G54: AMB-ZEN · NL-IMM | H54: Multi-select. | I54: Δ famille complétée → 5 codes.
A55: AK · enfants | B55: AK-CRE | C55: CRÉATIF & LUDIQUE | D55: filtre + tri | E55: 2.9 (cond.) | F55: slot = enfants · nb_enfants > 0 | G55: KD-ACT · ART_ATE | H55: Multi-select.
A56: AK · enfants | B56: AK-DEC | C56: DÉCOUVERTE & APPRENTISSAGE | D56: filtre + tri | E56: 2.9 | F56: nb_enfants > 0 | G56: KD-ACT | H56: Multi-select. | I56: Δ ajouté.
A57: AK · enfants | B57: AK-NAT | C57: NATURE & EXPLORATION | D57: filtre + tri | E57: 2.9 | F57: nb_enfants > 0 | G57: AK-NAT | H57: Multi-select. | I57: Δ ajouté.
A58: AK · enfants | B58: AK-LOI | C58: LOISIRS & ÉNERGIE | D58: filtre + tri | E58: 2.9 | F58: nb_enfants > 0 | G58: KD-CLB · KD-PIS · POO_CLU | H58: Multi-select. | I58: Δ ajouté.
A59: AK · enfants | B59: AK-SER | C59: SÉRÉNITÉ PARENTS | D59: filtre + tri | E59: 2.9 | F59: nb_enfants > 0 | G59: BAB | H59: Multi-select. | I59: Δ famille complétée → 5 codes.
A60: RG · régimes | B60: RG-VEG | C60: Cuisine végétarienne | D60: filtre dur | E60: 2.5 / 2.7 | F60: exige VENUE_VEGETARIAN · option végétarienne au menu | G60: — | H60: Filtre dur : exige l'attribut lieu VENUE_VEGETARIAN (créé dans MASTER_TAGS). Garde anti-set-vide légère (la plupart des lieux proposent une option). | I60: Δ attribut VENUE_VEGETARIAN créé (miroir MASTER_TAGS)
A61: RG · régimes | B61: RG-ALG | C61: Allergies à signaler | D61: filtre (info) | E61: 2.5 / 2.7 | F61: — (non éliminatoire) | G61: — | H61: Transmission au presta via feuille de route (niv. 3). Pas un filtre dur. | I61: Δ reclassé info.
A62: ═══ ÉTAPE 3 · DEVIS (add-ons) ═══
A63: TR · transport | B63: TR-BER | C63: Berline incluse | D63: suggéré d'office | E63: 3 devis | F63: — | G63: — | H63: Suggéré d'office au devis SAUF gestion_transport = CLIENT_GERE (2.11 masquée). | I63: Δ FIX retiré si client gère son transport.
A64: TR · transport | B64: TR-BEL | C64: Berline luxe (+100 €/j) | D64: upgrade devis | E64: 3 | F64: — | G64: — | H64: Upgrade proposé au devis.
A65: TR · transport | B65: TR-SUV | C65: SUV premium (+150 €/j) | D65: upgrade devis | E65: 3 | F65: — | G65: — | H65: Upgrade.
A66: TR · transport | B66: TR-VAN | C66: Van premium (+200 €/j) | D66: upgrade devis | E66: 3 | F66: — | G66: — | H66: Upgrade.
A67: SE · sécurité | B67: SE-PRO/FEM/SUR/24H/ETU | C67: Sécurité privée | D67: add-on devis | E67: 3 | F67: — | G67: — | H67: Saisie dans le devis. ⚠ Aucune famille de matching « sécurité privée » → à créer pour scorer/chiffrer. | I67: Δ déplacé en étape 3.
A68: SE · sécurité | B68: SE-ESC/EVE/MUL | C68: Sécurité événementielle | D68: auto-injecté (pack EV) | E68: 3 / moteur | F68: — | G68: — | H68: Auto-injectés par le PACK ÉVÉNEMENT si EV-* coché. ⚠ Codes opérationnels hors bible (grille tarifs) — désormais définis dans MASTER_TAGS (famille SE-OPER).
A70: 📖 LÉGENDE & DOCTRINE — comment lire cette table
A71: Sources | B71: Remappé sur 🔖 CODES DE RÉFÉRENCE (bible) + 🌐 PARCOURS WEB uniquement.
A72: Statut MOTEUR | B72: Le moteur n'existe pas encore : cette table est sa SPÉCIFICATION D'ENTRÉE, pas un reflet de ses formules.
A73: MASTER_TAGS | B73: N'est PAS la source ici. Les tags d'équipement deviennent des CIBLES, pas une contrainte.
A74: TYPE — filtre dur | B74: Élimine les fiches presta non conformes (capacité, budget, type, slot, régime).
A75: TYPE — tri | B75: Scoring : remonte les fiches conformes, n'élimine personne.
A76: TYPE — filtre + tri | B76: Filtre le slot/usage PUIS score à l'intérieur.
A77: TYPE — règle | B77: Logique de parcours (gating, quotas, exclusivité).
A78: Tags nus | B78: Tags de tri listés sans poids ni n° de score. Pondération = travail du moteur, ultérieur.
A79: Attributs lieu | B79: Végétarien = RG-VEG (→ attribut VENUE_VEGETARIAN) · allergies = RG-ALG (signalement). Équipements = tags de tri dans MASTER_TAGS. Aucun code inventé dans la bible.
A80: — CORRECTIONS INTÉGRÉES (vs MATCHING V1) —
A81: SUR MESURE | B81: Filtre dur ≥1200 € → SUPPRIMÉ. « Sur mesure » = neutre, scoring premium léger. Évite le set vide.
A83: AU-EXC | B83: Exclusivité : occupe la matinée, désactive 2.5 déjeuner + 2.6 après-midi ; restent dîner + soirée.
A84: Familles complétées | B84: NL-* (2→5), AK-* (1→5), AU-SPO/AU-ELI ajoutés, RA-D*/RA-N* complets, EV-AFE/AFA/EVG ajoutés, HB-* (1→6).
A85: « pour N » | B85: PUB-GRP appliqué seulement si N≥3 (ne biaise plus un couple vers des lieux de groupe).
A86: TR-BER | B86: Plus suggéré d'office si gestion_transport = CLIENT_GERE.
A87: RG-ALG | B87: Reclassé en filtre info (signalement presta), pas filtre dur.
A88: RESTE À FOURNIR | B88: L'onglet MOTEUR (scores, pondérations, bandes LVL, coef NPS, table inclusion EV) — à construire À PARTIR de cette table.

Sheet MOTEUR
A1: ⚙️ MOTEUR · spécification de calcul SOLÝVENTS — séquencée sur le 🌐 PARCOURS WEB (Étapes 1→4) · V2
A2: 📜 DOCTRINE · Le moteur suit le déroulé du parcours web. BLOC 0 (hors parcours) pré-qualifie chaque prestataire à l'onboarding (note intrinsèque → cloches LVL). Puis, à mesure que le client avance, le moteur applique les FILTRES DURS (éliminent) et le TRI (points, n'éliminent jamais) propres à chaque étape. Cellules JAUNES = seuls paramètres éditables.
A3: PIPELINE ▸ BLOC 0 Note intrinsèque /5 → cloches LVL │ ÉTAPE 1 filtres cadrage + tri esprit → ÉTAPE 2 filtres expériences + tri + packs EV → ÉTAPE 3 transport/sécurité/devis → ÉTAPE 4 classement final (note × coef NPS + Σ tri) + honoraires SOLÝ
A5: ═══ BLOC 0 · PRÉ-QUALIFICATION PRESTATAIRE (onboarding · hors parcours client) → note intrinsèque /5 & cloches LVL ═══
A6: Chaque score est noté 0–5 par le moteur à partir de la colonne source de la fiche. Note finale = Σ(score × poids)/100 (sur l'échelle 0–5 car Σ poids = 100). Les poids (jaune) sont éditables. Cette note est indépendante de la requête client — elle est calculée une fois, à l'onboarding.
A7: SCORE | B7: LIBELLÉ | C7: SOURCE (fiche / bible) | D7: RÈGLE DE NOTATION 0–5 | E7: ÉCHELLE | F7: POIDS % | G7: DÉTAIL / BARÈME INDICATIF
A8: M1 | B8: STANDING | C8: Col. STANDING (ST) · bible ST-PRE/SIG/ULT | D8: Mappage standing → note | E8: 0–5 | F8: 15 | G8: ST-ULT=5 · ST-SIG=4 · ST-PRE=3 · non renseigné=2
A9: M2 | B9: RATINGS plateformes | C9: Col. PLATEFORMES (RATING) · Google/Trip/Booking/Airbnb | D9: Moyenne pondérée des notes normalisées /5 (Booking /10 → /5), pondérée par nb d'avis (log) | E9: 0–5 | F9: 15 | G9: note_norm × min(1 ; log10(1+avis)/3) · multi-plateformes = moyenne
A10: M3 | B10: LABELS & DISTINCTIONS | C10: Bible LABEL-* (Relais&Châteaux, Michelin Key, Virtuoso, LHW…) | D10: +1 par label majeur, plafonné à 5 | E10: 0–5 | F10: 10 | G10: 0 label=0 · 1=2 · 2=3,5 · 3=4,5 · 4+=5
A11: M4 | B11: ANCIENNETÉ / RÉPUTATION | C11: Col. ANCIENNETÉ (ANC) · bible ANC-INST/ANC-NEW | D11: Institution = valeur sûre ; nouveau spot = potentiel | E11: 0–5 | F11: 6 | G11: ANC-INST=5 · standard=3 · ANC-NEW=3 (bonus découverte traité étape 4)
A12: M5 | B12: CLARTÉ DU POSITIONNEMENT | C12: Col. ATMOSPHÈRE (AMB) + ESPRIT (OR) | D12: Cohérence : AMB renseignée et non contradictoire | E12: 0–5 | F12: 6 | G12: AMB nette=5 · AMB générique=3 · conflit AMB-FES×AMB-ZEN=1
A13: M6 | B13: ÉQUIPEMENTS & SERVICES | C13: MASTER_TAGS ÉQUIPEMENT (spa, rooftop, pool club, DJ, terrasse…) | D13: Densité d'équipements distinctifs détectés sur la fiche | E13: 0–5 | F13: 10 | G13: 0 tag=1 · 1-2=3 · 3-4=4 · 5+=5
A14: M7 | B14: FAMILLE / ENFANTS | C14: Col. KD (KD-KFR/CLB/PIS/ACT) | D14: Couverture des équipements enfants (neutre si lieu non familial) | E14: 0–5 | F14: 4 | G14: aucun=2,5(neutre) · KD-KFR=3,5 · +CLB/PIS/ACT=+0,5 chacun (max 5)
A15: M8 | B15: ACCÈS & PRIVATISATION | C15: Col. TYPE D'ACCÈS (ACC) · ACC-PRV / privatisable | D15: Capacité à offrir de l'exclusivité | E15: 0–5 | F15: 6 | G15: ACC-PRV=5 · ACC-CLI=3 · ACC-PUB seul=2
A16: M9 | B16: COUVERTURE PUBLICS | C16: Col. PUBLIC (PUB-*) | D16: Largeur des publics adressés (sans diluer le positionnement) | E16: 0–5 | F16: 4 | G16: 1 public=3 · 2-3=4 · 4+=5 · incohérent=2
A17: M10 | B17: DIGITALISATION / PRÉSENCE | C17: Cols. NIVEAU DIGITAL, SITE, INSTA, réseaux | D17: Présence en ligne actionnable | E17: 0–5 | F17: 3 | G17: Élevé+site+réseaux=5 · moyen=3 · faible/à compléter=1
A18: M11 | B18: CONFORMITÉ RÉGLEMENTAIRE | C18: Cols. AUTORISATION, CLASSEMENT OFFICIEL (Maroc) | D18: Sécurité juridique du référencement | E18: 0–5 | F18: 4 | G18: conforme & classé=5 · en cours=3 · NC=1
A19: M12 | B19: COMMERCIAL / PARTENARIAT | C19: Cols. CONVENTION SIGNÉE, COMMISSION, STATUT CONTACT | D19: Solidité de la relation SOLÝ | E19: 0–5 | F19: 5 | G19: convention signée=5 · en négociation=3 · non contacté=1
... A21: M14 | B21: SCORE SUR-MESURE | C21: Bible SC · SCORE_SUR_MESURE (🆕) · capacité à privatiser/composer | D21: Aptitude à fermer un lieu / composer multi-lieux (HB-SUR) | E21: 0–5 | F21: 8 | G21: privatisation totale + multi-lieux=5 · privatisable partiel=3 · non=1
A22: TOTAL PONDÉRATIONS (doit faire 100) | F22: =SUM(F8:F21) -> 100
A24: ▸ EXEMPLE DE CALCUL · fiche fictive « Riad Signature » (modifiez les notes 0–5 en colonne F pour tester le moteur)
A25: SCORE | B25: LIBELLÉ | F25: NOTE 0–5 | G25: CONTRIB = note × poids /100
A26: =A8 -> M1 | B26: =B8 -> STANDING | F26: 5 | G26: =F26*F8/100 -> 0.75
A27: =A9 -> M2 | B27: =B9 -> RATINGS plateformes | F27: 4 | G27: =F27*F9/100 -> 0.6
A28: =A10 -> M3 | B28: =B10 -> LABELS & DISTINCTIONS | F28: 3.5 | G28: =F28*F10/100 -> 0.35
A29: =A11 -> M4 | B29: =B11 -> ANCIENNETÉ / RÉPUTATION | F29: 5 | G29: =F29*F11/100 -> 0.3
A30: =A12 -> M5 | B30: =B12 -> CLARTÉ DU POSITIONNEMENT | F30: 5 | G30: =F30*F12/100 -> 0.3
A31: =A13 -> M6 | B31: =B13 -> ÉQUIPEMENTS & SERVICES | F31: 4 | G31: =F31*F13/100 -> 0.4
A32: =A14 -> M7 | B32: =B14 -> FAMILLE / ENFANTS | F32: 2.5 | G32: =F32*F14/100 -> 0.1
A33: =A15 -> M8 | B33: =B15 -> ACCÈS & PRIVATISATION | F33: 5 | G33: =F33*F15/100 -> 0.3
A34: =A16 -> M9 | B34: =B16 -> COUVERTURE PUBLICS | F34: 4 | G34: =F34*F16/100 -> 0.16
A35: =A17 -> M10 | B35: =B17 -> DIGITALISATION / PRÉSENCE | F35: 3 | G35: =F35*F17/100 -> 0.09
A36: =A18 -> M11 | B36: =B18 -> CONFORMITÉ RÉGLEMENTAIRE | F36: 3 | G36: =F36*F18/100 -> 0.12
A37: =A19 -> M12 | B37: =B19 -> COMMERCIAL / PARTENARIAT | F37: 5 | G37: =F37*F19/100 -> 0.25
... A39: =A21 -> M14 | B39: =B21 -> SCORE SUR-MESURE | F39: 3 | G39: =F39*F21/100 -> 0.24
A40: NOTE INTRINSÈQUE FINALE (Σ contributions · échelle 0–5) | G40: =SUM(G26:G39) -> 4.16
A41: → QUALIFICATION LVL (cloches) dérivée automatiquement | G41: {=IFS(G40<=2,"LVL-1 · 🔔",G40<=3.5,"LVL-2 · 🔔🔔",G40<=4,"LVL-3 · 🔔🔔🔔",G40<=4.5,"LVL-4 · 🔔🔔🔔🔔",TRUE,"LVL-5 · 🔔🔔🔔🔔🔔")} -> LVL-4 · 🔔🔔🔔🔔
A43: ═══ BANDES LVL · LES CLOCHES (mapping note finale → qualification · repris de la bible) ═══
A44: CODE | B44: LIBELLÉ | C44: NOTE FINALE | D44: SENS | G44: COMMENTAIRE MOTEUR
A45: LVL-1 | B45: 🔔 UNE CLOCHE | C45: 0 – 2,0 | D45: Hors standard / non retenu | G45: Sort de la matrice de recommandation
A46: LVL-2 | B46: 🔔🔔 DEUX CLOCHES | C46: 2,1 – 3,5 | D46: Correct sans plus | G46: Proposé en second rideau / dépannage
A47: LVL-3 | B47: 🔔🔔🔔 TROIS CLOCHES | C47: 3,6 – 4,0 | D47: Bonne adresse | G47: Recommandable par défaut
A48: LVL-4 | B48: 🔔🔔🔔🔔 QUATRE CLOCHES | C48: 4,1 – 4,5 | D48: Exceptionnel | G48: Mis en avant dans les matchs premium
A49: LVL-5 | B49: 🔔🔔🔔🔔🔔 CINQ CLOCHES | C49: 4,6 – 5,0 | D49: Ultime / signature mondiale | G49: Tête de liste · réservé clients HOT/AMBASSADEUR
A51: ═══ ÉTAPE 1 · CONFIGURATION DU SÉJOUR (parcours 1.x : esprit OR · hébergement HB · budget BG · public · N participants · dates) ═══
A52: Le moteur applique d'abord les filtres durs de cadrage (éliminent les fiches non conformes), puis amorce le tri selon l'esprit du séjour. Aucun tag de tri n'élimine.
A53: ▸ FILTRES DURS (éliminent la fiche si non respecté)
A54: # | B54: FILTRE DUR | C54: SOURCE REQUÊTE | D54: RÈGLE
A55: F1 | B55: Capacité ≥ N | C55: Étape 1 · composition « pour N » | D55: capacité_fiche ≥ taille_groupe ; PUB-GRP exigé si N≥3
A56: F2 | B56: Budget | C56: Étape 1 · BG1–BG5 | D56: prix/nuit/chambre dans la bande BG (BG1–BG5, hébergement classique) · BG-LIBRE = AUCUNE élimination, disponible UNIQUEMENT sous HB-SUR
A57: F3 | B57: Type d'hébergement | C57: Étape 1 · HB-* (single-select) | D57: type_fiche = HB choisi · HB-SUR = combinaison ≥2 types (multi-lieux SOLÝ) → impose BG-LIBRE ; les types classiques imposent BG1–BG5
A59: ▸ TRI · points ajoutés aux fiches conformes (pondération éditable colonne F)
A60: TAG | B60: DÉCLENCHEUR | C60: S'APPLIQUE À | F60: POINTS | G60: COMMENTAIRE
A61: T2 | B61: Boost ESPRIT séjour (OR-*) cohérent | C61: tout le séjour (boost global) | F61: 15 | G61: OR single-select · diffuse sur HEB·RES·ACT·POI
A62: T3 | B62: Standing ST-ULT / ST-SIG | C62: TOUS | F62: 15 | G62: ST-ULT=+15 · ST-SIG=+10 (premium)
A63: T4 | B63: Match PUBLIC (PUB requête ∈ PUB fiche) | C63: TOUS | F63: 8 | G63: PUB-FAM ouvre slot enfants 2.9
A65: ═══ ÉTAPE 2 · EXPÉRIENCES (parcours 2.x : événement EV · slots matinée→enfants · régime) ═══
A66: Filtres durs propres aux expériences (slot, régime, usage événementiel), puis tri sur l'adéquation expérientielle. La sélection EV déclenche en plus les PACKS CRM (table en bas d'étape).
A67: ▸ FILTRES DURS
A68: # | B68: FILTRE DUR | C68: SOURCE REQUÊTE | D68: RÈGLE
A69: F4 | B69: Slot / créneau | C69: Étape 2 · matinée/déjeuner/après-midi/dîner/soirée/enfants | D69: la fiche doit servir le slot demandé · AU-EXC désactive déjeuner+après-midi
A70: F5 | B70: Régime végétarien | C70: Étape 2 · RG-VEG | D70: exige l'attribut lieu VENUE_VEGETARIAN (garde anti-set-vide légère)
A71: F6 | B71: Usage événementiel | C71: Étape 2 · EV-* / USAGE_EVT | D71: la fiche ESP/HEB doit porter l'usage (DEM_MAR, ANNIV_FES…)
A72: F7 | B72: Quota participants | C72: Règle moteur | D72: si nb_adultes < 5 (hors EV-DEM) → PACK INDISPONIBLE (blocage dur) · événement masqué · message « accessible dès 5 participants ». EV-DEM = 2 adultes (seule exception).
A74: ▸ TRI · points expériences (pondération éditable colonne F)
A75: TAG | B75: DÉCLENCHEUR | C75: S'APPLIQUE À | F75: POINTS | G75: COMMENTAIRE
A76: T1 | B76: Match AMBIANCE exact (AMB requête = AMB fiche) | C76: HEB·RES·ACT·ESP·POI | F76: 20 | G76: Repère bible (AMB-ROM +20). Cœur du tri.
A77: T5 | B77: Tag ÉQUIPEMENT cible atteint (spa, rooftop, DJ, pool club…) | C77: par tag matché | F77: 12 | G77: cibles MASTER_TAGS · cumulables, plafond +36
A78: T6 | B78: Catégorie POI demandée (POI-VIS/SHO/FOO/IMM/VUE) | C78: POI·ACT | F78: 8 | G78: selon univers AU-* choisi
A80: ▸ PÉNALITÉS (déclassent, n'éliminent pas)
A81: P1 | B81: ⚠ Pénalité AMB-FES × AMB-ZEN (incompatibles) | C81: TOUS | F81: -30 | G81: règle bible : festif ✕ zen → forte pénalité croisée
A82: P2 | B82: ⚠ Pénalité contrainte dure non compatible requête | C82: TOUS | F82: -15 | G82: ex. NEIGH_SENSITIVE sur usage festif
A84: ▸ TABLE D'INCLUSION ÉVÉNEMENT (parcours 2.1) · ce que chaque PACK CRM injecte automatiquement
A85: Les 5 EV standards déversent 2 PACKS CRM (fermés) : prestataires EVT-*, sécurité opérationnelle SE-OPER et orientation espaces EP-*. EV-AUT n'a pas de pack — le conseiller puise dans la bibliothèque interne EV-INTERNE (13 packs back-office).
A86: EV | B86: ÉVÉNEMENT | C86: CONDITION | D86: ESPACES EP-* orientés | E86: PACKS | F86: SE-OPER | G86: PRESTATAIRES EVT-* injectés
A87: EV-DEM | B87: Demande en mariage | C87: exactement 2 adultes | D87: EP-ROO · EP-RIA · EP-RES | E87: 2 (fermés) | F87: — (discret · option SE-PRO) | G87: EVT-FLO · EVT-PHO · EVT-MIX · EVT-CHE · EVT-LUM · EVT-MAS (usage DINER_PRV)
A88: EV-AFE | B88: Anniversaire festif | C88: ≥ 5 adultes (obligatoire · blocage dur) | D88: EP-VIL · EP-POL · EP-ROO | E88: 2 | F88: SE-EVE | G88: EVT-DJ · EVT-SOU · EVT-LUM · EVT-MIX · EVT-FOC · EVT-PHO · EVT-ANI
A89: EV-AFA | B89: Anniversaire familial | C89: ≥ 5 adultes (obligatoire) · ouvre nb enfants | D89: EP-VIL · EP-DOM · EP-JAR | E89: 2 | F89: SE-EVE (léger) | G89: EVT-ANE · EVT-TRA · EVT-PAT · EVT-PHO · EVT-ANI
A90: EV-EVJF | B90: EVJF | C90: ≥ 5 adultes (obligatoire) | D90: EP-VIL · EP-POL · EP-BEA | E90: 2 | F90: SE-EVE | G90: EVT-DJ · EVT-MUA · EVT-HAI · EVT-MIX · EVT-DAN · EVT-PHO
A91: EV-EVG | B91: EVG | C91: ≥ 5 adultes (obligatoire) | D91: EP-VIL · EP-POL · EP-BIV | E91: 2 | F91: SE-EVE | G91: EVT-DJ · EVT-MIX · EVT-SHI · EVT-FOC · EVT-PHO
A92: EV-AUT | B92: Autre (cas par cas) | C92: champ libre | D92: selon brief | E92: 0 · SOLÝ Assistance 24h | F92: SE-ETU (étude sur mesure) | G92: Aucun pack auto · conseiller puise EV-INTERNE (SEM/GALA/DES/DIN/NET/BAB/MAR/BAP/FIA/ANV/RET/REU/VOW)
A94: ═══ ÉTAPE 3 · TRANSPORT · SÉCURITÉ · DEVIS (parcours 3.x) ═══
A95: Aucun filtre d'élimination à cette étape : transport et sécurité sont des ADD-ONS proposés et chiffrés au devis. Le moteur suggère, le conseiller arbitre. En fin d'étape, le moteur cumule le montant du séjour.
A96: CODE | B96: LIBELLÉ / CODES | C96: CATÉGORIE | D96: RÈGLE MOTEUR | G96: SOURCE / NOTE
A97: TR-* | B97: Transport : TR-BER · TR-BEL · TR-SUV · TR-VAN | C97: Add-on suggéré | D97: Suggéré au devis selon N et standing · TR-BER NON suggéré si gestion_transport = CLIENT_GERE | G97: Bible TR · PARCOURS 2.11 (déplacé ét.3)
A98: SE-* | B98: Sécurité privée : SE-SUR · SE-PRO · SE-FEM · SE-24H · SE-ETU | C98: Add-on devis | D98: Proposée en option, jamais un filtre. Chiffrée au devis selon brief client. | G98: Bible SE · PARCOURS 2.10 (déplacé ét.3)
A99: SE-OPER | B99: Sécurité opérationnelle (événement) | C99: Injectée (rappel) | D99: Injectée automatiquement par les PACKS EV de l'étape 2 (SE-EVE / SE-ETU). Non choisie par le client. | G99: Voir table packs EV · étape 2
A100: DEVIS | B100: Cumul du montant séjour | C100: Calcul | D100: Montant séjour = Σ (hébergement ét.1 + expériences ét.2 + transport + sécurité ét.3). Reporté à l'étape 4. | G100: PARCOURS Étape 3 · cumul
A102: ═══ ÉTAPE 4 · CLASSEMENT FINAL & HONORAIRES SOLÝ (parcours 4.x) ═══
A103: Le moteur produit le classement final des recommandations puis le devis honoraires. Les signaux qualité transverses (indépendants d'une étape précise) et le coef NPS s'agrègent ici dans le score classé.
A104: ▸ SIGNAUX QUALITÉ TRANSVERSES (alimentent le classement final · pondération éditable colonne F)
A105: TAG | B105: DÉCLENCHEUR | C105: S'APPLIQUE À | F105: POINTS | G105: COMMENTAIRE
A106: T7 | B106: Label premium (Relais&Châteaux, Michelin Key…) | C106: HEB·RES | F106: 5 | G106: +5 par label, plafond +15
A107: T8 | B107: Rating plateforme élevé (≥4,5/5 & avis nombreux) | C107: TOUS | F107: 5 | G107: signal de satisfaction réelle
A108: T9 | B108: Bonus cloches LVL | C108: TOUS | F108: 5 | G108: LVL-5=+20 … LVL-1=0 · départage final
A109: T10 | B109: Bonus découverte ANC-NEW | C109: TOUS | F109: 4 | G109: « à tester en avant-première »
A111: ▸ COEFFICIENT SOLÝ AJUSTÉ NPS (post-séjour · multiplie la note intrinsèque au classement)
A112: CODE | B112: LIBELLÉ | C112: SCORE NPS | D112: IMPACT | F112: FACTEUR | G112: ACTION MOTEUR
A113: NPS-DETRA | B113: DÉTRACTEUR | C113: 0 – 6 | D113: Client mécontent | F113: ×0,95 | G113: Pénalise le prestataire · alerte qualité
A114: NPS-PASSI | B114: PASSIF | C114: 7 – 8 | D114: Neutre / correct | F114: ×1,00 | G114: Coef inchangé
...

Sheet SCORING_RULES
A1: ⚙️ SCORING_RULES · pondération des tags de TRI · paramètre éditable du MOTEUR · V1
A2: 📜 DOCTRINE · Cet onglet sort les POIDS du code : chaque tag de tri reçoit un SCORE (points) que le moteur additionne en phase de tri (jamais d'élimination). Modifier un score ici = re-régler le moteur sans toucher au développement. Barème de référence : voir MOTEUR · Section B (AMB exact = +20, esprit OR = +15, standing = +10/15…).
A3: 🔗 Colonnes FAMILLE / TAG / LIBELLÉ / TYPE = tirées par formule de MASTER_TAGS (auto-alignées sur la bible : un tag de tri ajouté à la bible apparaît ici). Colonne SCORE (jaune) = seul paramètre à saisir, laissé à blanc en V1.
H4: ⚙️ BARÈME DE TRI · source unique des poids (éditable) — repris de MOTEUR Section B
A5: FAMILLE | B5: TAG | C5: LIBELLÉ | D5: TYPE MATCHING | E5: SCORE (pts) | H5: CLÉ (tag ou famille) | I5: POINTS | J5: RÉFÉRENCE MOTEUR
A6: {=_xlws.FILTER(MASTER_TAGS!A3:A221,ISNUMBER(SEARCH("tri",MASTER_TAGS!E3:E221))*ISERROR(SEARCH("pas de",MASTER_TAGS!E3:E221)))} -> #NAME? | B6: {=_xlws.FILTER(MASTER_TAGS!C3:E221,ISNUMBER(SEARCH("tri",MASTER_TAGS!E3:E221))*ISERROR(SEARCH("pas de",MASTER_TAGS!E3:E221)))} -> #NAME? | E6: =XLOOKUP($B6,$H$6:$H$25,$I$6:$I$25,XLOOKUP($A6,$H$6:$H$25,$I$6:$I$25,0)) -> #NAME? | H6: AMB | I6: 20 | J6: T1 · Ambiance exacte — cœur du tri
E7: =XLOOKUP($B7,$H$6:$H$25,$I$6:$I$25,XLOOKUP($A7,$H$6:$H$25,$I$6:$I$25,0)) -> 0 | H7: OR | I7: 15 | J7: T2 · Esprit du séjour
E8: =XLOOKUP($B8,$H$6:$H$25,$I$6:$I$25,XLOOKUP($A8,$H$6:$H$25,$I$6:$I$25,0)) -> 0 | H8: ST-ULT | I8: 15 | J8: T3 · Standing ultra exclusif
E9: =XLOOKUP($B9,$H$6:$H$25,$I$6:$I$25,XLOOKUP($A9,$H$6:$H$25,$I$6:$I$25,0)) -> 0 | H9: ST-SIG | I9: 10 | J9: T3 · Standing signature
E10: =XLOOKUP($B10,$H$6:$H$25,$I$6:$I$25,XLOOKUP($A10,$H$6:$H$25,$I$6:$I$25,0)) -> 0 | H10: ST-PRE | I10: 5 | J10: T3 · Standing premium (interpolé)
E11: =XLOOKUP($B11,$H$6:$H$25,$I$6:$I$25,XLOOKUP($A11,$H$6:$H$25,$I$6:$I$25,0)) -> 0 | H11: LVL-5 | I11: 20 | J11: T9 · Cloches — tête de liste
E12: =XLOOKUP($B12,$H$6:$H$25,$I$6:$I$25,XLOOKUP($A12,$H$6:$H$25,$I$6:$I$25,0)) -> 0 | H12: LVL-4 | I12: 15 | J12: T9 · Cloches
E13: =XLOOKUP($B13,$H$6:$H$25,$I$6:$I$25,XLOOKUP($A13,$H$6:$H$25,$I$6:$I$25,0)) -> 0 | H13: LVL-3 | I13: 10 | J13: T9 · Cloches
E14: =XLOOKUP($B14,$H$6:$H$25,$I$6:$I$25,XLOOKUP($A14,$H$6:$H$25,$I$6:$I$25,0)) -> 0 | H14: LVL-2 | I14: 5 | J14: T9 · Cloches
E15: =XLOOKUP($B15,$H$6:$H$25,$I$6:$I$25,XLOOKUP($A15,$H$6:$H$25,$I$6:$I$25,0)) -> 0 | H15: LVL-1 | I15: 0 | J15: T9 · Hors standard
E16: =XLOOKUP($B16,$H$6:$H$25,$I$6:$I$25,XLOOKUP($A16,$H$6:$H$25,$I$6:$I$25,0)) -> 0 | H16: ÉQUIPEMENT | I16: 12 | J16: T5 · Tag équipement ciblé (plafond +36)
E17: =XLOOKUP($B17,$H$6:$H$25,$I$6:$I$25,XLOOKUP($A17,$H$6:$H$25,$I$6:$I$25,0)) -> 0 | H17: PUBLIC | I17: 8 | J17: T4 · Match public
E18: =XLOOKUP($B18,$H$6:$H$25,$I$6:$I$25,XLOOKUP($A18,$H$6:$H$25,$I$6:$I$25,0)) -> 0 | H18: POI | I18: 8 | J18: T6 · Catégorie POI demandée
... E25: =XLOOKUP($B25,$H$6:$H$25,$I$6:$I$25,XLOOKUP($A25,$H$6:$H$25,$I$6:$I$25,0)) -> 0 | H25: KD | I25: 8 | J25: Équipement enfants du lieu
E26: =XLOOKUP($B26,$H$6:$H$25,$I$6:$I$25,XLOOKUP($A26,$H$6:$H$25,$I$6:$I$25,0)) -> 0
E27: =XLOOKUP($B27,$H$6:$H$25,$I$6:$I$25,XLOOKUP($A27,$H$6:$H$25,$I$6:$I$25,0)) -> 0
E28: =XLOOKUP($B28,$H$6:$H$25,$I$6:$I$25,XLOOKUP($A28,$H$6:$H$25,$I$6:$I$25,0)) -> 0
E29: =XLOOKUP($B29,$H$6:$H$25,$I$6:$I$25,XLOOKUP($A29,$H$6:$H$25,$I$6:$I$25,0)) -> 0
E30: =XLOOKUP($B30,$H$6:$H$25,$I$6:$I$25,XLOOKUP($A30,$H$6:$H$25,$I$6:$I$25,0)) -> 0
E31: =XLOOKUP($B31,$H$6:$H$25,$I$6:$I$25,XLOOKUP($A31,$H$6:$H$25,$I$6:$I$25,0)) -> 0
E32: =XLOOKUP($B32,$H$6:$H$25,$I$6:$I$25,XLOOKUP($A32,$H$6:$H$25,$I$6:$I$25,0)) -> 0
E33: =XLOOKUP($B33,$H$6:$H$25,$I$6:$I$25,XLOOKUP($A33,$H$6:$H$25,$I$6:$I$25,0)) -> 0
E34: =XLOOKUP($B34,$H$6:$H$25,$I$6:$I$25,XLOOKUP($A34,$H$6:$H$25,$I$6:$I$25,0)) -> 0
E35: =XLOOKUP($B35,$H$6:$H$25,$I$6:$I$25,XLOOKUP($A35,$H$6:$H$25,$I$6:$I$25,0)) -> 0
E36: =XLOOKUP($B36,$H$6:$H$25,$I$6:$I$25,XLOOKUP($A36,$H$6:$H$25,$I$6:$I$25,0)) -> 0
E37: =XLOOKUP($B37,$H$6:$H$25,$I$6:$I$25,XLOOKUP($A37,$H$6:$H$25,$I$6:$I$25,0)) -> 0
... E93: =XLOOKUP($B93,$H$6:$H$25,$I$6:$I$25,XLOOKUP($A93,$H$6:$H$25,$I$6:$I$25,0)) -> 0

Sheet SOLY_RULES
A1: 🤖 SOLY_RULES · garde-fous de génération automatique des séjours SOLÝ · V1
A2: 📜 DOCTRINE · Règles non négociables que le moteur / l'IA SOLÝ doit respecter avant de proposer un séjour. Filtres durs = éliminent ; règles & garde-fous = encadrent ; pénalités = déclassent sans éliminer. Chaque règle pointe vers son onglet source.
A4: # | B4: RÈGLE | C4: TYPE | D4: PORTÉE / PARAMÈTRE | E4: SOURCE | F4: STATUT
A5: 1 | B5: Minimum 2 expériences par jour | C5: Composition | D5: ≥ 2 expériences / jour (hors hébergement) | E5: SOLY_RULES (ordre slots ci-dessous) · PARCOURS 2.2 | F5: ✓ Actif
A6: 2 | B6: Pas de double réservation | C6: Composition | D6: 1 prestataire / créneau max par jour | E6: SOLY_RULES (ordre slots ci-dessous) | F6: ✓ Actif
A7: 3 | B7: Respect des filtres alimentaires | C7: Filtre dur + info | D7: RG-VEG → exige VENUE_VEGETARIAN ; RG-ALG = signalement (non bloquant) | E7: MATCHING F5 · MASTER_TAGS | F7: ⚠ À instrumenter (attribut lieu)
A8: 4 | B8: Respect du budget | C8: Filtre dur | D8: BG1–BG5 = bande prix/nuit (hébergement classique) ; BG-LIBRE = aucun filtre, RÉSERVÉ à HB-SUR (couplage exclusif — anti set-vide) | E8: MATCHING F2 | F8: ✓ Actif
A9: 5 | B9: Respect du nombre de participants | C9: Filtre dur | D9: capacité ≥ N ; PUB-GRP exigé si N ≥ 3 | E9: MATCHING F1 | F9: ✓ Actif
A10: 6 | B10: Respect du type d'hébergement | C10: Filtre dur | D10: HB-* single-select ; HB-SUR = combinaison ≥ 2 types (multi-lieux) → impose BG-LIBRE | E10: MATCHING F3 | F10: ✓ Actif
A11: 7 | B11: Respect du slot / créneau | C11: Filtre dur | D11: la fiche doit servir le slot demandé (matinée…soirée) | E11: MATCHING F4 | F11: ✓ Actif
A12: 8 | B12: Quota événement ≥ 5 participants (blocage dur) | C12: Filtre dur | D12: EV-* accessibles uniquement à ≥ 5 participants · SEULE EXCEPTION EV-DEM (demande en mariage = 2 adultes) · sous 5 (hors EV-DEM) → pack INDISPONIBLE, événement masqué/désactivé | E12: PARCOURS 2.1 · MATCHING · MOTEUR | F12: ✓ Actif
A13: 9 | B13: Exclusivité AU-EXC | C13: Règle composition | D13: excursion journée → désactive Déjeuner (2.5) + Après-midi (2.6) | E13: SOLY_RULES (ordre slots ci-dessous) · MATCHING | F13: ✓ Actif
A14: 10 | B14: Anti set-vide | C14: Garde-fou | D14: ne jamais renvoyer 0 résultat (Sur mesure, quota < 5, RG souples) | E14: MOTEUR · doctrine | F14: ✓ Actif
A15: 11 | B15: Le tri n'élimine jamais | C15: Principe moteur | D15: les tags de tri ré-ordonnent les fiches conformes, sans en exclure | E15: MOTEUR · Section B | F15: ✓ Actif
A16: 12 | B16: Incompatibilité AMB-FES × AMB-ZEN | C16: Pénalité | D16: −30 pts (déclasse, n'élimine pas) ; festif × zen | E16: MOTEUR P1 | F16: ✓ Actif
... A20: 16 | B20: Double codage hébergement | C20: Règle données | D20: Un lieu vendu à la nuit ET privatisable = 2 fiches distinctes, une par code applicable (ex : HOT/INC/RIA à la nuit + COL en privatisation ; chaque fiche = 1 ID contact unique). Valable sur tout le fichier + onglet HEBERGEMENT. | E20: HEBERGEMENT · REF_CODES | F20: ✓ Actif
A22: 🧩 ORDRE D'ASSEMBLAGE DES SLOTS · le moteur remplit chaque journée dans l'ordre de priorité croissante (repris de l'ex-onglet COMPOSITION_RULES)
A23: SLOT | B23: PRIORITÉ | C23: RÉF. PARCOURS
A24: MATINÉE | B24: 1 | C24: 2.4
A25: DÉJEUNER | B25: 2 | C25: 2.5
A26: APRÈS-MIDI | B26: 3 | C26: 2.6
A27: DÎNER | B27: 4 | C27: 2.7
A28: SOIRÉE | B28: 5 | C28: 2.8
A29: ENFANTS | B29: 6 | C29: 2.9

Sheet HONORAIRES_SOLY
A1: 💰 HONORAIRES_SOLY · rémunération SOLÝ = % par type de prestation réservée · V1
A2: 📜 DOCTRINE · SOLÝ facture un honoraire = un POURCENTAGE appliqué au montant réservé de chaque type de prestation (parcours Étape 4). Honoraire = Montant réservé HT × % SOLÝ. Le client paie : Σ montants réservés (étapes 1–3) + Σ honoraires SOLÝ. Les % (jaune) sont à définir par la direction.
A3: 🔗 Colonne MONTANT RÉSERVÉ = alimentée par le cumul du devis (étapes 1–3 du MOTEUR) · ici valeurs d'EXEMPLE à remplacer par le devis réel. Colonne % SOLÝ = barre tarifaire à saisir une fois.
A5: # | B5: TYPE DE PRESTATION | C5: CODES / FAMILLES CONCERNÉS (étape) | D5: MONTANT RÉSERVÉ HT (€) | E5: % HONORAIRE SOLÝ | F5: HONORAIRE SOLÝ (€)
A6: 1 | B6: Hôtel / Hébergement | C6: HB-* (Étape 1) | D6: 8000 | E6: 0.1 | F6: =IF($E6="","",D6*E6) -> 800
A7: 2 | B7: Événement à organiser | C7: EV-* + 2 PACKS CRM (Étape 2.1) | D7: 2000 | E7: 0.1 | F7: =IF($E7="","",D7*E7) -> 200
A8: 3 | B8: Événementiel | C8: EVT-* prestataires (DJ, traiteur, déco, fleuriste, photo…) (Étape 2.1) | D8: 1500 | E8: 0.1 | F8: =IF($E8="","",D8*E8) -> 150
A9: 4 | B9: Espace privatisé | C9: EP-* / ESP-TYPE espaces privatisables (Étape 2.1) | D9: 1000 | E9: 0.1 | F9: =IF($E9="","",D9*E9) -> 100
A10: 5 | B10: Activité | C10: Toutes expériences : AU-* · RA-D* · RA-N* · NL-* · POI · AK-* (Kids / Enfants) (Étape 2) | D10: 1200 | E10: 0.1 | F10: =IF($E10="","",D10*E10) -> 120
A11: 6 | B11: Transport | C11: TR-* (Étape 3) | D11: 500 | E11: 0.1 | F11: =IF($E11="","",D11*E11) -> 50
A12: 7 | B12: Sécurité | C12: SE-* privées (Étape 3) | D12: 250 | E12: 0.1 | F12: =IF($E12="","",D12*E12) -> 25
A13: TOTAL | B13: Séjour + honoraires | D13: =SUM(D6:D12) -> 14450 | E13: =IF(D13=0,"",F13/D13) -> 0.1 | F13: =SUM(F6:F12) -> 1445
A15: MONTANT TOTAL À PAYER PAR LE CLIENT (HT) | D15: =D13+F13 -> 15895

Sheet HEBERGEMENT
B1: IDENTITÉ & LOCALISATION · ✅ V1 vérifié (aligné 🔖 CODES DE RÉFÉRENCE) | M1: TARIFS (€/NUIT) | T1: COORDONNÉES & RÉSEAUX | AA1: NOTES | AB1: ATTRIBUTS RÉFÉRENTIEL SOLÝVENTS
A2: VILLE | B2: DESIGNATION | C2: ID CONTACT | D2: LIBELLÉ SOLÝVENTS | E2: CODE | F2: NOM | G2: CLASSEMENT (REF) | H2: BUDGET (BG) | I2: ADRESSE | J2: QUARTIER | K2: NBRE DE CH | L2: PRIVATISABLE | M2: CHAMBRE | N2: MINI SUITE | O2: SUITE | P2: SUITE AVEC PISCINE | Q2: VILLA – NB CH | R2: VILLA – TARIF (À PARTIR DE) | S2: NOTES | T2: TELEPHONE | U2: WHATSAPP | V2: EMAIL | W2: CONTACT DÉCISIONNAIRE | X2: SITE WEB | Y2: INSTAGRAM | Z2: FACEBOOK | AA2: NOTES CONTACT | AB2: STANDING (ST) | AC2: ATMOSPHÈRE (AMB) | AD2: ÉQUIP. ENFANTS (KD) | AE2: QUALIF · CLOCHE (LVL) | AF2: LABELS / DISTINCTIONS (LAB) | AG2: ESPRIT (OR) | AH2: PUBLIC | AI2: TYPE D'ACCÈS (ACC) | AJ2: USAGES ÉVÉNEMENTIELS
A3: MARRAKECH | B3: HEBERGEMENT | C3: H072 | D3: INCONTOURNABLE | E3: {=IFERROR(INDEX(REF_CODES!$B$8:$B$13,MATCH($D3,REF_CODES!$C$8:$C$13,0)),"")} -> HB-INC | F3: LES JARDINS DE LA KOUTOUBIA | G3: 5 ETOILES | H3: BG1 · Moins de 300 € | I3: 26 Rue De La Koutoubia, Médina | J3: Medina | K3: 108 | L3: NON | M3: 285 | N3: 465 | O3: 525 | P3: 725 | Q3: NA | R3: NA | S3: NA | T3: 212 5 24 38 8800 | U3: À compléter | V3: commercial@jardinskoutoubia.com | W3: à compléter | X3: https://www.lesjardinsdelakoutoubia.com | Y3: @jardinsdelakoutoubia | Z3: https://facebook.com/jardinsdelakoutoubia | AA3: Importé de HEBERGEMENT. Quartier : Medina · Site : https://www.lesjardinsdelakoutoubia.com | Coord. complétée(s) depuis annuaire : tél [Ancien statut: Importé] | AB3: ST-ULT · ULTRA EXCLUSIF | AC3: AMB-ROM · ROMANTIQUE | AD3: KD-KFR · KIDS FRIENDLY | AE3: LVL-3 · 🔔🔔🔔 TROIS CLOCHES | AF3: À qualifier (labels / distinctions) | AG3: OR-ROM · ROMANTIQUE | AH3: PUB-CPL · Couple | AI3: ACC-PUB | AJ3: Mariage, séminaire, privatisation
A4: MARRAKECH | B4: HEBERGEMENT | C4: H073 | D4: INCONTOURNABLE | E4: {=IFERROR(INDEX(REF_CODES!$B$8:$B$13,MATCH($D4,REF_CODES!$C$8:$C$13,0)),"")} -> HB-INC | F4: Es Saadi Marrakech Resort - Palace | G4: 5 ETOILES | H4: BG3 · 500 – 800 € | I4: Rue Ibrahim El Mazini Hivernage, L'Hivernage | J4: Hivernage | K4: 252 | L4: NON | M4: 367 | N4: 518 | O4: 647 | P4: NA | Q4: 1 ; 2 | R4: 1600 | S4: NA | T4: +212 524 337400 | U4: À compléter | V4: selfcoordination@essaadi.com · palace@essaadi.com | W4: Rania BAAMRI | X4: https://www.essaadi.com | Y4: @essaadimarrakech | Z4: https://facebook.com/essaadimarrakechresort | AA4: Importé de HEBERGEMENT. Quartier : Hivernage · Site : https://www.essaadi.com | Coord. complétée(s) depuis annuaire : tél [Ancien statut: Importé] | Villa(s) privatisable(s) déplacée(s) → HB-COL | AB4: ST-ULT · ULTRA EXCLUSIF | AC4: AMB-ROM · ROMANTIQUE | AD4: KD-CLB · KIDS CLUB | AE4: LVL-3 · 🔔🔔🔔 TROIS CLOCHES | AF4: À qualifier (labels / distinctions) | AG4: OR-PRO · PROFESSIONNEL | AH4: PUB-GRP · Groupe | AI4: ACC-PUB | AJ4: Très fort potentiel évènementiel
A5: MARRAKECH | B5: HEBERGEMENT | C5: H075 | D5: INCONTOURNABLE | E5: {=IFERROR(INDEX(REF_CODES!$B$8:$B$13,MATCH($D5,REF_CODES!$C$8:$C$13,0)),"")} -> HB-INC | F5: Hôtel & Ryads Barrière Le Naoura | G5: 5 ETOILES | H5: BG2 · 300 – 500 € | I5: Djebel Alakhdar - Bab Doukkala, Médina | J5: Hivernage | K5: 145 | L5: OUI | M5: 300 | N5: 400 | O5: 600 | P5: 900 | Q5: 1 ; 2 ; 3 ; 6 | R5: 1200 | S5: Villa 1 CH: 1200 · Villa 2 CH: 1800 · Villa 3 CH: 2500 · Villa 6 CH: 5000 | T5: 212524459000 | U5: À compléter | V5: reservation@groupebarriere.com | W5: à compléter | X5: https://www.hotelsbarriere.com/fr/marrakech/le-naoura.html | Y5: à compléter | Z5: https://facebook.com/hotelryadsbarrierelenaouramarrakech | AA5: Importé de HEBERGEMENT. Quartier : Hivernage · Site : https://www.hotelsbarriere.com/fr/marrakech/le-naoura.html | Coord. complétée(s) depuis annuaire : tél [Ancien statut: Importé] | Villa(s) privatisable(s) déplacée(s) → HB-COL | AB5: ST-ULT · ULTRA EXCLUSIF | AC5: AMB-ROM · ROMANTIQUE | AD5: KD-KFR · KIDS FRIENDLY | AE5: LVL-3 · 🔔🔔🔔 TROIS CLOCHES | AF5: À qualifier (labels / distinctions) | AG5: OR-ROM · ROMANTIQUE | AH5: PUB-CPL · Couple | AI5: ACC-PUB · ACC-PRV | AJ5: Mariage, séminaire, privatisation
A6: MARRAKECH | B6: HEBERGEMENT | C6: H026 | D6: HOTEL & RESORT | E6: {=IFERROR(INDEX(REF_CODES!$B$8:$B$13,MATCH($D6,REF_CODES!$C$8:$C$13,0)),"")} -> HB-HOT | F6: Park Hyatt Marrakech | G6: 5 ETOILES | H6: BG3 · 500 – 800 € | I6: Al Maaden Golf Resort | J6: Al Maaden | K6: 130 | L6: OUI | M6: 550 | N6: NA | O6: 700 | P6: NA | Q6: 1 ; 2 ; 3 | R6: 1800 | S6: Villa 1 CH: 1800 · Villa 2 CH: 3000 · Villa 3 CH: 4500 | T6: +212 7 75 75 75 61 / 212524441234 | U6: +212 775757561 (à confirmer) | V6: marrakech.park@hyatt.com | W6: Mme Fatim Zahra El Basri | X6: non trouvé | Y6: @parkhyattmarrakech | Z6: https://facebook.com/ParkHyattmarrakech | AA6: Coord. complétée(s) depuis annuaire : tél | Villa(s) privatisable(s) déplacée(s) → HB-COL | AB6: ST-ULT · ULTRA EXCLUSIF | AC6: AMB-ROM · ROMANTIQUE | AD6: KD-CLB · KIDS CLUB | AE6: LAB-VIRT · VIRTUOSO | AF6: LAB-VIRT · VIRTUOSO | AG6: OR-ROM · ROMANTIQUE | AH6: PUB-CPL · Couple | AI6: ACC-PUB · ACC-PRV | AJ6: Séminaires premium
A7: MARRAKECH | B7: HEBERGEMENT | C7: H004 | D7: INCONTOURNABLE | E7: {=IFERROR(INDEX(REF_CODES!$B$8:$B$13,MATCH($D7,REF_CODES!$C$8:$C$13,0)),"")} -> HB-INC | F7: The Oberoi Marrakech | G7: 5 ETOILES | H7: BG3 · 500 – 800 € | I7: BP 22788 - Route de Ouarzazate | J7: Route d'Ouarzazate | K7: 111 | L7: OUI | M7: 481 | N7: 750 | O7: 900 | P7: 1000 | Q7: 1 | R7: 1200 | S7: NA | T7: +212 525 08 15 15 / +212 664 77 66 31 / 212525081515 | U7: +212 664776631 (à confirmer) | V7: reservations@oberoigroup.com | W7: Mlle Fatima Ezahra El Idrissi | X7: https://www.oberoihotels.com/hotels-in-morocco-marrakech/ | Y7: @oberoimarrakech | Z7: NA | AA7: Coord. complétée(s) depuis annuaire : tél | Villa(s) privatisable(s) déplacée(s) → HB-COL | AB7: ST-ULT · ULTRA EXCLUSIF | AC7: AMB-ROM · ROMANTIQUE | AD7: KD-CLB · KIDS CLUB | AE7: LAB-VIRT · VIRTUOSO | AF7: LAB-VIRT · VIRTUOSO | AG7: OR-ROM · ROMANTIQUE | AH7: PUB-CPL · Couple | AI7: ACC-PUB · ACC-PRV | AJ7: Mariages destination
A8: MARRAKECH | B8: HEBERGEMENT | C8: H001 | D8: INCONTOURNABLE | E8: {=IFERROR(INDEX(REF_CODES!$B$8:$B$13,MATCH($D8,REF_CODES!$C$8:$C$13,0)),"")} -> HB-INC | F8: Royal Mansour Marrakech | G8: 5 ETOILES | H8: BG5 · 1 200 € et + | I8: Rue Abou Abbas El Sebti, Médina | J8: Hivernage | K8: 53 | L8: OUI | M8: 2200 | N8: 2800 | O8: 3500 | P8: NA | Q8: 1 ; 2 ; 3 ; 4 | R8: 1500 | S8: NA | T8: +212 529 80 80 80 / 212529808069 | U8: À compléter | V8: marrakech@royalmansour.com | W8: M. Ibensrhir (ibensrhir@royalmansour.com) | X8: https://www.royalmansour.com | Y8: @royalmansour | Z8: @royalmansourmarrakech | AA8: Domaine email corrigé (royalmansour.com) | Coord. complétée(s) depuis annuaire : tél [Ancien statut: Complété ✦] | Villa(s) privatisable(s) déplacée(s) → HB-COL | AB8: ST-ULT · ULTRA EXCLUSIF | AC8: AMB-ROM · ROMANTIQUE | AD8: KD-KFR · KIDS FRIENDLY | AE8: LAB-VIRT · VIRTUOSO · LAB-LHW · LEADING HOTELS OF THE WORLD | AF8: LAB-VIRT · VIRTUOSO · LAB-LHW · LEADING HOTELS OF THE WORLD | AG8: OR-ROM · ROMANTIQUE | AH8: PUB-CPL · Couple | AI8: ACC-PUB · ACC-PRV | AJ8: Mariages VIP, privatisations
A9: MARRAKECH | B9: HEBERGEMENT | C9: H006 | D9: INCONTOURNABLE | E9: {=IFERROR(INDEX(REF_CODES!$B$8:$B$13,MATCH($D9,REF_CODES!$C$8:$C$13,0)),"")} -> HB-INC | F9: Amanjena Resort | G9: 5 ETOILES | H9: BG4 · 800 – 1 200 € | I9: Km 12 Route de Ouarzazate P.O. Box 2405 | J9: Route d'Ouarzazate | K9: 40 | L9: OUI | M9: 837 | N9: 1100 | O9: 1500 | P9: 2000 | Q9: 1 | R9: 4000 | S9: NA | T9: +212 524 39 90 00 | U9: À compléter | V9: amanjena@aman.com | W9: Mme Sara Laghmir | X9: https://www.aman.com/resorts/amanjena | Y9: @amanresorts | Z9: https://facebook.com/amanjenaresort | AA9: Coord. complétée(s) depuis annuaire : tél | Villa(s) privatisable(s) déplacée(s) → HB-COL | AB9: ST-ULT · ULTRA EXCLUSIF | AC9: AMB-ROM · ROMANTIQUE | AD9: KD-CLB · KIDS CLUB | AE9: LVL-3 · 🔔🔔🔔 TROIS CLOCHES | AF9: À qualifier (labels / distinctions) | AG9: OR-ROM · ROMANTIQUE | AH9: PUB-CPL · Couple | AI9: ACC-PUB · ACC-PRV | AJ9: Mariage, séminaire, privatisation
A10: MARRAKECH | B10: HEBERGEMENT | C10: H077 | D10: RIAD & PATRIMOINE | E10: {=IFERROR(INDEX(REF_CODES!$B$8:$B$13,MATCH($D10,REF_CODES!$C$8:$C$13,0)),"")} -> HB-RIA | F10: Dar Rhizlane, Palais Table d'hôtes & SPA | G10: 5 ETOILES | H10: BG2 · 300 – 500 € | I10: Avenue Jnane El Harti Hivernage, L'Hivernage | J10: Hivernage | K10: 20 | L10: OUI | M10: 250 | N10: 400 | O10: 600 | P10: NA | Q10: NA | R10: NA | S10: NA | T10: +212 5 24 42 13 03 / +212 5 24 44 79 00 | U10: À compléter | V10: contact@rhizlane.com | W10: à compléter | X10: https://www.dar-rhizlane.com | Y10: @darrhizlane | Z10: NA | AA10: Importé de HEBERGEMENT. Quartier : Hivernage · Site : https://www.dar-rhizlane.com | Coord. complétée(s) depuis annuaire : tél [Ancien statut: Importé] | Fusion doublons : Dar Rhizlane, Palais Table d'hôtes & SPA (H077) + Dar Rhizlane (H149) | AB10: ST-PRE · PREMIUM | AC10: AMB-ZEN · ZEN & BIEN-ÊTRE | AD10: KD-KFR · KIDS FRIENDLY | AE10: LAB-MMS · MR & MRS SMITH | AF10: LAB-MMS · MR & MRS SMITH | AG10: OR-ROM · ROMANTIQUE | AH10: PUB-CPL · Couple | AI10: ACC-PUB · ACC-PRV | AJ10: Mariage intimiste, anniversaire
A11: MARRAKECH | B11: HEBERGEMENT | C11: H019 | D11: NATURE & HORIZON | E11: {=IFERROR(INDEX(REF_CODES!$B$8:$B$13,MATCH($D11,REF_CODES!$C$8:$C$13,0)),"")} -> HB-NAT | F11: Kasbah d'if | G11: 5 ETOILES | H11: BG3 · 500 – 800 € | I11: km 25 Route du Barrage Agafay | J11: Désert d'Agafay (Tameslouht) | K11: 37 | L11: OUI | M11: 300 | N11: 450 | O11: 600 | P11: NA | Q11: NA | R11: NA | S11: NA | T11: +212 808 68 56 66 | U11: À compléter | V11: contact@kasbahdif.com | W11: Mr Abdellatif / Gérant | X11: https://www.kasbahdif.com | Y11: @kasbahdif | Z11: NA | AA11: Coord. complétée(s) depuis annuaire : tél | Fusion doublons : Kasbah d'if (H019) | AB11: ST-SIG · SIGNATURE | AC11: AMB-ZEN · ZEN & BIEN-ÊTRE | AD11: KD-KFR · KIDS FRIENDLY | AE11: LVL-2 · 🔔🔔 DEUX CLOCHES | AF11: À qualifier (labels / distinctions) | AG11: OR-ZEN · ZEN & BIEN-ÊTRE | AH11: PUB-CPL · Couple | AI11: ACC-PUB · ACC-PRV | AJ11: Privatisation, EVJF
A12: MARRAKECH | B12: HEBERGEMENT | C12: H003 | D12: INCONTOURNABLE | E12: {=IFERROR(INDEX(REF_CODES!$B$8:$B$13,MATCH($D12,REF_CODES!$C$8:$C$13,0)),"")} -> HB-INC | F12: Mandarin Oriental, Marrakech | G12: 5 ETOILES | H12: BG5 · 1 200 € et + | I12: Route Du Golf Royal | J12: Route du Golf Royal | K12: 63 | L12: OUI | M12: 530 | N12: 800 | O12: 1200 | P12: NA | Q12: 1 | R12: 1350 | S12: NA | T12: +212 524 29 88 88 | U12: À compléter | V12: momrk-reservations@mohg.com | W12: Mme Nada Hihi | X12: https://www.mandarinoriental.com/fr/marrakech/la-medina | Y12: @mo_marrakech | Z12: https://facebook.com/MandarinOrientalMarrakech | AA12: Coord. complétée(s) depuis annuaire : tél | Villa(s) privatisable(s) déplacée(s) → HB-COL | AB12: ST-ULT · ULTRA EXCLUSIF | AC12: AMB-ROM · ROMANTIQUE | AD12: KD-CLB · KIDS CLUB | AE12: LVL-3 · 🔔🔔🔔 TROIS CLOCHES | AF12: À qualifier (labels / distinctions) | AG12: OR-ROM · ROMANTIQUE | AH12: PUB-CPL · Couple | AI12: ACC-PUB · ACC-PRV | AJ12: Mariages & groupes
A13: MARRAKECH | B13: HEBERGEMENT | C13: H079 | D13: INCONTOURNABLE | E13: {=IFERROR(INDEX(REF_CODES!$B$8:$B$13,MATCH($D13,REF_CODES!$C$8:$C$13,0)),"")} -> HB-INC | F13: Les Jardins De La Médina | G13: 5 ETOILES | H13: BG2 · 300 – 500 € | I13: 21 Derb Chtouka, Kasbah | J13: Médina (Kasbah) | K13: 36 | L13: OUI | M13: 300 | N13: NA | O13: NA | P13: NA | Q13: NA | R13: NA | S13: NA | T13: +212 524 381 851 | U13: À compléter | V13: info@lesjardinsdelamedina.com | W13: doublon Les Jardins de la Médina | X13: https://www.lesjardinsdelamedina.com | Y13: @lesjardinsdelamedina | Z13: NA | AA13: Importé de HEBERGEMENT. Quartier : Médina — Kasbah · Site : lesjardinsdelamedina.com | Coord. complétée(s) depuis annuaire : tél [Ancien statut: Importé] | Fusion doublons : Les Jardins de la Medina Collection (H079) | AB13: ST-ULT · ULTRA EXCLUSIF | AC13: AMB-ROM · ROMANTIQUE | AD13: KD-KFR · KIDS FRIENDLY | AE13: LVL-3 · 🔔🔔🔔 TROIS CLOCHES | AF13: À qualifier (labels / distinctions) | AG13: OR-ROM · ROMANTIQUE | AH13: PUB-CPL · Couple | AI13: ACC-PUB · ACC-PRV | AJ13: Mariage, dîner privé
A14: MARRAKECH | B14: HEBERGEMENT | C14: H080 | D14: INCONTOURNABLE | E14: {=IFERROR(INDEX(REF_CODES!$B$8:$B$13,MATCH($D14,REF_CODES!$C$8:$C$13,0)),"")} -> HB-INC | F14: The Mellah Hotel | G14: 5 ETOILES | H14: BG1 · Moins de 300 € | I14: Derb Alaati Allah No 13 Hay Salam, Mellah | J14: Médina (Mellah) | K14: 10 | L14: OUI | M14: 200 | N14: NA | O14: NA | P14: NA | Q14: NA | R14: NA | S14: NA | T14: +212 628 613848 | U14: +212 628613848 (à confirmer) | V14: hello@hotelthemellah.com | W14: à compléter | X14: https://www.themellahmarrakech.com | Y14: @themellahmarrakech | Z14: NA | AA14: Importé de HEBERGEMENT. Quartier : Médina (Mellah) · Site : https://www.themellahmarrakech.com | Coord. complétée(s) depuis annuaire : tél [Ancien statut: Importé] | AB14: ST-SIG · SIGNATURE | AC14: AMB-ROM · ROMANTIQUE | AD14: KD-KFR · KIDS FRIENDLY | AE14: LVL-1 · 🔔 UNE CLOCHE | AF14: À qualifier (labels / distinctions) | AG14: OR-ROM · ROMANTIQUE | AH14: PUB-CPL · Couple | AI14: ACC-PUB · ACC-PRV | AJ14: Shooting, influenceurs
A15: MARRAKECH | B15: HEBERGEMENT | C15: H081 | D15: INCONTOURNABLE | E15: {=IFERROR(INDEX(REF_CODES!$B$8:$B$13,MATCH($D15,REF_CODES!$C$8:$C$13,0)),"")} -> HB-INC | F15: PL Place Boutique Hôtel & Restaurant | G15: 5 ETOILES | H15: BG1 · Moins de 300 € | I15: DAR TOUNSSI RTE DE FES ENNAKHIL | J15: Palmeraie | K15: 9 | L15: OUI | M15: 200 | N15: 300 | O15: 350 | P15: NA | Q15: NA | R15: NA | S15: NA | T15: +212 6 66 48 59 29 | U15: À compléter | V15: hello@plplace-marrakech.com | W15: tél. non trouvé de source fiable (numéros contradictoires selon annuaires) | X15: https://www.plplace.com | Y15: @plplace_marrakech | Z15: NA | AA15: Importé de HEBERGEMENT. Quartier : Palmeraie · Site : https://www.plplace.com | Coord. complétée(s) depuis annuaire : email [Ancien statut: À compléter] | AB15: ST-SIG · SIGNATURE | AC15: AMB-ROM · ROMANTIQUE | AD15: KD-CLB · KIDS CLUB | AE15: LVL-1 · 🔔 UNE CLOCHE | AF15: À qualifier (labels / distinctions) | AG15: OR-ROM · ROMANTIQUE | AH15: PUB-CPL · Couple | AI15: ACC-PUB · ACC-PRV | AJ15: Privatisation légère
A16: MARRAKECH | B16: HEBERGEMENT | C16: H082 | D16: NATURE & HORIZON | E16: {=IFERROR(INDEX(REF_CODES!$B$8:$B$13,MATCH($D16,REF_CODES!$C$8:$C$13,0)),"")} -> HB-NAT | F16: La Pause Ecolodge Agafay | G16: Ecolodge de luxe · camp désert Agafay (non classé étoiles, créé 2003) | H16: BG2 · 300 – 500 € | I16: Agafay Desert | J16: Agafay | K16: non trouvé | L16: OUI | M16: 280 | N16: 450 | O16: 1200 | P16: NA | Q16: NA | R16: NA | S16: NA | T16: +212 524 421576 | U16: À compléter | V16: lapause1@gmail.com | W16: à compléter | X16: https://www.lapause-marrakech.com | Y16: @lapauseagafay | Z16: NA | AA16: Importé de HEBERGEMENT. Quartier : Agafay · Site : https://www.lapause-marrakech.com | Coord. complétée(s) depuis annuaire : tél [Ancien statut: Importé] | AB16: ST-PRE · PREMIUM | AC16: AMB-ZEN · ZEN & BIEN-ÊTRE | AD16: KD-KFR · KIDS FRIENDLY | AE16: LVL-2 · 🔔🔔 DEUX CLOCHES | AF16: À qualifier (labels / distinctions) | AG16: OR-ZEN · ZEN & BIEN-ÊTRE | AH16: PUB-CPL · Couple | AI16: ACC-PUB · ACC-PRV | AJ16: EVJF, retraite yoga
A17: MARRAKECH | B17: HEBERGEMENT | C17: H008 | D17: RIAD & PATRIMOINE | E17: {=IFERROR(INDEX(REF_CODES!$B$8:$B$13,MATCH($D17,REF_CODES!$C$8:$C$13,0)),"")} -> HB-RIA | F17: Riad Camilia | G17: Maison d'hôtes · riad (cat. maison d'hôtes) | H17: BG1 · Moins de 300 € | I17: 9 Derb El Ouali, Kaat Benahid, Médina | J17: Médina | K17: 6-7 | L17: OUI | M17: 145 | N17: NA | O17: NA | P17: NA | Q17: NA | R17: NA | S17: NA | T17: +212 5 244 43 081 / +212 524 443 081 / +212 669 283 492 | U17: +212 669283492 (à confirmer) | V17: contact@riadcamilia.com | W17: Propriétaire Riad | X17: riadcamilia.com | Y17: @riadcamilia | Z17: NA | AA17: Mention fichier : « plus en activité » — à vérifier | Coord. complétée(s) depuis annuaire : tél | AB17: ST-PRE · PREMIUM | AC17: AMB-ZEN · ZEN & BIEN-ÊTRE | AD17: KD-KFR · KIDS FRIENDLY | AE17: LVL-2 · 🔔🔔 DEUX CLOCHES | AF17: À qualifier (labels / distinctions) | AG17: OR-ROM · ROMANTIQUE | AH17: PUB-CPL · Couple | AI17: ACC-PUB · ACC-PRV | AJ17: Privatisation, anniversaire
A18: MARRAKECH | B18: HEBERGEMENT | C18: H007 | D18: INCONTOURNABLE | E18: {=IFERROR(INDEX(REF_CODES!$B$8:$B$13,MATCH($D18,REF_CODES!$C$8:$C$13,0)),"")} -> HB-INC | F18: Four Seasons Resort Marrakech | G18: 5 ETOILES | H18: BG4 · 800 – 1 200 € | I18: 1 Boulevard de la Menara, L'Hivernage, | J18: Hivernage | K18: 141 | L18: OUI | M18: 700 | N18: 900 | O18: 1200 | P18: NA | Q18: NA | R18: NA | S18: NA | T18: +212 524 35 92 00 | U18: À compléter | V18: reservations.morocco@fourseasons.com | W18: Hajar Naciri | X18: https://www.fourseasons.com/marrakech/ | Y18: @fsmarrakech | Z18: https://facebook.com/FourSeasonsResortMarrakech | AA18: Coord. complétée(s) depuis annuaire : tél | AB18: ST-ULT · ULTRA EXCLUSIF | AC18: AMB-ROM · ROMANTIQUE | AD18: KD-CLB · KIDS CLUB | AE18: LAB-VIRT · VIRTUOSO | AF18: LAB-VIRT · VIRTUOSO | AG18: OR-ROM · ROMANTIQUE | AH18: PUB-CPL · Couple | AI18: ACC-PUB · ACC-PRV | AJ18: Évènements haut de gamme
A19: MARRAKECH | B19: HEBERGEMENT | C19: H005 | D19: INCONTOURNABLE | E19: {=IFERROR(INDEX(REF_CODES!$B$8:$B$13,MATCH($D19,REF_CODES!$C$8:$C$13,0)),"")} -> HB-INC | F19: Selman Marrakech | G19: 5 ETOILES | H19: BG3 · 500 – 800 € | I19: BP 24 530 Marrakech Atlas, KM 5, route d'Amizmiz | J19: Route d'Amizmiz | K19: 60 | L19: OUI | M19: 407 | N19: 750 | O19: 1200 | P19: NA | Q19: NA | R19: NA | S19: NA | T19: +212 524 45 96 00 | U19: À compléter | V19: info@selman-marrakech.com | W19: Mme Nihad Najdi | X19: https://www.selman-marrakech.com | Y19: @selmanmarrakech | Z19: https://facebook.com/selmanmarrakech | AA19: Coord. complétée(s) depuis annuaire : tél | AB19: ST-ULT · ULTRA EXCLUSIF | AC19: AMB-ROM · ROMANTIQUE | AD19: KD-CLB · KIDS CLUB | AE19: LAB-VIRT · VIRTUOSO | AF19: LAB-VIRT · VIRTUOSO | AG19: OR-ROM · ROMANTIQUE | AH19: PUB-CPL · Couple | AI19: ACC-PUB · ACC-PRV | AJ19: Mariages & événements privés
A20: MARRAKECH | B20: HEBERGEMENT | C20: H009 | D20: RIAD & PATRIMOINE | E20: {=IFERROR(INDEX(REF_CODES!$B$8:$B$13,MATCH($D20,REF_CODES!$C$8:$C$13,0)),"")} -> HB-RIA | F20: Le Farnatchi | G20: 5 ETOILES | H20: BG1 · Moins de 300 € | I20: 2 Derb El Farnatchi, Rue Souk El Fassis, Médina | J20: Médina | K20: 10 | L20: OUI | M20: 280 | N20: 400 | O20: 550 | P20: NA | Q20: NA | R20: NA | S20: NA | T20: +212 524 384 910 | U20: À compléter | V20: non trouvé | W20: Mr Naciri Mourad / DG : Mr Gamse Wix | X20: https://lefarnatchi.com | Y20: facebook.com/LeFarnatchi | Z20: NA | AA20: Coord. complétée(s) depuis annuaire : tél | AB20: ST-PRE · PREMIUM | AC20: AMB-ZEN · ZEN & BIEN-ÊTRE | AD20: KD-KFR · KIDS FRIENDLY | AE20: LVL-3 · 🔔🔔🔔 TROIS CLOCHES | AF20: À qualifier (labels / distinctions) | AG20: OR-ROM · ROMANTIQUE | AH20: PUB-CPL · Couple | AI20: ACC-PUB · ACC-PRV | AJ20: Évènements VIP
A21: MARRAKECH | B21: HEBERGEMENT | C21: H012 | D21: RIAD & PATRIMOINE | E21: {=IFERROR(INDEX(REF_CODES!$B$8:$B$13,MATCH($D21,REF_CODES!$C$8:$C$13,0)),"")} -> HB-RIA | F21: Riad Noir d'Ivoire | G21: Riad de luxe · boutique-hôtel 4★ (9 logements : 7 suites + 2 ch.) | H21: BG1 · Moins de 300 € | I21: 31-33 Derb Jdid, Bab Doukkala, Médina, 40000 | J21: Médina | K21: 9 | L21: OUI | M21: 160 | N21: NA | O21: NA | P21: NA | Q21: NA | R21: NA | S21: NA | T21: +212 524 37 76 07 / +212 524 380975 | U21: À compléter | V21: contact@noir-d-ivoire.com | W21: Direction Riad | X21: https://noir-d-ivoire.com | Y21: @riadnoirdivoire | Z21: NA | AA21: Coord. complétée(s) depuis annuaire : tél | AB21: ST-PRE · PREMIUM | AC21: AMB-ZEN · ZEN & BIEN-ÊTRE | AD21: KD-KFR · KIDS FRIENDLY | AE21: LVL-2 · 🔔🔔 DEUX CLOCHES | AF21: À qualifier (labels / distinctions) | AG21: OR-ROM · ROMANTIQUE | AH21: PUB-CPL · Couple | AI21: ACC-PUB · ACC-PRV | AJ21: Anniversaire
A22: MARRAKECH | B22: HEBERGEMENT | C22: H002 | D22: INCONTOURNABLE | E22: {=IFERROR(INDEX(REF_CODES!$B$8:$B$13,MATCH($D22,REF_CODES!$C$8:$C$13,0)),"")} -> HB-INC | F22: La Mamounia | G22: 5 ETOILES | H22: BG2 · 300 – 500 € | I22: Avenue Bab Jdid, 40040 Marrakech | J22: Hivernage | K22: 209 | L22: OUI | M22: 451 | N22: NA | O22: NA | P22: NA | Q22: NA | R22: NA | S22: NA | T22: +212 524 38 86 00 | U22: À compléter | V22: reservations@mamounia.com | W22: Mr Saad Chheb | X22: https://www.mamounia.com | Y22: @mamouniamarrakech | Z22: https://facebook.com/LaMamouniaMarrakech | AA22: Coord. complétée(s) depuis annuaire : tél | AB22: ST-ULT · ULTRA EXCLUSIF | AC22: AMB-ROM · ROMANTIQUE | AD22: KD-KFR · KIDS FRIENDLY | AE22: LVL-3 · 🔔🔔🔔 TROIS CLOCHES | AF22: LAB-VIRT · VIRTUOSO | AG22: OR-PRO · PROFESSIONNEL | AH22: PUB-GRP · Groupe | AI22: ACC-PUB · ACC-PRV | AJ22: Mariage, séminaire, privatisation
A23: MARRAKECH | B23: HEBERGEMENT | C23: H011 | D23: RIAD & PATRIMOINE | E23: {=IFERROR(INDEX(REF_CODES!$B$8:$B$13,MATCH($D23,REF_CODES!$C$8:$C$13,0)),"")} -> HB-RIA | F23: Riad El Fenn | G23: 4 ETOILES | H23: BG2 · 300 – 500 € | I23: 2 Derb Moulay Abdellah Ben Hezzian, Bab El Ksour, Médina | J23: Médina | K23: 41 | L23: OUI | M23: 310 | N23: NA | O23: NA | P23: NA | Q23: NA | R23: NA | S23: NA | T23: +212 524 44 12 10 | U23: À compléter | V23: non trouvé | W23: Vanessa Branson (propriétaire) / Mr Soufiane | X23: https://el-fenn.com | Y23: @el.fenn | Z23: https://facebook.com/ElFennMarrakech | AA23: Coord. complétée(s) depuis annuaire : tél | AB23: ST-PRE · PREMIUM | AC23: AMB-ZEN · ZEN & BIEN-ÊTRE | AD23: KD-KFR · KIDS FRIENDLY | AE23: LAB-MMS · MR & MRS SMITH | AF23: LAB-MMS · MR & MRS SMITH | AG23: OR-ROM · ROMANTIQUE | AH23: PUB-CPL · Couple | AI23: ACC-PUB · ACC-PRV | AJ23: Shooting, mode, influence
A24: MARRAKECH | B24: HEBERGEMENT | C24: H093 | D24: INCONTOURNABLE | E24: {=IFERROR(INDEX(REF_CODES!$B$8:$B$13,MATCH($D24,REF_CODES!$C$8:$C$13,0)),"")} -> HB-INC | F24: Fairmont Royal | G24: 5 ETOILES | H24: BG1 · Moins de 300 € | I24: Km 12, route d'Amizmiz | J24: Route d'Amizmiz | K24: 134 | L24: OUI | M24: 295 | N24: NA | O24: NA | P24: NA | Q24: NA | R24: NA | S24: NA | T24: +212 524 48 78 00 | U24: À compléter | V24: marrakech@fairmont.com | W24: à compléter | X24: https://royalpalmmarrakech.com | Y24: à compléter | Z24: @fairmontmarrakech | AA24: Importé de HEBERGEMENT. Quartier : Route d'Amizmiz · Site : https://royalpalmmarrakech.com | Coord. complétée(s) depuis annuaire : tél [Ancien statut: Importé] | AB24: ST-ULT · ULTRA EXCLUSIF | AC24: AMB-ROM · ROMANTIQUE | AD24: KD-CLB · KIDS CLUB | AE24: LAB-VIRT · VIRTUOSO | AF24: LAB-VIRT · VIRTUOSO | AG24: OR-ROM · ROMANTIQUE | AH24: PUB-CPL · Couple | AI24: ACC-PUB · ACC-PRV | AJ24: Mariage, séminaire, privatisation
A25: MARRAKECH | B25: HEBERGEMENT | C25: H013 | D25: RIAD & PATRIMOINE | E25: {=IFERROR(INDEX(REF_CODES!$B$8:$B$13,MATCH($D25,REF_CODES!$C$8:$C$13,0)),"")} -> HB-RIA | F25: Riad Kheirredine | G25: Maison d'hôtes · riad (cat. maison d'hôtes) | H25: BG1 · Moins de 300 € | I25: 2, Derb Chelligui, Sidi Ben Slimane, Médina | J25: Médina | K25: 10 | L25: OUI | M25: 200 | N25: 300 | O25: 420 | P25: NA | Q25: NA | R25: NA | S25: NA | T25: +212 524 386 364 | U25: À compléter | V25: book@riadkheirredine.com | W25: Direction Riad | X25: https://www.riadkheirredine.com | Y25: @riadkheirredine | Z25: NA | AA25: Coord. complétée(s) depuis annuaire : tél | AB25: ST-PRE · PREMIUM | AC25: AMB-ZEN · ZEN & BIEN-ÊTRE | AD25: KD-KFR · KIDS FRIENDLY | AE25: LVL-2 · 🔔🔔 DEUX CLOCHES | AF25: À qualifier (labels / distinctions) | AG25: OR-ROM · ROMANTIQUE | AH25: PUB-CPL · Couple | AI25: ACC-PUB · ACC-PRV | AJ25: Privatisation, anniversaire
A26: MARRAKECH | B26: HEBERGEMENT | C26: H014 | D26: RIAD & PATRIMOINE | E26: {=IFERROR(INDEX(REF_CODES!$B$8:$B$13,MATCH($D26,REF_CODES!$C$8:$C$13,0)),"")} -> HB-RIA | F26: Riad 72 | G26: Maison d'hôtes · riad (cat. maison d'hôtes) | H26: BG1 · Moins de 300 € | I26: 72 Arset Aouzal, Bab Doukkala | J26: Médina | K26: non trouvé | L26: OUI | M26: 180 | N26: NA | O26: NA | P26: NA | Q26: NA | R26: NA | S26: NA | T26: +212 524 38 76 29 | U26: À compléter | V26: info@riad72.com | W26: Direction commerciale | X26: https://www.riad72.com | Y26: @riad72 | Z26: NA | AA26: Coord. complétée(s) depuis annuaire : tél | AB26: ST-PRE · PREMIUM | AC26: AMB-ZEN · ZEN & BIEN-ÊTRE | AD26: KD-KFR · KIDS FRIENDLY | AE26: LVL-1 · 🔔 UNE CLOCHE | AF26: À qualifier (labels / distinctions) | AG26: OR-ROM · ROMANTIQUE | AH26: PUB-CPL · Couple | AI26: ACC-PUB · ACC-PRV | AJ26: Privatisation, anniversaire
A27: MARRAKECH | B27: HEBERGEMENT | C27: H015 | D27: RIAD & PATRIMOINE | E27: {=IFERROR(INDEX(REF_CODES!$B$8:$B$13,MATCH($D27,REF_CODES!$C$8:$C$13,0)),"")} -> HB-RIA | F27: Riad Mena & Beyond | G27: Maison d'hôtes · riad (cat. maison d'hôtes) | H27: BG1 · Moins de 300 € | I27: 70 Derb J'Did, Douar Graoua, Médina | J27: Médina | K27: 7 | L27: OUI | M27: 250 | N27: NA | O27: NA | P27: NA | Q27: NA | R27: NA | S27: NA | T27: +212 524 38 18 28 | U27: À compléter | V27: non trouvé | W27: Mme Philomena / Direction Générale | X27: riadmenaandbeyond.com | Y27: @riadmena | Z27: NA | AA27: Coord. complétée(s) depuis annuaire : email, tél | AB27: ST-PRE · PREMIUM | AC27: AMB-ZEN · ZEN & BIEN-ÊTRE | AD27: KD-KFR · KIDS FRIENDLY | AE27: LVL-2 · 🔔🔔 DEUX CLOCHES | AF27: À qualifier (labels / distinctions) | AG27: OR-ROM · ROMANTIQUE | AH27: PUB-CPL · Couple | AI27: ACC-PUB · ACC-PRV | AJ27: Couple premium
A28: MARRAKECH | B28: HEBERGEMENT | C28: H017 | D28: RIAD & PATRIMOINE | E28: {=IFERROR(INDEX(REF_CODES!$B$8:$B$13,MATCH($D28,REF_CODES!$C$8:$C$13,0)),"")} -> HB-RIA | F28: Riad Due | G28: Maison d'hôtes · riad (cat. maison d'hôtes) | H28: BG1 · Moins de 300 € | I28: 2 Derb Chantouf, Riad Larousse, Médina | J28: Médina | K28: 4 | L28: OUI | M28: 200 | N28: 300 | O28: 450 | P28: NA | Q28: NA | R28: NA | S28: NA | T28: +212 524 38 76 87 / +212 524 378 864 | U28: À compléter | V28: info@riaddue.net | W28: Direction (Eleni) | X28: riaddue.net | Y28: @riaddueboutiquehotel | Z28: NA | AA28: Recherche web : email/Instagram/direction renseignés ; site riaddue.com | Coord. complétée(s) depuis annuaire : tél [Ancien statut: Complété ✦] | AB28: ST-PRE · PREMIUM | AC28: AMB-ZEN · ZEN & BIEN-ÊTRE | AD28: KD-KFR · KIDS FRIENDLY | AE28: LVL-1 · 🔔 UNE CLOCHE | AF28: À qualifier (labels / distinctions) | AG28: OR-ROM · ROMANTIQUE | AH28: PUB-CPL · Couple | AI28: ACC-PUB · ACC-PRV | AJ28: Privatisation, anniversaire
A29: MARRAKECH | B29: HEBERGEMENT | C29: H044 | D29: RIAD & PATRIMOINE | E29: {=IFERROR(INDEX(REF_CODES!$B$8:$B$13,MATCH($D29,REF_CODES!$C$8:$C$13,0)),"")} -> HB-RIA | F29: Riad Le Yasmine | G29: Maison d'hôtes · riad (cat. maison d'hôtes) | H29: BG1 · Moins de 300 € | I29: 209 Rue Ank Jemel, Bab Taghzout | J29: Médina | K29: 8 | L29: OUI | M29: 150 | N29: 220 | O29: 300 | P29: NA | Q29: NA | R29: NA | S29: NA | T29: +212 524 377 012 | U29: À compléter | V29: leriadyasmine@gmail.com | W29: Mr Gabriel / Direction | X29: https://www.riad-yasmine.com | Y29: @riadyasmine | Z29: NA | AA29: Coord. complétée(s) depuis annuaire : tél | Fusion doublons : Riad Yasmine (H044) | AB29: ST-PRE · PREMIUM | AC29: AMB-ZEN · ZEN & BIEN-ÊTRE | AD29: KD-KFR · KIDS FRIENDLY | AE29: LVL-3 · 🔔🔔🔔 TROIS CLOCHES | AF29: À qualifier (labels / distinctions) | AG29: OR-ROM · ROMANTIQUE | AH29: PUB-CPL · Couple | AI29: ACC-PUB · ACC-PRV | AJ29: Influence, Instagram
A30: MARRAKECH | B30: HEBERGEMENT | C30: H045 | D30: RIAD & PATRIMOINE | E30: {=IFERROR(INDEX(REF_CODES!$B$8:$B$13,MATCH($D30,REF_CODES!$C$8:$C$13,0)),"")} -> HB-RIA | F30: Riad Brummell Medina | G30: Maison d'hôtes · riad (cat. maison d'hôtes) | H30: BG1 · Moins de 300 € | I30: 20 Derb Assabbane | J30: Médina | K30: 5 | L30: OUI | M30: 180 | N30: 250 | O30: 350 | P30: NA | Q30: NA | R30: NA | S30: NA | T30: +212 524 38 58 06 | U30: À compléter | V30: salam@riadbrummell.com | W30: Direction | X30: https://riadbrummell.brummellprojects.com | Y30: @brummellmedina | Z30: NA | AA30: Coord. complétée(s) depuis annuaire : tél | AB30: ST-PRE · PREMIUM | AC30: AMB-ZEN · ZEN & BIEN-ÊTRE | AD30: KD-KFR · KIDS FRIENDLY | AE30: LAB-MMS · MR & MRS SMITH | AF30: LAB-MMS · MR & MRS SMITH | AG30: OR-ROM · ROMANTIQUE | AH30: PUB-CPL · Couple | AI30: ACC-PUB · ACC-PRV | AJ30: Privatisation, anniversaire
A31: MARRAKECH | B31: HEBERGEMENT | C31: H046 | D31: RIAD & PATRIMOINE | E31: {=IFERROR(INDEX(REF_CODES!$B$8:$B$13,MATCH($D31,REF_CODES!$C$8:$C$13,0)),"")} -> HB-RIA | F31: Riad Kniza | G31: Maison d'hôtes · riad (cat. maison d'hôtes) | H31: BG1 · Moins de 300 € | I31: 34 Derb l'Hôtel, Bab Doukkala | J31: Médina | K31: 11 | L31: OUI | M31: 220 | N31: 320 | O31: 450 | P31: NA | Q31: NA | R31: NA | S31: NA | T31: +212 524 37 69 42 | U31: À compléter | V31: non trouvé | W31: Mr Kamal / Resp Commercial | X31: https://riadkniza.com | Y31: @riadkniza | Z31: NA | AA31: Coord. complétée(s) depuis annuaire : tél | AB31: ST-PRE · PREMIUM | AC31: AMB-ZEN · ZEN & BIEN-ÊTRE | AD31: KD-KFR · KIDS FRIENDLY | AE31: LVL-2 · 🔔🔔 DEUX CLOCHES | AF31: À qualifier (labels / distinctions) | AG31: OR-ROM · ROMANTIQUE | AH31: PUB-CPL · Couple | AI31: ACC-PUB · ACC-PRV | AJ31: Privatisation, anniversaire
A32: MARRAKECH | B32: HEBERGEMENT | C32: H084 | D32: RIAD & PATRIMOINE | E32: {=IFERROR(INDEX(REF_CODES!$B$8:$B$13,MATCH($D32,REF_CODES!$C$8:$C$13,0)),"")} -> HB-RIA | F32: Riad Livia Marrakech - Adults Only | G32: Maison d'hôtes · riad (cat. maison d'hôtes) | H32: BG1 · Moins de 300 € | I32: 36 SIDI AYOUB DERB EL ARSA, Médina | J32: Médina | K32: 5 | L32: OUI | M32: 150 | N32: 200 | O32: 280 | P32: NA | Q32: NA | R32: NA | S32: Adults Only | T32: +212 808 666 132 | U32: À compléter | V32: info@riad-livia.com | W32: à compléter | X32: https://www.riad-livia.com | Y32: @riadlivia | Z32: NA | AA32: Importé de HEBERGEMENT. Quartier : Médina · Site : https://www.riad-livia.com | Coord. complétée(s) depuis annuaire : tél [Ancien statut: Importé] | AB32: ST-PRE · PREMIUM | AC32: AMB-ZEN · ZEN & BIEN-ÊTRE | AD32: — Adults only (pas d'équipement enfants) | AE32: LVL-1 · 🔔 UNE CLOCHE | AF32: À qualifier (labels / distinctions) | AG32: OR-ROM · ROMANTIQUE | AH32: PUB-ADU · Adultes uniquement | AI32: ACC-PUB · ACC-PRV | AJ32: Anniversaire
A33: MARRAKECH | B33: HEBERGEMENT | C33: H090 | D33: RIAD & PATRIMOINE | E33: {=IFERROR(INDEX(REF_CODES!$B$8:$B$13,MATCH($D33,REF_CODES!$C$8:$C$13,0)),"")} -> HB-RIA | F33: Riad Al Rimal & Spa | G33: Maison d'hôtes · riad (cat. maison d'hôtes) | H33: BG1 · Moins de 300 € | I33: 43 Derb Fahl Ezzafriti Quartier Laksour , Médina, | J33: Médina | K33: 17 | L33: OUI | M33: 120 | N33: 200 | O33: 280 | P33: NA | Q33: NA | R33: NA | S33: NA | T33: +212 661 582972 | U33: +212 661582972 (à confirmer) | V33: non trouvé | W33: à compléter | X33: https://www.riad-alrimal.com | Y33: @riadalrimal | Z33: NA | AA33: Importé de HEBERGEMENT. Quartier : Médina · Site : https://www.riad-alrimal.com | Coord. complétée(s) depuis annuaire : tél [Ancien statut: À compléter] | AB33: ST-PRE · PREMIUM | AC33: AMB-ZEN · ZEN & BIEN-ÊTRE | AD33: KD-KFR · KIDS FRIENDLY | AE33: LVL-2 · 🔔🔔 DEUX CLOCHES | AF33: À qualifier (labels / distinctions) | AG33: OR-ROM · ROMANTIQUE | AH33: PUB-CPL · Couple | AI33: ACC-PUB · ACC-PRV | AJ33: Anniversaire, groupe
A34: MARRAKECH | B34: HEBERGEMENT | C34: H091 | D34: RIAD & PATRIMOINE | E34: {=IFERROR(INDEX(REF_CODES!$B$8:$B$13,MATCH($D34,REF_CODES!$C$8:$C$13,0)),"")} -> HB-RIA | F34: Riad Anaqa | G34: Maison d'hôtes · riad (cat. maison d'hôtes) | H34: BG1 · Moins de 300 € | I34: 184, 185 Arset Aouzal Road, | J34: Médina | K34: non trouvé | L34: OUI | M34: 250 | N34: NA | O34: NA | P34: NA | Q34: 5 | R34: 250 | S34: Villa 5 CH: 250 | T34: +212 664 838694 | U34: +212 664838694 (à confirmer) | V34: reservations@anaqa-signature.com | W34: à compléter | X34: https://www.riad-anaqa.com | Y34: @anaqasignature | Z34: NA | AA34: Importé de HEBERGEMENT. Quartier : Médina · Site : https://www.riad-anaqa.com | Coord. complétée(s) depuis annuaire : tél [Ancien statut: Importé] | Villa(s) privatisable(s) déplacée(s) → HB-COL | AB34: ST-PRE · PREMIUM | AC34: AMB-ZEN · ZEN & BIEN-ÊTRE | AD34: KD-KFR · KIDS FRIENDLY | AE34: LVL-2 · 🔔🔔 DEUX CLOCHES | AF34: À qualifier (labels / distinctions) | AG34: OR-ROM · ROMANTIQUE | AH34: PUB-CPL · Couple | AI34: ACC-PUB · ACC-PRV | AJ34: Privatisation complète
A35: MARRAKECH | B35: HEBERGEMENT | C35: H094 | D35: RIAD & PATRIMOINE | E35: {=IFERROR(INDEX(REF_CODES!$B$8:$B$13,MATCH($D35,REF_CODES!$C$8:$C$13,0)),"")} -> HB-RIA | F35: Sakkan | G35: À confirmer (catégorie / classement) | H35: BG1 · Moins de 300 € | I35: 43 Rue Sidi Yamani, Mouassine | J35: Médina | K35: 12 | L35: OUI | M35: 210 | N35: 310 | O35: 350 | P35: NA | Q35: NA | R35: NA | S35: NA | T35: +212 6 62 67 02 90 | U35: +212 662670290 (à confirmer) | V35: info@riadsakkan.com | W35: à compléter | X35: https://riadsakkan.com | Y35: @riadsakkan | Z35: NA | AA35: Importé de HEBERGEMENT. Quartier : Médina · Site : https://riadsakkan.com | Coord. complétée(s) depuis annuaire : tél [Ancien statut: Importé] | AB35: ST-PRE · PREMIUM | AC35: AMB-ZEN · ZEN & BIEN-ÊTRE | AD35: KD-KFR · KIDS FRIENDLY | AE35: LVL-2 · 🔔🔔 DEUX CLOCHES | AF35: À qualifier (labels / distinctions) | AG35: OR-ROM · ROMANTIQUE | AH35: PUB-CPL · Couple | AI35: ACC-PUB · ACC-PRV | AJ35: Privatisation
A36: MARRAKECH | B36: HEBERGEMENT | C36: H095 | D36: RIAD & PATRIMOINE | E36: {=IFERROR(INDEX(REF_CODES!$B$8:$B$13,MATCH($D36,REF_CODES!$C$8:$C$13,0)),"")} -> HB-RIA | F36: Dar Seven | G36: Maison d'hôtes · riad (cat. maison d'hôtes) | H36: BG1 · Moins de 300 € | I36: 7 Derb Ben Moussa, Kaa Sour, Sidi Benslimane | J36: Médina (Sidi Benslimane) | K36: 5 | L36: OUI | M36: 200 | N36: 280 | O36: 400 | P36: NA | Q36: NA | R36: NA | S36: NA | T36: +39 347 743 4272 | U36: À compléter | V36: info@darseven.com | W36: N° de tél. italien (propriétaires) — pas de fixe marocain publié | X36: https://www.darseven.com | Y36: @darsevenmarrakech | Z36: NA | AA36: Importé de HEBERGEMENT. Quartier : Médina (Sidi Benslimane) · Site : https://www.darseven.com | Coord. complétée(s) depuis annuaire : tél [Ancien statut: Importé] | AB36: ST-PRE · PREMIUM | AC36: AMB-ZEN · ZEN & BIEN-ÊTRE | AD36: KD-KFR · KIDS FRIENDLY | AE36: LVL-2 · 🔔🔔 DEUX CLOCHES | AF36: À qualifier (labels / distinctions) | AG36: OR-ROM · ROMANTIQUE | AH36: PUB-CPL · Couple | AI36: ACC-PUB · ACC-PRV | AJ36: Privatisation
A37: MARRAKECH | B37: HEBERGEMENT | C37: H096 | D37: RIAD & PATRIMOINE | E37: {=IFERROR(INDEX(REF_CODES!$B$8:$B$13,MATCH($D37,REF_CODES!$C$8:$C$13,0)),"")} -> HB-RIA | F37: Dar Zemora | G37: Maison d'hôtes · riad (cat. maison d'hôtes) | H37: BG1 · Moins de 300 € | I37: 72 Rue El Aandalib, Palmeraie | J37: Palmeraie | K37: 6 | L37: OUI | M37: 160 | N37: NA | O37: 292 | P37: NA | Q37: 2 | R37: 640 | S37: Villa 2 CH: 640 | T37: +44 7913 152195 | U37: À compléter | V37: lindsay@darzemora.com | W37: à compléter | X37: https://darzemora.com | Y37: @darzemora | Z37: NA | AA37: Importé de HEBERGEMENT. Quartier : Palmeraie · Site : https://darzemora.com | Coord. complétée(s) depuis annuaire : tél [Ancien statut: Importé] | Villa(s) privatisable(s) déplacée(s) → HB-COL | AB37: ST-PRE · PREMIUM | AC37: AMB-ZEN · ZEN & BIEN-ÊTRE | AD37: KD-CLB · KIDS CLUB | AE37: LVL-2 · 🔔🔔 DEUX CLOCHES | AF37: À qualifier (labels / distinctions) | AG37: OR-ROM · ROMANTIQUE | AH37: PUB-CPL · Couple | AI37: ACC-PUB · ACC-PRV | AJ37: Mariage intimiste
A38: MARRAKECH | B38: HEBERGEMENT | C38: H097 | D38: RIAD & PATRIMOINE | E38: {=IFERROR(INDEX(REF_CODES!$B$8:$B$13,MATCH($D38,REF_CODES!$C$8:$C$13,0)),"")} -> HB-RIA | F38: Riad Jaaneman | G38: Maison d'hôtes · riad (cat. maison d'hôtes) | H38: BG1 · Moins de 300 € | I38: 12 Derb Sraghna, Dar El Bacha, Médina, 40000 | J38: Médina | K38: 5 | L38: OUI | M38: 180 | N38: 250 | O38: 350 | P38: NA | Q38: NA | R38: NA | S38: NA | T38: +212 524 382164 | U38: À compléter | V38: info@riadjaaneman.com | W38: à compléter | X38: https://www.riadjaaneman.com | Y38: @riadjaaneman | Z38: NA | AA38: Importé de HEBERGEMENT. Quartier : Médina · Site : https://www.riadjaaneman.com | Coord. complétée(s) depuis annuaire : tél [Ancien statut: Importé] | AB38: ST-PRE · PREMIUM | AC38: AMB-ZEN · ZEN & BIEN-ÊTRE | AD38: KD-KFR · KIDS FRIENDLY | AE38: LAB-MMS · MR & MRS SMITH | AF38: LAB-MMS · MR & MRS SMITH | AG38: OR-ROM · ROMANTIQUE | AH38: PUB-CPL · Couple | AI38: ACC-PUB · ACC-PRV | AJ38: Privatisation
A39: MARRAKECH | B39: HEBERGEMENT | C39: H099 | D39: RIAD & PATRIMOINE | E39: {=IFERROR(INDEX(REF_CODES!$B$8:$B$13,MATCH($D39,REF_CODES!$C$8:$C$13,0)),"")} -> HB-RIA | F39: Riad Olema et Spa | G39: Maison d'hôtes · riad (cat. maison d'hôtes) | H39: BG1 · Moins de 300 € | I39: 31-32 Derb Sidi Ahmed ou Moussa, Bab Doukkala | J39: Médina | K39: 15 | L39: OUI | M39: 150 | N39: 220 | O39: 300 | P39: NA | Q39: NA | R39: NA | S39: NA | T39: +212 524 378 288 | U39: À compléter | V39: adm.riadolema@gmail.com | W39: à compléter | X39: https://www.riadolema-spa.com | Y39: @riadolema | Z39: NA | AA39: Importé de HEBERGEMENT. Quartier : Médina · Site : https://www.riadolema-spa.com | Coord. complétée(s) depuis annuaire : tél [Ancien statut: Importé] | AB39: ST-PRE · PREMIUM | AC39: AMB-ZEN · ZEN & BIEN-ÊTRE | AD39: KD-KFR · KIDS FRIENDLY | AE39: LVL-2 · 🔔🔔 DEUX CLOCHES | AF39: À qualifier (labels / distinctions) | AG39: OR-ROM · ROMANTIQUE | AH39: PUB-CPL · Couple | AI39: ACC-PUB · ACC-PRV | AJ39: Mariage intimiste
A40: MARRAKECH | B40: HEBERGEMENT | C40: H100 | D40: RIAD & PATRIMOINE | E40: {=IFERROR(INDEX(REF_CODES!$B$8:$B$13,MATCH($D40,REF_CODES!$C$8:$C$13,0)),"")} -> HB-RIA | F40: Riad Houdou | G40: Maison d'hôtes · riad (cat. maison d'hôtes) | H40: BG1 · Moins de 300 € | I40: Rue Essebtiyne, n°54 Derb el Hammam, quartier Moukef, Médina | J40: Médina | K40: 10 | L40: OUI | M40: 85 | N40: NA | O40: NA | P40: NA | Q40: NA | R40: NA | S40: NA | T40: +212 5 24 38 37 93 / +212 6 08 86 40 72 | U40: +212 608864072 (à confirmer) | V40: le.riad.houdou@gmail.com | W40: à compléter | X40: riadhoudou.com | Y40: @riadhoudou | Z40: NA | AA40: Importé de HEBERGEMENT. Quartier : Médina · Site : riadhoudou.com | Coord. complétée(s) depuis annuaire : tél [Ancien statut: Importé] | AB40: ST-PRE · PREMIUM | AC40: AMB-ZEN · ZEN & BIEN-ÊTRE | AD40: KD-KFR · KIDS FRIENDLY | AE40: LVL-1 · 🔔 UNE CLOCHE | AF40: À qualifier (labels / distinctions) | AG40: OR-ROM · ROMANTIQUE | AH40: PUB-CPL · Couple | AI40: ACC-PUB · ACC-PRV | AJ40: Groupe amis
A41: MARRAKECH | B41: HEBERGEMENT | C41: H101 | D41: RIAD & PATRIMOINE | E41: {=IFERROR(INDEX(REF_CODES!$B$8:$B$13,MATCH($D41,REF_CODES!$C$8:$C$13,0)),"")} -> HB-RIA | F41: Riad Idra | G41: Maison d'hôtes · riad (cat. maison d'hôtes) | H41: BG1 · Moins de 300 € | I41: 105 Derb Tizougarine, Dar El Bacha | J41: Médina | K41: 7 | L41: OUI | M41: 200 | N41: 280 | O41: 400 | P41: NA | Q41: NA | R41: NA | S41: NA | T41: +212 524 391 776 | U41: À compléter | V41: contact@riadidra.com | W41: à compléter | X41: https://www.riad-idra-marrakech.com | Y41: @riadidra | Z41: NA | AA41: Importé de HEBERGEMENT. Quartier : Médina · Site : https://www.riad-idra-marrakech.com | Coord. complétée(s) depuis annuaire : tél [Ancien statut: Importé] | Fusion doublons : Riad Idra (H101) | AB41: ST-PRE · PREMIUM | AC41: AMB-ZEN · ZEN & BIEN-ÊTRE | AD41: KD-KFR · KIDS FRIENDLY | AE41: LVL-2 · 🔔🔔 DEUX CLOCHES | AF41: À qualifier (labels / distinctions) | AG41: OR-ROM · ROMANTIQUE | AH41: PUB-CPL · Couple | AI41: ACC-PUB · ACC-PRV | AJ41: Anniversaire
A42: MARRAKECH | B42: HEBERGEMENT | C42: H102 | D42: RIAD & PATRIMOINE | E42: {=IFERROR(INDEX(REF_CODES!$B$8:$B$13,MATCH($D42,REF_CODES!$C$8:$C$13,0)),"")} -> HB-RIA | F42: Dar Anika | G42: Maison d'hôtes · riad (cat. maison d'hôtes) | H42: BG1 · Moins de 300 € | I42: Quartier Kennaria, Médina | J42: Médina | K42: 12 | L42: OUI | M42: 150 | N42: NA | O42: NA | P42: NA | Q42: NA | R42: NA | S42: NA | T42: +212 5 24 39 17 51 | U42: À compléter | V42: non trouvé | W42: email non trouvé (formulaire) | X42: riadanika.com | Y42: @daranika | Z42: https://facebook.com/Anikamarrakech2022 | AA42: Importé de HEBERGEMENT. Quartier : Médina · Site : riadanika.com [Ancien statut: À compléter] | Fusion doublons : Riad Anika (H102) | AB42: ST-PRE · PREMIUM | AC42: AMB-ZEN · ZEN & BIEN-ÊTRE | AD42: KD-KFR · KIDS FRIENDLY | AE42: LVL-2 · 🔔🔔 DEUX CLOCHES | AF42: À qualifier (labels / distinctions) | AG42: OR-ROM · ROMANTIQUE | AH42: PUB-CPL · Couple | AI42: ACC-PUB · ACC-PRV | AJ42: Privatisation
A43: MARRAKECH | B43: HEBERGEMENT | C43: H103 | D43: RIAD & PATRIMOINE | E43: {=IFERROR(INDEX(REF_CODES!$B$8:$B$13,MATCH($D43,REF_CODES!$C$8:$C$13,0)),"")} -> HB-RIA | F43: Riad Houma | G43: Maison d'hôtes · riad (cat. maison d'hôtes) | H43: BG1 · Moins de 300 € | I43: 49 Kaa El Houma, Riad Zitoune Jdid, Médina | J43: Médina | K43: 8 | L43: OUI | M43: 90 | N43: NA | O43: NA | P43: NA | Q43: NA | R43: NA | S43: NA | T43: +212 662 628 942 | U43: +212 662628942 (à confirmer) | V43: riadhouma.marrakech@gmail.com | W43: à compléter | X43: riadhoumamarrakech.com | Y43: @riadhouma | Z43: NA | AA43: Importé de HEBERGEMENT. Quartier : Médina · Site : riadhoumamarrakech.com | Coord. complétée(s) depuis annuaire : tél [Ancien statut: Importé] | AB43: ST-PRE · PREMIUM | AC43: AMB-ZEN · ZEN & BIEN-ÊTRE | AD43: KD-KFR · KIDS FRIENDLY | AE43: LVL-1 · 🔔 UNE CLOCHE | AF43: À qualifier (labels / distinctions) | AG43: OR-ROM · ROMANTIQUE | AH43: PUB-CPL · Couple | AI43: ACC-PUB · ACC-PRV | AJ43: Groupe
A44: MARRAKECH | B44: HEBERGEMENT | C44: H104 | D44: RIAD & PATRIMOINE | E44: {=IFERROR(INDEX(REF_CODES!$B$8:$B$13,MATCH($D44,REF_CODES!$C$8:$C$13,0)),"")} -> HB-RIA | F44: Dar Sabra | G44: Maison d'hôtes · riad (cat. maison d'hôtes) | H44: BG1 · Moins de 300 € | I44: Circuit de la Palmeraie, Douar Abiad | J44: Palmeraie | K44: 22 | L44: OUI | M44: 116 | N44: NA | O44: NA | P44: NA | Q44: NA | R44: NA | S44: NA | T44: +212 524 329 172 | U44: À compléter | V44: non trouvé | W44: à compléter | X44: darsabra-marrakech.com | Y44: @darsabra | Z44: NA | AA44: Importé de HEBERGEMENT. Quartier : Palmeraie · Site : darsabra-marrakech.com | Coord. complétée(s) depuis annuaire : tél [Ancien statut: À compléter] | AB44: ST-PRE · PREMIUM | AC44: AMB-ZEN · ZEN & BIEN-ÊTRE | AD44: KD-CLB · KIDS CLUB | AE44: LVL-2 · 🔔🔔 DEUX CLOCHES | AF44: À qualifier (labels / distinctions) | AG44: OR-ROM · ROMANTIQUE | AH44: PUB-CPL · Couple | AI44: ACC-PUB · ACC-PRV | AJ44: Shooting photo
A45: MARRAKECH | B45: HEBERGEMENT | C45: H105 | D45: RIAD & PATRIMOINE | E45: {=IFERROR(INDEX(REF_CODES!$B$8:$B$13,MATCH($D45,REF_CODES!$C$8:$C$13,0)),"")} -> HB-RIA | F45: Riyad Al Moussika | G45: À confirmer (catégorie / classement) | H45: BG1 · Moins de 300 € | I45: 62 Derb Boutouil, Kennaria | J45: Médina | K45: 5 | L45: OUI | M45: 180 | N45: 250 | O45: 350 | P45: NA | Q45: NA | R45: NA | S45: NA | T45: +212 524 389067 | U45: À compléter | V45: non trouvé | W45: à compléter | X45: http://www.riyad-al-moussika.com | Y45: @almoussika | Z45: NA | AA45: Importé de HEBERGEMENT. Quartier : Médina · Site : http://www.riyad-al-moussika.com | Coord. complétée(s) depuis annuaire : tél [Ancien statut: À compléter] | AB45: ST-PRE · PREMIUM | AC45: AMB-ZEN · ZEN & BIEN-ÊTRE | AD45: KD-KFR · KIDS FRIENDLY | AE45: LVL-2 · 🔔🔔 DEUX CLOCHES | AF45: À qualifier (labels / distinctions) | AG45: OR-ROM · ROMANTIQUE | AH45: PUB-CPL · Couple | AI45: ACC-PUB · ACC-PRV | AJ45: Mariage intimiste
A46: MARRAKECH | B46: HEBERGEMENT | C46: H106 | D46: RIAD & PATRIMOINE | E46: {=IFERROR(INDEX(REF_CODES!$B$8:$B$13,MATCH($D46,REF_CODES!$C$8:$C$13,0)),"")} -> HB-RIA | F46: Elegancia Riad Boutique & SPA | G46: À confirmer (catégorie / classement) | H46: BG1 · Moins de 300 € | I46: 23 Derb Zaouia, Bab Doukkala, Médina | J46: Médina | K46: 11 | L46: OUI | M46: 176 | N46: NA | O46: NA | P46: NA | Q46: NA | R46: NA | S46: NA | T46: +212 524 386 980 | U46: À compléter | V46: info@riadelegancia.com | W46: à compléter | X46: non trouvé | Y46: @riadelegancia | Z46: NA | AA46: Importé de HEBERGEMENT. Quartier : Médina | Coord. complétée(s) depuis annuaire : tél [Ancien statut: Importé] | AB46: ST-PRE · PREMIUM | AC46: AMB-ZEN · ZEN & BIEN-ÊTRE | AD46: KD-KFR · KIDS FRIENDLY | AE46: LVL-2 · 🔔🔔 DEUX CLOCHES | AF46: À qualifier (labels / distinctions) | AG46: OR-ROM · ROMANTIQUE | AH46: PUB-CPL · Couple | AI46: ACC-PUB · ACC-PRV | AJ46: Anniversaire
A47: MARRAKECH | B47: HEBERGEMENT | C47: H107 | D47: RIAD & PATRIMOINE | E47: {=IFERROR(INDEX(REF_CODES!$B$8:$B$13,MATCH($D47,REF_CODES!$C$8:$C$13,0)),"")} -> HB-RIA | F47: Riad Kbour & Chou | G47: Maison d'hôtes · riad (cat. maison d'hôtes) | H47: BG1 · Moins de 300 € | I47: Nord-ouest de la médina (près Bab Doukkala / Majorelle) | J47: Médina | K47: 7 | L47: OUI | M47: 144 | N47: NA | O47: NA | P47: NA | Q47: NA | R47: NA | S47: NA | T47: +212 6 75 06 54 70 | U47: À compléter | V47: non trouvé | W47: tél/email non trouvés (formulaire) | X47: riadkbourchou.com | Y47: @riadkbourchou | Z47: NA | AA47: Importé de HEBERGEMENT. Quartier : Médina · Site : riadkbourchou.com [Ancien statut: À compléter] | AB47: ST-PRE · PREMIUM | AC47: AMB-ZEN · ZEN & BIEN-ÊTRE | AD47: KD-KFR · KIDS FRIENDLY | AE47: LVL-2 · 🔔🔔 DEUX CLOCHES | AF47: À qualifier (labels / distinctions) | AG47: OR-ROM · ROMANTIQUE | AH47: PUB-CPL · Couple | AI47: ACC-PUB · ACC-PRV | AJ47: Privatisation
A48: MARRAKECH | B48: HEBERGEMENT | C48: H108 | D48: RIAD & PATRIMOINE | E48: {=IFERROR(INDEX(REF_CODES!$B$8:$B$13,MATCH($D48,REF_CODES!$C$8:$C$13,0)),"")} -> HB-RIA | F48: Riad Azzar | G48: Maison d'hôtes · riad (cat. maison d'hôtes) | H48: BG1 · Moins de 300 € | I48: 94 Derb Moulay Abdelkader, Derb Dabachi | J48: Médina | K48: 6 | L48: OUI | M48: 170 | N48: 240 | O48: 320 | P48: NA | Q48: NA | R48: NA | S48: NA | T48: +39 346 606 0622 | U48: À compléter | V48: non trouvé | W48: tél non confirmé (mobile +212 661 158 179 via annuaire non officiel — à vérifier) | X48: https://www.riadazzar.com | Y48: @riadazzar | Z48: NA | AA48: Importé de HEBERGEMENT. Quartier : Médina · Site : https://www.riadazzar.com [Ancien statut: À compléter] | AB48: ST-PRE · PREMIUM | AC48: AMB-ZEN · ZEN & BIEN-ÊTRE | AD48: KD-KFR · KIDS FRIENDLY | AE48: LVL-2 · 🔔🔔 DEUX CLOCHES | AF48: À qualifier (labels / distinctions) | AG48: OR-ROM · ROMANTIQUE | AH48: PUB-CPL · Couple | AI48: ACC-PUB · ACC-PRV | AJ48: Anniversaire
A49: MARRAKECH | B49: HEBERGEMENT | C49: H109 | D49: RIAD & PATRIMOINE | E49: {=IFERROR(INDEX(REF_CODES!$B$8:$B$13,MATCH($D49,REF_CODES!$C$8:$C$13,0)),"")} -> HB-RIA | F49: Riad Karmela Princesse | G49: Maison d'hôtes · riad (cat. maison d'hôtes) | H49: BG1 · Moins de 300 € | I49: 4 Derb El Ferrane, Azbezt, Place Ben Salah | J49: Médina | K49: 10 | L49: OUI | M49: 200 | N49: 280 | O49: 380 | P49: NA | Q49: NA | R49: NA | S49: NA | T49: +212 524 387937 | U49: À compléter | V49: info@riadkarmelaprincesse.com | W49: à compléter | X49: https://www.riadkarmelaprincesse.com | Y49: @riadkarmela | Z49: NA | AA49: Importé de HEBERGEMENT. Quartier : Médina · Site : https://www.riadkarmelaprincesse.com | Coord. complétée(s) depuis annuaire : tél [Ancien statut: Importé] | AB49: ST-PRE · PREMIUM | AC49: AMB-ZEN · ZEN & BIEN-ÊTRE | AD49: KD-KFR · KIDS FRIENDLY | AE49: LVL-2 · 🔔🔔 DEUX CLOCHES | AF49: À qualifier (labels / distinctions) | AG49: OR-ROM · ROMANTIQUE | AH49: PUB-CPL · Couple | AI49: ACC-PUB · ACC-PRV | AJ49: Mariage intimiste
A50: MARRAKECH | B50: HEBERGEMENT | C50: H110 | D50: RIAD & PATRIMOINE | E50: {=IFERROR(INDEX(REF_CODES!$B$8:$B$13,MATCH($D50,REF_CODES!$C$8:$C$13,0)),"")} -> HB-RIA | F50: Riad Danka | G50: Maison d'hôtes · riad (cat. maison d'hôtes) | H50: BG1 · Moins de 300 € | I50: 141 Derb Arjane, Rahba Lakdima, Médina | J50: Médina | K50: 6-7 | L50: OUI | M50: 144 | N50: NA | O50: NA | P50: NA | Q50: NA | R50: NA | S50: NA | T50: +212 524 440 404 / +212 660 417 313 | U50: +212 660417313 (à confirmer) | V50: contact@riaddanka.com | W50: à compléter | X50: riaddanka.com | Y50: @riaddanka | Z50: NA | AA50: Importé de HEBERGEMENT. Quartier : Médina · Site : riaddanka.com | Coord. complétée(s) depuis annuaire : tél [Ancien statut: Importé] | AB50: ST-PRE · PREMIUM | AC50: AMB-ZEN · ZEN & BIEN-ÊTRE | AD50: KD-KFR · KIDS FRIENDLY | AE50: LVL-2 · 🔔🔔 DEUX CLOCHES | AF50: À qualifier (labels / distinctions) | AG50: OR-ROM · ROMANTIQUE | AH50: PUB-CPL · Couple | AI50: ACC-PUB · ACC-PRV | AJ50: Privatisation
A51: MARRAKECH | B51: HEBERGEMENT | C51: H118 | D51: INCONTOURNABLE | E51: {=IFERROR(INDEX(REF_CODES!$B$8:$B$13,MATCH($D51,REF_CODES!$C$8:$C$13,0)),"")} -> HB-INC | F51: IZZA Marrakech | G51: À confirmer (catégorie / classement) | H51: BG2 · 300 – 500 € | I51: 46, Driba Laarida, Sidi Ahmed Soussi, Médina | J51: Médina | K51: 14 | L51: OUI | M51: 350 | N51: 500 | O51: 700 | P51: NA | Q51: NA | R51: NA | S51: NA | T51: +212 6 61 95 62 46 | U51: +212 661956246 (à confirmer) | V51: reception@izza.com | W51: 7 riads interconnectés | X51: izza.com | Y51: à compléter | Z51: NA | AA51: Importé de HEBERGEMENT. Quartier : Médina · Site : izza.com | Coord. complétée(s) depuis annuaire : tél [Ancien statut: Importé] | AB51: ST-SIG · SIGNATURE | AC51: AMB-ROM · ROMANTIQUE | AD51: KD-KFR · KIDS FRIENDLY | AE51: LVL-2 · 🔔🔔 DEUX CLOCHES | AF51: À qualifier (labels / distinctions) | AG51: OR-ROM · ROMANTIQUE | AH51: PUB-CPL · Couple | AI51: ACC-PUB · ACC-PRV | AJ51: Mariage, séminaire, privatisation
A52: MARRAKECH | B52: HEBERGEMENT | C52: H111 | D52: RIAD & PATRIMOINE | E52: {=IFERROR(INDEX(REF_CODES!$B$8:$B$13,MATCH($D52,REF_CODES!$C$8:$C$13,0)),"")} -> HB-RIA | F52: Riad Les Yeux Bleus | G52: Maison d'hôtes · riad (cat. maison d'hôtes) | H52: BG1 · Moins de 300 € | I52: 7 Derb El Ferrane, Rue Fatima Zohra, Bab Doukkala | J52: Médina | K52: 11 | L52: OUI | M52: 160 | N52: 230 | O52: 300 | P52: NA | Q52: NA | R52: NA | S52: NA | T52: +212 524 378 161 | U52: À compléter | V52: non trouvé | W52: à compléter | X52: https://marrakech-boutique-riad.com | Y52: @riadlesyeuxbleus | Z52: NA | AA52: Importé de HEBERGEMENT. Quartier : Médina · Site : https://marrakech-boutique-riad.com | Coord. complétée(s) depuis annuaire : tél [Ancien statut: À compléter] | Fusion doublons : Riad Les Yeux Bleus (H111) | AB52: ST-PRE · PREMIUM | AC52: AMB-ZEN · ZEN & BIEN-ÊTRE | AD52: KD-KFR · KIDS FRIENDLY | AE52: LVL-2 · 🔔🔔 DEUX CLOCHES | AF52: À qualifier (labels / distinctions) | AG52: OR-ROM · ROMANTIQUE | AH52: PUB-CPL · Couple | AI52: ACC-PUB · ACC-PRV | AJ52: Anniversaire
A53: MARRAKECH | B53: HEBERGEMENT | C53: H120 | D53: INCONTOURNABLE | E53: {=IFERROR(INDEX(REF_CODES!$B$8:$B$13,MATCH($D53,REF_CODES!$C$8:$C$13,0)),"")} -> HB-INC | F53: Tigmiza Boutique Hotel & Spa | G53: 5 ETOILES | H53: BG2 · 300 – 500 € | I53: Douar Laghribate, Bab Atlas | J53: Palmeraie | K53: 27 | L53: OUI | M53: 320 | N53: 450 | O53: 600 | P53: NA | Q53: NA | R53: NA | S53: NA | T53: +212 524 393 700 | U53: À compléter | V53: non trouvé | W53: à compléter | X53: https://www.hotel-tigmiza-marrakech.com | Y53: à compléter | Z53: NA | AA53: Importé de HEBERGEMENT. Quartier : Palmeraie · Site : https://www.hotel-tigmiza-marrakech.com | Coord. complétée(s) depuis annuaire : tél [Ancien statut: À compléter] | AB53: ST-SIG · SIGNATURE | AC53: AMB-ROM · ROMANTIQUE | AD53: KD-CLB · KIDS CLUB | AE53: LVL-2 · 🔔🔔 DEUX CLOCHES | AF53: TemptingPlaces · Meilleur Hôtel Afrique | AG53: OR-ROM · ROMANTIQUE | AH53: PUB-CPL · Couple | AI53: ACC-PUB · ACC-PRV | AJ53: Mariage, séminaire, privatisation
A54: MARRAKECH | B54: HEBERGEMENT | C54: H112 | D54: RIAD & PATRIMOINE | E54: {=IFERROR(INDEX(REF_CODES!$B$8:$B$13,MATCH($D54,REF_CODES!$C$8:$C$13,0)),"")} -> HB-RIA | F54: Riad Adore | G54: Maison d'hôtes · riad (cat. maison d'hôtes) | H54: BG1 · Moins de 300 € | I54: 97 Derb Tizougarine, Dar El Bacha | J54: Médina | K54: 10 | L54: OUI | M54: 190 | N54: 270 | O54: 380 | P54: NA | Q54: NA | R54: NA | S54: NA | T54: +212 524 377737 | U54: À compléter | V54: contact@riadadore.com | W54: à compléter | X54: https://www.riadadore.com | Y54: @riadadore | Z54: NA | AA54: Importé de HEBERGEMENT. Quartier : Médina · Site : https://www.riadadore.com | Coord. complétée(s) depuis annuaire : tél [Ancien statut: Importé] | Fusion doublons : Riad Adore (H112) | AB54: ST-PRE · PREMIUM | AC54: AMB-ZEN · ZEN & BIEN-ÊTRE | AD54: KD-KFR · KIDS FRIENDLY | AE54: LVL-2 · 🔔🔔 DEUX CLOCHES | AF54: À qualifier (labels / distinctions) | AG54: OR-ROM · ROMANTIQUE | AH54: PUB-CPL · Couple | AI54: ACC-PUB · ACC-PRV | AJ54: Anniversaire
A55: MARRAKECH | B55: HEBERGEMENT | C55: H113 | D55: RIAD & PATRIMOINE | E55: {=IFERROR(INDEX(REF_CODES!$B$8:$B$13,MATCH($D55,REF_CODES!$C$8:$C$13,0)),"")} -> HB-RIA | F55: Riad Abracadabra | G55: Maison d'hôtes · riad (cat. maison d'hôtes) | H55: BG1 · Moins de 300 € | I55: 125 Derb Jamaa, Derb Dabachi, Médina | J55: Médina | K55: 8 | L55: OUI | M55: 110 | N55: NA | O55: NA | P55: NA | Q55: NA | R55: NA | S55: NA | T55: +212 611 324 269 / +212 524 38 40 39 | U55: +212 611324269 (à confirmer) | V55: info@riadabracadabra.com | W55: doublon Riad Abracadabra | X55: riadabracadabra.com | Y55: @riadabracadabra | Z55: NA | AA55: Importé de HEBERGEMENT. Quartier : Médina · Site : riadabracadabra.com | Coord. complétée(s) depuis annuaire : tél [Ancien statut: Importé] | Fusion doublons : Riad Abracadabra (H113) | AB55: ST-PRE · PREMIUM | AC55: AMB-ZEN · ZEN & BIEN-ÊTRE | AD55: KD-KFR · KIDS FRIENDLY | AE55: LVL-2 · 🔔🔔 DEUX CLOCHES | AF55: À qualifier (labels / distinctions) | AG55: OR-ROM · ROMANTIQUE | AH55: PUB-CPL · Couple | AI55: ACC-PUB · ACC-PRV | AJ55: Privatisation
A56: MARRAKECH | B56: HEBERGEMENT | C56: H114 | D56: RIAD & PATRIMOINE | E56: {=IFERROR(INDEX(REF_CODES!$B$8:$B$13,MATCH($D56,REF_CODES!$C$8:$C$13,0)),"")} -> HB-RIA | F56: Riad Botanica | G56: Maison d'hôtes · riad (cat. maison d'hôtes) | H56: BG1 · Moins de 300 € | I56: 78 Derb Sidi Lahcen Ou Ali, Bab Doukkala, Médina | J56: Médina | K56: 5-6 | L56: OUI | M56: 150 | N56: NA | O56: NA | P56: NA | Q56: NA | R56: NA | S56: NA | T56: +212 7 01 19 19 51 | U56: À compléter | V56: non trouvé | W56: tél/email non trouvés (formulaire) — privatisation complète possible | X56: riadbotanica.com | Y56: @riadbotanica | Z56: NA | AA56: Importé de HEBERGEMENT. Quartier : Médina · Site : riadbotanica.com [Ancien statut: À compléter] | Fusion doublons : Riad Botanica (H114) | AB56: ST-PRE · PREMIUM | AC56: AMB-ZEN · ZEN & BIEN-ÊTRE | AD56: KD-KFR · KIDS FRIENDLY | AE56: LVL-2 · 🔔🔔 DEUX CLOCHES | AF56: À qualifier (labels / distinctions) | AG56: OR-ROM · ROMANTIQUE | AH56: PUB-CPL · Couple | AI56: ACC-PUB · ACC-PRV | AJ56: Privatisation
A57: MARRAKECH | B57: HEBERGEMENT | C57: H115 | D57: RIAD & PATRIMOINE | E57: {=IFERROR(INDEX(REF_CODES!$B$8:$B$13,MATCH($D57,REF_CODES!$C$8:$C$13,0)),"")} -> HB-RIA | F57: Dar Kandi | G57: Maison d'hôtes · riad (cat. maison d'hôtes) | H57: BG1 · Moins de 300 € | I57: 215 Derb Arset Aouzal, Bab Doukkala, Médina | J57: Médina — Bab Doukkala | K57: 6 | L57: OUI | M57: 150 | N57: NA | O57: NA | P57: NA | Q57: NA | R57: NA | S57: NA | T57: +212 5 24 38 17 53 | U57: À compléter | V57: info@darkandi.com | W57: à compléter | X57: darkandi.com | Y57: à compléter | Z57: NA | AA57: Importé de HEBERGEMENT. Quartier : Médina — Bab Doukkala · Site : darkandi.com | Coord. complétée(s) depuis annuaire : email [Ancien statut: À compléter] | AB57: ST-PRE · PREMIUM | AC57: AMB-ZEN · ZEN & BIEN-ÊTRE | AD57: KD-KFR · KIDS FRIENDLY | AE57: LVL-2 · 🔔🔔 DEUX CLOCHES | AF57: À qualifier (labels / distinctions) | AG57: OR-ROM · ROMANTIQUE | AH57: PUB-CPL · Couple | AI57: ACC-PUB · ACC-PRV | AJ57: Privatisation, anniversaire
A58: MARRAKECH | B58: HEBERGEMENT | C58: H116 | D58: RIAD & PATRIMOINE | E58: {=IFERROR(INDEX(REF_CODES!$B$8:$B$13,MATCH($D58,REF_CODES!$C$8:$C$13,0)),"")} -> HB-RIA | F58: Riad Tzarra | G58: Maison d'hôtes · riad (cat. maison d'hôtes) | H58: BG1 · Moins de 300 € | I58: Quartier Kaat Benahid, Médina (près Medersa Ben Youssef) | J58: Médina | K58: 4 | L58: OUI | M58: 100 | N58: NA | O58: NA | P58: NA | Q58: NA | R58: NA | S58: NA | T58: +212 5 24 37 74 74 | U58: +212 663 839 292 | V58: contact@riadtzarra.com | W58: géré via agences (riads.fr) — souvent loué entier | X58: https://www.riadtzarra.com | Y58: NA | Z58: NA | AA58: Importé de HEBERGEMENT. Quartier : Médina [Ancien statut: À compléter] | AB58: ST-PRE · PREMIUM | AC58: AMB-ZEN · ZEN & BIEN-ÊTRE | AD58: KD-KFR · KIDS FRIENDLY | AE58: LVL-1 · 🔔 UNE CLOCHE | AF58: À qualifier (labels / distinctions) | AG58: OR-ROM · ROMANTIQUE | AH58: PUB-CPL · Couple | AI58: ACC-PUB · ACC-PRV | AJ58: Privatisation, anniversaire
A59: MARRAKECH | B59: HEBERGEMENT | C59: H126 | D59: HOTEL & RESORT | E59: {=IFERROR(INDEX(REF_CODES!$B$8:$B$13,MATCH($D59,REF_CODES!$C$8:$C$13,0)),"")} -> HB-HOT | F59: The Capaldi Hotel, Restaurant & Spa | G59: À confirmer (catégorie / classement) | H59: BG1 · Moins de 300 € | I59: Route d'Amizmiz Km 39, Lalla Takerkoust | J59: Lalla Takerkoust | K59: 23 | L59: OUI | M59: 280 | N59: 400 | O59: 550 | P59: NA | Q59: NA | R59: NA | S59: NA | T59: +212 600 069 900 | U59: +212 600069900 (à confirmer) | V59: info@thecapaldi.com | W59: à compléter | X59: https://www.thecapaldi.com | Y59: à compléter | Z59: NA | AA59: Importé de HEBERGEMENT. Quartier : Lalla Takerkoust · Site : https://www.thecapaldi.com | Coord. complétée(s) depuis annuaire : tél [Ancien statut: Importé] | Fusion doublons : The Capaldi Hotel (H126) | AB59: ST-SIG · SIGNATURE | AC59: AMB-ROM · ROMANTIQUE | AD59: KD-CLB · KIDS CLUB | AE59: LVL-3 · 🔔🔔🔔 TROIS CLOCHES | AF59: À qualifier (labels / distinctions) | AG59: OR-ROM · ROMANTIQUE | AH59: PUB-CPL · Couple | AI59: ACC-PUB · ACC-PRV | AJ59: Mariage, retraite
A60: MARRAKECH | B60: HEBERGEMENT | C60: H127 | D60: HOTEL & RESORT | E60: {=IFERROR(INDEX(REF_CODES!$B$8:$B$13,MATCH($D60,REF_CODES!$C$8:$C$13,0)),"")} -> HB-HOT | F60: Hotel Les Cinq Djellabas | G60: À confirmer (catégorie / classement) | H60: BG1 · Moins de 300 € | I60: Les Lodges de Jnanat, Douar Al Gribate | J60: Palmeraie | K60: 10 | L60: OUI | M60: 200 | N60: 300 | O60: 450 | P60: NA | Q60: NA | R60: NA | S60: NA | T60: +212 644 091 091 | U60: +212 644091091 (à confirmer) | V60: non trouvé | W60: à compléter | X60: https://www.hotel-les5djellabas.com | Y60: à compléter | Z60: NA | AA60: Importé de HEBERGEMENT. Quartier : Palmeraie · Site : https://www.hotel-les5djellabas.com | Coord. complétée(s) depuis annuaire : tél [Ancien statut: À compléter] | AB60: ST-SIG · SIGNATURE | AC60: AMB-ROM · ROMANTIQUE | AD60: KD-CLB · KIDS CLUB | AE60: LVL-3 · 🔔🔔🔔 TROIS CLOCHES | AF60: À qualifier (labels / distinctions) | AG60: OR-ROM · ROMANTIQUE | AH60: PUB-CPL · Couple | AI60: ACC-PUB · ACC-PRV | AJ60: Luxe, bien-être
A61: MARRAKECH | B61: HEBERGEMENT | C61: H117 | D61: RIAD & PATRIMOINE | E61: {=IFERROR(INDEX(REF_CODES!$B$8:$B$13,MATCH($D61,REF_CODES!$C$8:$C$13,0)),"")} -> HB-RIA | F61: Riad Ksar Fawz & Spa | G61: Maison d'hôtes · riad (cat. maison d'hôtes) | H61: BG1 · Moins de 300 € | I61: Derb Sbaia 2, Kasbah, Médina | J61: Médina | K61: 11 | L61: OUI | M61: 121 | N61: NA | O61: NA | P61: NA | Q61: NA | R61: NA | S61: NA | T61: +212 5 24 39 16 62 | U61: À compléter | V61: contact@ksarfawz-spa.com | W61: ≈ ex-Ksar Kasbah & Spa (même établissement, renommé) | X61: ksarfawz-spa.com | Y61: à compléter | Z61: NA | AA61: Importé de HEBERGEMENT. Quartier : Médina · Site : ksarfawz-spa.com | Coord. complétée(s) depuis annuaire : tél [Ancien statut: Importé] | Fusion doublons : Ksar Kasbah & Spa (H137) | AB61: ST-PRE · PREMIUM | AC61: AMB-ZEN · ZEN & BIEN-ÊTRE | AD61: KD-KFR · KIDS FRIENDLY | AE61: LVL-2 · 🔔🔔 DEUX CLOCHES | AF61: À qualifier (labels / distinctions) | AG61: OR-ROM · ROMANTIQUE | AH61: PUB-CPL · Couple | AI61: ACC-PUB · ACC-PRV | AJ61: Privatisation, anniversaire
A62: MARRAKECH | B62: HEBERGEMENT | C62: H119 | D62: RIAD & PATRIMOINE | E62: {=IFERROR(INDEX(REF_CODES!$B$8:$B$13,MATCH($D62,REF_CODES!$C$8:$C$13,0)),"")} -> HB-RIA | F62: La Brillante Marrakech | G62: À confirmer (catégorie / classement) | H62: BG1 · Moins de 300 € | I62: 6, rue Bahia, Riad Zitoune Jdid, Médina | J62: Médina | K62: 6 | L62: OUI | M62: 250 | N62: NA | O62: NA | P62: NA | Q62: NA | R62: NA | S62: NA | T62: +212 6 96 03 59 51 | U62: +212 696035951 (à confirmer) | V62: contact@h-labrillante.com | W62: à compléter | X62: h-labrillante.com | Y62: à compléter | Z62: NA | AA62: Importé de HEBERGEMENT. Quartier : Médina · Site : h-labrillante.com | Coord. complétée(s) depuis annuaire : tél [Ancien statut: Importé] | AB62: ST-PRE · PREMIUM | AC62: AMB-ZEN · ZEN & BIEN-ÊTRE | AD62: KD-KFR · KIDS FRIENDLY | AE62: LVL-2 · 🔔🔔 DEUX CLOCHES | AF62: À qualifier (labels / distinctions) | AG62: OR-ROM · ROMANTIQUE | AH62: PUB-CPL · Couple | AI62: ACC-PUB · ACC-PRV | AJ62: Privatisation, anniversaire
A63: MARRAKECH | B63: HEBERGEMENT | C63: H132 | D63: INCONTOURNABLE | E63: {=IFERROR(INDEX(REF_CODES!$B$8:$B$13,MATCH($D63,REF_CODES!$C$8:$C$13,0)),"")} -> HB-INC | F63: La Maison Arabe | G63: 5 ETOILES | H63: BG1 · Moins de 300 € | I63: 1 Derb Assehbé, Bab Doukkala | J63: Médina | K63: 26 | L63: OUI | M63: 196 | N63: 320 | O63: 480 | P63: NA | Q63: NA | R63: NA | S63: NA | T63: +212 524 387 010 | U63: À compléter | V63: non trouvé | W63: à compléter | X63: https://www.cenizaro.com/lamaisonarabe | Y63: à compléter | Z63: NA | AA63: Importé de HEBERGEMENT. Quartier : Médina · Site : https://www.cenizaro.com/lamaisonarabe | Coord. complétée(s) depuis annuaire : tél [Ancien statut: À compléter] | AB63: ST-PRE · PREMIUM | AC63: AMB-ROM · ROMANTIQUE | AD63: KD-KFR · KIDS FRIENDLY | AE63: LVL-3 · 🔔🔔🔔 TROIS CLOCHES | AF63: À qualifier (labels / distinctions) | AG63: OR-ROM · ROMANTIQUE | AH63: PUB-CPL · Couple | AI63: ACC-PUB · ACC-PRV | AJ63: Gastronomie, couple
A64: MARRAKECH | B64: HEBERGEMENT | C64: H134 | D64: NATURE & HORIZON | E64: {=IFERROR(INDEX(REF_CODES!$B$8:$B$13,MATCH($D64,REF_CODES!$C$8:$C$13,0)),"")} -> HB-NAT | F64: Lodge K Boutique Hotel Piscine & Spa Marrakech | G64: À confirmer (catégorie / classement) | H64: BG1 · Moins de 300 € | I64: Route de Fès Km 5, Dar Tounsi, Commune Ennakhil | J64: Route de Fès | K64: 5 | L64: OUI | M64: 235 | N64: NA | O64: NA | P64: NA | Q64: NA | R64: NA | S64: NA | T64: +212 6 60 15 39 24 | U64: À compléter | V64: non trouvé | W64: tél/email non trouvés (formulaire) | X64: lodgek.com | Y64: à compléter | Z64: NA | AA64: Importé de HEBERGEMENT. Quartier : Route de Fès · Site : lodgek.com [Ancien statut: À compléter] | AB64: ST-SIG · SIGNATURE | AC64: AMB-ZEN · ZEN & BIEN-ÊTRE | AD64: KD-KFR · KIDS FRIENDLY | AE64: LVL-2 · 🔔🔔 DEUX CLOCHES | AF64: À qualifier (labels / distinctions) | AG64: OR-ZEN · ZEN & BIEN-ÊTRE | AH64: PUB-CPL · Couple | AI64: ACC-PUB · ACC-PRV | AJ64: Nature, détente
A65: MARRAKECH | B65: HEBERGEMENT | C65: H121 | D65: RIAD & PATRIMOINE | E65: {=IFERROR(INDEX(REF_CODES!$B$8:$B$13,MATCH($D65,REF_CODES!$C$8:$C$13,0)),"")} -> HB-RIA | F65: Dar Sofil - Adults Only | G65: Maison d'hôtes · riad (cat. maison d'hôtes) | H65: BG1 · Moins de 300 € | I65: Km 10,5 Route de l'Ourika, Commune de Tassoultante | J65: Route de l'Ourika | K65: 7 | L65: OUI | M65: 200 | N65: NA | O65: NA | P65: NA | Q65: NA | R65: NA | S65: NA | T65: +212 6 64 69 86 01 | U65: À compléter | V65: non trouvé | W65: tél/email non trouvés (formulaire) — adults only, location villa entière possible | X65: darsofilmarrakech.com | Y65: à compléter | Z65: NA | AA65: Importé de HEBERGEMENT. Quartier : Route de l'Ourika · Site : darsofilmarrakech.com [Ancien statut: À compléter] | AB65: ST-PRE · PREMIUM | AC65: AMB-ZEN · ZEN & BIEN-ÊTRE | AD65: — Adults only (pas d'équipement enfants) | AE65: LVL-2 · 🔔🔔 DEUX CLOCHES | AF65: À qualifier (labels / distinctions) | AG65: OR-ROM · ROMANTIQUE | AH65: PUB-ADU · Adultes uniquement | AI65: ACC-PUB · ACC-PRV | AJ65: Privatisation, mariage
A66: MARRAKECH | B66: HEBERGEMENT | C66: H122 | D66: RIAD & PATRIMOINE | E66: {=IFERROR(INDEX(REF_CODES!$B$8:$B$13,MATCH($D66,REF_CODES!$C$8:$C$13,0)),"")} -> HB-RIA | F66: Riad & Spa Azzouz | G66: Maison d'hôtes · riad (cat. maison d'hôtes) | H66: BG1 · Moins de 300 € | I66: 4 derb Azzouz, Mouassine, Médina (accès Bab Laksour) | J66: Médina | K66: 6 | L66: OUI | M66: 115 | N66: NA | O66: NA | P66: NA | Q66: NA | R66: NA | S66: NA | T66: +212 5 24 38 90 40 | U66: À compléter | V66: non trouvé | W66: tél/email non trouvés (formulaire) — privatisation possible (16 pers.) ; ⚠️ homonyme Kasbah, à vérifier | X66: riadazzouz.com | Y66: à compléter | Z66: NA | AA66: Importé de HEBERGEMENT. Quartier : Médina · Site : riadazzouz.com [Ancien statut: À compléter] | AB66: ST-PRE · PREMIUM | AC66: AMB-ZEN · ZEN & BIEN-ÊTRE | AD66: KD-KFR · KIDS FRIENDLY | AE66: LVL-2 · 🔔🔔 DEUX CLOCHES | AF66: À qualifier (labels / distinctions) | AG66: OR-ROM · ROMANTIQUE | AH66: PUB-CPL · Couple | AI66: ACC-PUB · ACC-PRV | AJ66: Couple, anniversaire
A67: MARRAKECH | B67: HEBERGEMENT | C67: H123 | D67: RIAD & PATRIMOINE | E67: {=IFERROR(INDEX(REF_CODES!$B$8:$B$13,MATCH($D67,REF_CODES!$C$8:$C$13,0)),"")} -> HB-RIA | F67: Riad Palais Calipau | G67: Maison d'hôtes · riad (cat. maison d'hôtes) | H67: BG1 · Moins de 300 € | I67: 14 Derb Ben Zina, Kasbah, Médina | J67: Médina | K67: 12 | L67: OUI | M67: 233 | N67: NA | O67: NA | P67: NA | Q67: NA | R67: NA | S67: NA | T67: +212 524 375 583 | U67: À compléter | V67: non trouvé | W67: à compléter | X67: riadpalaiscalipau.com | Y67: à compléter | Z67: NA | AA67: Importé de HEBERGEMENT. Quartier : Médina · Site : riadpalaiscalipau.com | Coord. complétée(s) depuis annuaire : tél [Ancien statut: À compléter] | AB67: ST-PRE · PREMIUM | AC67: AMB-ZEN · ZEN & BIEN-ÊTRE | AD67: KD-KFR · KIDS FRIENDLY | AE67: LVL-2 · 🔔🔔 DEUX CLOCHES | AF67: À qualifier (labels / distinctions) | AG67: OR-ROM · ROMANTIQUE | AH67: PUB-CPL · Couple | AI67: ACC-PUB · ACC-PRV | AJ67: Mariage intimiste
A68: MARRAKECH | B68: HEBERGEMENT | C68: H124 | D68: RIAD & PATRIMOINE | E68: {=IFERROR(INDEX(REF_CODES!$B$8:$B$13,MATCH($D68,REF_CODES!$C$8:$C$13,0)),"")} -> HB-RIA | F68: Riad l'Oiseau du Paradis | G68: Maison d'hôtes · riad (cat. maison d'hôtes) | H68: BG1 · Moins de 300 € | I68: 27, derb Cherrata, Arset El Houta, Médina | J68: Médina | K68: 14 | L68: OUI | M68: 80 | N68: NA | O68: NA | P68: NA | Q68: NA | R68: NA | S68: NA | T68: +212 524 38 74 38 / +212 661 65 25 09 | U68: +212 661652509 (à confirmer) | V68: contactoiseauduparadis@gmail.com | W68: à compléter | X68: riadoiseauduparadis.com | Y68: à compléter | Z68: NA | AA68: Importé de HEBERGEMENT. Quartier : Médina · Site : riadoiseauduparadis.com | Coord. complétée(s) depuis annuaire : tél [Ancien statut: Importé] | AB68: ST-PRE · PREMIUM | AC68: AMB-ZEN · ZEN & BIEN-ÊTRE | AD68: KD-KFR · KIDS FRIENDLY | AE68: LVL-1 · 🔔 UNE CLOCHE | AF68: À qualifier (labels / distinctions) | AG68: OR-ROM · ROMANTIQUE | AH68: PUB-CPL · Couple | AI68: ACC-PUB · ACC-PRV | AJ68: Séjour loisirs
A69: MARRAKECH | B69: HEBERGEMENT | C69: H125 | D69: RIAD & PATRIMOINE | E69: {=IFERROR(INDEX(REF_CODES!$B$8:$B$13,MATCH($D69,REF_CODES!$C$8:$C$13,0)),"")} -> HB-RIA | F69: Riad Le Pèlerin | G69: Maison d'hôtes · riad (cat. maison d'hôtes) | H69: BG1 · Moins de 300 € | I69: 92 Derb Tizougarine, Dar El Bacha, Médina | J69: Médina | K69: 7 | L69: OUI | M69: 100 | N69: NA | O69: NA | P69: NA | Q69: NA | R69: NA | S69: NA | T69: +212 8 08 52 27 39 | U69: À compléter | V69: non trouvé | W69: tél/email non trouvés (formulaire) | X69: lepelerinmarrakech.com | Y69: à compléter | Z69: NA | AA69: Importé de HEBERGEMENT. Quartier : Médina · Site : lepelerinmarrakech.com [Ancien statut: À compléter] | AB69: ST-PRE · PREMIUM | AC69: AMB-ZEN · ZEN & BIEN-ÊTRE | AD69: KD-KFR · KIDS FRIENDLY | AE69: LVL-2 · 🔔🔔 DEUX CLOCHES | AF69: À qualifier (labels / distinctions) | AG69: OR-ROM · ROMANTIQUE | AH69: PUB-CPL · Couple | AI69: ACC-PUB · ACC-PRV | AJ69: Couple
A70: MARRAKECH | B70: HEBERGEMENT | C70: H128 | D70: RIAD & PATRIMOINE | E70: {=IFERROR(INDEX(REF_CODES!$B$8:$B$13,MATCH($D70,REF_CODES!$C$8:$C$13,0)),"")} -> HB-RIA | F70: Riad Dar Al Dall | G70: Maison d'hôtes · riad (cat. maison d'hôtes) | H70: BG1 · Moins de 300 € | I70: Kaat Benahid, Médina | J70: Médina | K70: 5 | L70: OUI | M70: 250 | N70: NA | O70: NA | P70: NA | Q70: NA | R70: NA | S70: NA | T70: +212 8 09 89 01 73 | U70: À compléter | V70: marrakech@thistimetomorrow.io | W70: ≈ This Time Tomorrow (5 résidences) | X70: non trouvé | Y70: à compléter | Z70: NA | AA70: Importé de HEBERGEMENT. Quartier : Médina | Coord. complétée(s) depuis annuaire : email [Ancien statut: À compléter] | AB70: ST-PRE · PREMIUM | AC70: AMB-ZEN · ZEN & BIEN-ÊTRE | AD70: KD-KFR · KIDS FRIENDLY | AE70: LVL-2 · 🔔🔔 DEUX CLOCHES | AF70: À qualifier (labels / distinctions) | AG70: OR-ROM · ROMANTIQUE | AH70: PUB-CPL · Couple | AI70: ACC-PUB · ACC-PRV | AJ70: Privatisation
A71: MARRAKECH | B71: HEBERGEMENT | C71: H131 | D71: RIAD & PATRIMOINE | E71: {=IFERROR(INDEX(REF_CODES!$B$8:$B$13,MATCH($D71,REF_CODES!$C$8:$C$13,0)),"")} -> HB-RIA | F71: Dar Kemgia | G71: Maison d'hôtes · riad (cat. maison d'hôtes) | H71: BG1 · Moins de 300 € | I71: Palmeraie | J71: Palmeraie | K71: 9 | L71: OUI | M71: 102 | N71: NA | O71: NA | P71: NA | Q71: NA | R71: NA | S71: NA | T71: À sourcer (contact direct) | U71: NA | V71: via Le Collectionist | W71: Location privée (20 pers.) via Le Collectionist / Villanovo — staff complet | X71: https://www.lecollectionist.com/en/luxury-rental/dar-kemgia-marrakech-and-surroundings | Y71: NA | Z71: NA | AA71: Importé de HEBERGEMENT. Quartier : Palmeraie [Ancien statut: À compléter] | AB71: ST-PRE · PREMIUM | AC71: AMB-ZEN · ZEN & BIEN-ÊTRE | AD71: KD-CLB · KIDS CLUB | AE71: LVL-2 · 🔔🔔 DEUX CLOCHES | AF71: À qualifier (labels / distinctions) | AG71: OR-ROM · ROMANTIQUE | AH71: PUB-CPL · Couple | AI71: ACC-PUB · ACC-PRV | AJ71: Villa privée
A72: MARRAKECH | B72: HEBERGEMENT | C72: H147 | D72: HOTEL & RESORT | E72: {=IFERROR(INDEX(REF_CODES!$B$8:$B$13,MATCH($D72,REF_CODES!$C$8:$C$13,0)),"")} -> HB-HOT | F72: Radisson Blu Hotel, Marrakech Carre Eden | G72: 5 ETOILES | H72: BG1 · Moins de 300 € | I72: 166-176 Avenue Mohamed V | J72: Guéliz | K72: 193 | L72: OUI | M72: 150 | N72: 220 | O72: 350 | P72: NA | Q72: NA | R72: NA | S72: NA | T72: +212 525 077 000 | U72: À compléter | V72: non trouvé | W72: à compléter | X72: https://www.radissonhotels.com/fr-fr/hotels/radisson-blu-marrakech-carre-eden | Y72: à compléter | Z72: NA | AA72: Importé de HEBERGEMENT. Quartier : Guéliz · Site : https://www.radissonhotels.com/fr-fr/hotels/radisson-blu-marrakech-carre-eden | Coord. complétée(s) depuis annuaire : tél [Ancien statut: À compléter] | Fusion doublons : Radisson Blu Carré Eden (H147) | AB72: ST-ULT · ULTRA EXCLUSIF | AC72: AMB-ROM · ROMANTIQUE | AD72: KD-CLB · KIDS CLUB | AE72: LVL-3 · 🔔🔔🔔 TROIS CLOCHES | AF72: À qualifier (labels / distinctions) | AG72: OR-PRO · PROFESSIONNEL | AH72: PUB-GRP · Groupe | AI72: ACC-PUB · ACC-PRV | AJ72: Corporate
A73: MARRAKECH | B73: HEBERGEMENT | C73: H148 | D73: INCONTOURNABLE | E73: {=IFERROR(INDEX(REF_CODES!$B$8:$B$13,MATCH($D73,REF_CODES!$C$8:$C$13,0)),"")} -> HB-INC | F73: Le Bab Hôtel | G73: À confirmer (catégorie / classement) | H73: BG1 · Moins de 300 € | I73: Angle Bd Mansour Eddahbi / Rue Mohamed El Beqqal, Guéliz | J73: Guéliz | K73: 43-45 | L73: OUI | M73: 84 | N73: NA | O73: NA | P73: NA | Q73: NA | R73: NA | S73: NA | T73: +212 524 435 250 | U73: À compléter | V73: non trouvé | W73: doublon Le Bab Hôtel | X73: babhotelmarrakech.ma | Y73: à compléter | Z73: NA | AA73: Importé de HEBERGEMENT. Quartier : Guéliz · Site : babhotelmarrakech.ma | Coord. complétée(s) depuis annuaire : tél [Ancien statut: À compléter] | Fusion doublons : Bab Hotel Marrakech (H148) | AB73: ST-ULT · ULTRA EXCLUSIF | AC73: AMB-ROM · ROMANTIQUE | AD73: KD-KFR · KIDS FRIENDLY | AE73: LVL-3 · 🔔🔔🔔 TROIS CLOCHES | AF73: À qualifier (labels / distinctions) | AG73: OR-ROM · ROMANTIQUE | AH73: PUB-CPL · Couple | AI73: ACC-PUB · ACC-PRV | AJ73: Lifestyle
A74: MARRAKECH | B74: HEBERGEMENT | C74: H150 | D74: HOTEL & RESORT | E74: {=IFERROR(INDEX(REF_CODES!$B$8:$B$13,MATCH($D74,REF_CODES!$C$8:$C$13,0)),"")} -> HB-HOT | F74: Palais Leonia | G74: À confirmer (catégorie / classement) | H74: BG2 · 300 – 500 € | I74: Oulad Hassoun, ~30 min de l'aéroport | J74: Oulad Hassoune | K74: 10 | L74: OUI | M74: 400 | N74: 550 | O74: 750 | P74: NA | Q74: 10 | R74: 300 | S74: NA | T74: À sourcer (contact direct) | U74: NA | V74: via agence | W74: 20 couchages, 1 280 m², piscine 36×22 m chauffée, héliport — location événementielle via Vrbo / villas-riads-marrakech.com | X74: https://villas-riads-marrakech.com/evenements/lieux-de-reception/palais-leonia/ | Y74: NA | Z74: NA | AA74: Importé de HEBERGEMENT. Quartier : Oulad Hassoune [Ancien statut: À compléter] | Villa(s) privatisable(s) déplacée(s) → HB-COL | AB74: ST-SIG · SIGNATURE | AC74: AMB-ROM · ROMANTIQUE | AD74: KD-CLB · KIDS CLUB | AE74: LVL-2 · 🔔🔔 DEUX CLOCHES | AF74: À qualifier (labels / distinctions) | AG74: OR-ROM · ROMANTIQUE | AH74: PUB-CPL · Couple | AI74: ACC-PUB · ACC-PRV | AJ74: Mariage, privatisation
A75: MARRAKECH | B75: HEBERGEMENT | C75: H135 | D75: RIAD & PATRIMOINE | E75: {=IFERROR(INDEX(REF_CODES!$B$8:$B$13,MATCH($D75,REF_CODES!$C$8:$C$13,0)),"")} -> HB-RIA | F75: Riad Ana Yela | G75: Maison d'hôtes · riad (cat. maison d'hôtes) | H75: BG1 · Moins de 300 € | I75: 28 Derb Zarwal, Route Kaa el Machraa, Bab Khemis, Médina | J75: Médina | K75: 5 | L75: OUI | M75: 250 | N75: NA | O75: NA | P75: NA | Q75: NA | R75: NA | S75: NA | T75: +212 524 386 969 ; booking +49 174 9208641 | U75: À compléter | V75: non trouvé | W75: email protégé sur le site (formulaire) | X75: anayela.com | Y75: à compléter | Z75: NA | AA75: Importé de HEBERGEMENT. Quartier : Médina · Site : anayela.com | Coord. complétée(s) depuis annuaire : tél [Ancien statut: À compléter] | Fusion doublons : Le Riad AnaYela (H152) + AnaYela (H152) | AB75: ST-PRE · PREMIUM | AC75: AMB-ZEN · ZEN & BIEN-ÊTRE | AD75: KD-KFR · KIDS FRIENDLY | AE75: LVL-3 · 🔔🔔🔔 TROIS CLOCHES | AF75: À qualifier (labels / distinctions) | AG75: OR-ROM · ROMANTIQUE | AH75: PUB-CPL · Couple | AI75: ACC-PUB · ACC-PRV | AJ75: Luxe expérientiel
A76: MARRAKECH | B76: HEBERGEMENT | C76: H153 | D76: INCONTOURNABLE | E76: {=IFERROR(INDEX(REF_CODES!$B$8:$B$13,MATCH($D76,REF_CODES!$C$8:$C$13,0)),"")} -> HB-INC | F76: L'Hôtel Marrakech | G76: À confirmer (catégorie / classement) | H76: BG2 · 300 – 500 € | I76: 41 Derb Sidi Lahcen ou Ali, Bab Doukkala, Médina | J76: Médina — Bab Doukkala | K76: 6 | L76: OUI | M76: 395 | N76: NA | O76: 544 | P76: NA | Q76: NA | R76: NA | S76: NA | T76: +212 524 38 78 80 | U76: À compléter | V76: non trouvé | W76: ≈ L'Hôtel Marrakech by Jasper Conran (doublon) | X76: l-hotelmarrakech.com | Y76: facebook.com/lhotelmarrakech | Z76: NA | AA76: Importé de HEBERGEMENT. Quartier : Médina — Bab Doukkala · Site : l-hotelmarrakech.com | Coord. complétée(s) depuis annuaire : tél [Ancien statut: À compléter] | Fusion doublons : Riad L'Hôtel Marrakech (H129) | AB76: ST-SIG · SIGNATURE | AC76: AMB-ROM · ROMANTIQUE | AD76: KD-KFR · KIDS FRIENDLY | AE76: LVL-3 · 🔔🔔🔔 TROIS CLOCHES | AF76: À qualifier (labels / distinctions) | AG76: OR-ROM · ROMANTIQUE | AH76: PUB-CPL · Couple | AI76: ACC-PUB · ACC-PRV | AJ76: Luxe
A77: MARRAKECH | B77: HEBERGEMENT | C77: H136 | D77: RIAD & PATRIMOINE | E77: {=IFERROR(INDEX(REF_CODES!$B$8:$B$13,MATCH($D77,REF_CODES!$C$8:$C$13,0)),"")} -> HB-RIA | F77: Riad La Maison Marrakech | G77: Maison d'hôtes · riad (cat. maison d'hôtes) | H77: BG1 · Moins de 300 € | I77: Bab Aylan, Médina | J77: Médina | K77: 3 | L77: OUI | M77: 250 | N77: NA | O77: NA | P77: NA | Q77: NA | R77: NA | S77: NA | T77: À sourcer (contact direct) | U77: NA | V77: via Airbnb | W77: 1 ch + 2 suites — location privée (designer Nicole Manfron) via staysomedays.com | X77: https://www.airbnb.com/rooms/411375 | Y77: @la.maison.marrakech | Z77: NA | AA77: Importé de HEBERGEMENT. Quartier : Médina [Ancien statut: À compléter] | AB77: ST-PRE · PREMIUM | AC77: AMB-ZEN · ZEN & BIEN-ÊTRE | AD77: KD-KFR · KIDS FRIENDLY | AE77: LVL-2 · 🔔🔔 DEUX CLOCHES | AF77: À qualifier (labels / distinctions) | AG77: OR-ROM · ROMANTIQUE | AH77: PUB-CPL · Couple | AI77: ACC-PUB · ACC-PRV | AJ77: Privatisation
A78: MARRAKECH | B78: HEBERGEMENT | C78: H155 | D78: INCONTOURNABLE | E78: {=IFERROR(INDEX(REF_CODES!$B$8:$B$13,MATCH($D78,REF_CODES!$C$8:$C$13,0)),"")} -> HB-INC | F78: Olinto, sur les contreforts de l'Atlas | G78: À confirmer (catégorie / classement) | H78: BG2 · 300 – 500 € | I78: Ouirgane (vallée de l'Atlas, ~60 km de Marrakech) | J78: Ouirgane (Atlas) | K78: non trouvé | L78: OUI | M78: 350 | N78: NA | O78: NA | P78: NA | Q78: NA | R78: NA | S78: NA | T78: +212 6 61 82 70 93 | U78: À compléter | V78: non trouvé | W78: tél/email non trouvés (formulaire) — boutique retreat, suites avec piscines privées | X78: olinto.com | Y78: à compléter | Z78: NA | AA78: Importé de HEBERGEMENT. Quartier : Ouirgane (Atlas) · Site : olinto.com [Ancien statut: À compléter] | AB78: ST-ULT · ULTRA EXCLUSIF | AC78: AMB-ROM · ROMANTIQUE | AD78: KD-KFR · KIDS FRIENDLY | AE78: LVL-3 · 🔔🔔🔔 TROIS CLOCHES | AF78: À qualifier (labels / distinctions) | AG78: OR-ROM · ROMANTIQUE | AH78: PUB-CPL · Couple | AI78: ACC-PUB · ACC-PRV | AJ78: Luxe expérientiel
A79: MARRAKECH | B79: HEBERGEMENT | C79: H156 | D79: HOTEL & RESORT | E79: {=IFERROR(INDEX(REF_CODES!$B$8:$B$13,MATCH($D79,REF_CODES!$C$8:$C$13,0)),"")} -> HB-HOT | F79: Sofitel Marrakech Palais Impérial & Spa | G79: 5 ETOILES | H79: BG1 · Moins de 300 € | I79: Rue Harroun Errachid | J79: Hivernage | K79: 330 | L79: OUI | M79: 280 | N79: 450 | O79: 650 | P79: NA | Q79: NA | R79: NA | S79: NA | T79: +212 5 24 42 56 00 | U79: À compléter | V79: non trouvé | W79: à compléter | X79: https://sofitel.accor.com/fr/hotels/3569.html | Y79: à compléter | Z79: NA | AA79: Importé de HEBERGEMENT. Quartier : Hivernage · Site : https://sofitel.accor.com/fr/hotels/3569.html [Ancien statut: À compléter] | Fusion doublons : Sofitel Marrakech Palais Impérial (H156) | AB79: ST-ULT · ULTRA EXCLUSIF | AC79: AMB-ROM · ROMANTIQUE | AD79: KD-CLB · KIDS CLUB | AE79: LVL-3 · 🔔🔔🔔 TROIS CLOCHES | AF79: À qualifier (labels / distinctions) | AG79: OR-PRO · PROFESSIONNEL | AH79: PUB-GRP · Groupe | AI79: ACC-PUB · ACC-PRV | AJ79: MICE, groupes
A80: MARRAKECH | B80: HEBERGEMENT | C80: À attribuer | D80: NATURE & HORIZON | E80: {=IFERROR(INDEX(REF_CODES!$B$8:$B$13,MATCH($D80,REF_CODES!$C$8:$C$13,0)),"")} -> HB-NAT | F80: Inara Camp | G80: À confirmer (catégorie / classement) | H80: BG2 · 300 – 500 € | I80: Désert d'Agafay (bureaux : Bloc 8 n°317 Sidi Ghanem) | J80: Agafay | K80: 19 | L80: OUI | M80: 350 | N80: 500 | O80: 800 | P80: NA | Q80: NA | R80: NA | S80: NA | T80: +212 524 205 070 | U80: À compléter | V80: contact@inaracamp.com | W80: À renseigner (prospection) | X80: https://inaracamp.com | Y80: facebook.com/inaracamp | Z80: NA | AA80: — | AB80: ST-PRE · PREMIUM | AC80: AMB-ZEN · ZEN & BIEN-ÊTRE | AD80: KD-KFR · KIDS FRIENDLY | AE80: LVL-2 · 🔔🔔 DEUX CLOCHES | AF80: À qualifier (labels / distinctions) | AG80: OR-ZEN · ZEN & BIEN-ÊTRE | AH80: PUB-CPL · Couple | AI80: ACC-PUB · ACC-PRV | AJ80: Mariage, séminaire, privatisation
A81: MARRAKECH | B81: HEBERGEMENT | C81: H027 | D81: HOTEL & RESORT | E81: {=IFERROR(INDEX(REF_CODES!$B$8:$B$13,MATCH($D81,REF_CODES!$C$8:$C$13,0)),"")} -> HB-HOT | F81: Hotel Nobu Marrakech | G81: 5 ETOILES | H81: BG2 · 300 – 500 € | I81: Av. Echouhada et Rue du Temple | J81: Hivernage | K81: 71 | L81: OUI | M81: 450 | N81: 650 | O81: 900 | P81: NA | Q81: NA | R81: NA | S81: NA | T81: +212 524 42 42 00 / +212 524 424 242 | U81: À compléter | V81: inquiries-marrakech@nobuhotels.com | W81: Mme Wissam / Mr Abdallaoui | X81: https://www.nobuhotels.com/marrakech | Y81: @nobumarrakech | Z81: NA | AA81: Coord. complétée(s) depuis annuaire : tél | Fusion doublons : Nobu Hotel Marrakech (H027) | AB81: ST-SIG · SIGNATURE | AC81: AMB-ROM · ROMANTIQUE | AD81: KD-CLB · KIDS CLUB | AE81: LVL-3 · 🔔🔔🔔 TROIS CLOCHES | AF81: À qualifier (labels / distinctions) | AG81: OR-ROM · ROMANTIQUE | AH81: PUB-CPL · Couple | AI81: ACC-PUB · ACC-PRV | AJ81: Luxe lifestyle
A82: MARRAKECH | B82: HEBERGEMENT | C82: H138 | D82: RIAD & PATRIMOINE | E82: {=IFERROR(INDEX(REF_CODES!$B$8:$B$13,MATCH($D82,REF_CODES!$C$8:$C$13,0)),"")} -> HB-RIA | F82: Riad 42 | G82: Maison d'hôtes · riad (cat. maison d'hôtes) | H82: BG1 · Moins de 300 € | I82: Kaat Benahid, Médina | J82: Médina | K82: 5 | L82: OUI | M82: 101 | N82: NA | O82: NA | P82: NA | Q82: NA | R82: NA | S82: NA | T82: +212 6 53 05 38 57 | U82: À compléter | V82: theriad42@gmail.com | W82: Réservation uniquement par email — riad entier dès ~630 $/nuit | X82: non trouvé | Y82: à compléter | Z82: NA | AA82: Importé de HEBERGEMENT. Quartier : Médina | Coord. complétée(s) depuis annuaire : email [Ancien statut: À compléter] | AB82: ST-PRE · PREMIUM | AC82: AMB-ZEN · ZEN & BIEN-ÊTRE | AD82: KD-KFR · KIDS FRIENDLY | AE82: LVL-1 · 🔔 UNE CLOCHE | AF82: À qualifier (labels / distinctions) | AG82: OR-ROM · ROMANTIQUE | AH82: PUB-CPL · Couple | AI82: ACC-PUB · ACC-PRV | AJ82: Privatisation
A83: MARRAKECH | B83: HEBERGEMENT | C83: H139 | D83: RIAD & PATRIMOINE | E83: {=IFERROR(INDEX(REF_CODES!$B$8:$B$13,MATCH($D83,REF_CODES!$C$8:$C$13,0)),"")} -> HB-RIA | F83: RIAD SAFIR | G83: Maison d'hôtes · riad (cat. maison d'hôtes) | H83: BG1 · Moins de 300 € | I83: 141 Derb Aghrab, Bab Aylan, Médina | J83: Médina | K83: 7 | L83: OUI | M83: 63 | N83: NA | O83: NA | P83: NA | Q83: NA | R83: NA | S83: NA | T83: +212 6 71 77 13 00 | U83: À compléter | V83: non trouvé | W83: tél/email non trouvés (formulaire) | X83: riadsafir.com | Y83: à compléter | Z83: NA | AA83: Importé de HEBERGEMENT. Quartier : Médina · Site : riadsafir.com [Ancien statut: À compléter] | AB83: ST-PRE · PREMIUM | AC83: AMB-ZEN · ZEN & BIEN-ÊTRE | AD83: KD-KFR · KIDS FRIENDLY | AE83: LVL-1 · 🔔 UNE CLOCHE | AF83: À qualifier (labels / distinctions) | AG83: OR-ROM · ROMANTIQUE | AH83: PUB-CPL · Couple | AI83: ACC-PUB · ACC-PRV | AJ83: Couple
A84: MARRAKECH | B84: HEBERGEMENT | C84: H143 | D84: RIAD & PATRIMOINE | E84: {=IFERROR(INDEX(REF_CODES!$B$8:$B$13,MATCH($D84,REF_CODES!$C$8:$C$13,0)),"")} -> HB-RIA | F84: Dar Moucha | G84: Maison d'hôtes · riad (cat. maison d'hôtes) | H84: BG1 · Moins de 300 € | I84: Douar Caïd Layadi, Bab Atlas, Palmeraie | J84: Palmeraie | K84: 6 | L84: OUI | M84: 120 | N84: 180 | O84: 250 | P84: NA | Q84: 6 | R84: 250 | S84: NA | T84: +212 6 73 72 87 00 | U84: À compléter | V84: non trouvé | W84: Instagram @dar.moucha — piscine chauffée en option (100 €/j + 300 €) | X84: marrakech-resort.com | Y84: à compléter | Z84: NA | AA84: Importé de HEBERGEMENT. Quartier : Palmeraie · Site : marrakech-resort.com [Ancien statut: À compléter] | Villa(s) privatisable(s) déplacée(s) → HB-COL | AB84: ST-PRE · PREMIUM | AC84: AMB-ZEN · ZEN & BIEN-ÊTRE | AD84: KD-CLB · KIDS CLUB | AE84: LVL-2 · 🔔🔔 DEUX CLOCHES | AF84: À qualifier (labels / distinctions) | AG84: OR-ROM · ROMANTIQUE | AH84: PUB-CPL · Couple | AI84: ACC-PUB · ACC-PRV | AJ84: Villa évènementielle
A85: MARRAKECH | B85: HEBERGEMENT | C85: H151 | D85: RIAD & PATRIMOINE | E85: {=IFERROR(INDEX(REF_CODES!$B$8:$B$13,MATCH($D85,REF_CODES!$C$8:$C$13,0)),"")} -> HB-RIA | F85: Maison Stella Cadente | G85: À confirmer (catégorie / classement) | H85: BG1 · Moins de 300 € | I85: non trouvée | J85: Médina | K85: 7 | L85: OUI | M85: 120 | N85: NA | O85: NA | P85: NA | Q85: NA | R85: NA | S85: NA | T85: +212 6 18 93 78 87 | U85: À compléter | V85: hello@marrakech.maison-stella-cadente.com | W85: à compléter | X85: marrakech.maison-stella-cadente.com | Y85: à compléter | Z85: NA | AA85: Importé de HEBERGEMENT. Site : marrakech.maison-stella-cadente.com | Coord. complétée(s) depuis annuaire : email [Ancien statut: À compléter] | AB85: ST-PRE · PREMIUM | AC85: AMB-ZEN · ZEN & BIEN-ÊTRE | AD85: KD-KFR · KIDS FRIENDLY | AE85: LVL-2 · 🔔🔔 DEUX CLOCHES | AF85: À qualifier (labels / distinctions) | AG85: OR-ROM · ROMANTIQUE | AH85: PUB-CPL · Couple | AI85: ACC-PUB · ACC-PRV | AJ85: Couple
A86: MARRAKECH | B86: HEBERGEMENT | C86: H154 | D86: RIAD & PATRIMOINE | E86: {=IFERROR(INDEX(REF_CODES!$B$8:$B$13,MATCH($D86,REF_CODES!$C$8:$C$13,0)),"")} -> HB-RIA | F86: Ryad Dyor, boutique-hôtel à Marrakech | G86: Maison d'hôtes · riad (cat. maison d'hôtes) | H86: BG1 · Moins de 300 € | I86: 1, Driba Jdida, Sidi Ben Slimane, Médina | J86: Médina | K86: 7 | L86: OUI | M86: 180 | N86: NA | O86: NA | P86: NA | Q86: NA | R86: NA | S86: NA | T86: +212 524 375 980 / +212 661 223 134 | U86: +212 661223134 (à confirmer) | V86: info@ryaddyor.com | W86: à compléter | X86: ryaddyor.com | Y86: à compléter | Z86: NA | AA86: Importé de HEBERGEMENT. Quartier : Médina · Site : ryaddyor.com | Coord. complétée(s) depuis annuaire : tél [Ancien statut: Importé] | AB86: ST-PRE · PREMIUM | AC86: AMB-ZEN · ZEN & BIEN-ÊTRE | AD86: KD-KFR · KIDS FRIENDLY | AE86: LVL-2 · 🔔🔔 DEUX CLOCHES | AF86: À qualifier (labels / distinctions) | AG86: OR-ROM · ROMANTIQUE | AH86: PUB-CPL · Couple | AI86: ACC-PUB · ACC-PRV | AJ86: Couple premium
A87: MARRAKECH | B87: HEBERGEMENT | C87: H157 | D87: RIAD & PATRIMOINE | E87: {=IFERROR(INDEX(REF_CODES!$B$8:$B$13,MATCH($D87,REF_CODES!$C$8:$C$13,0)),"")} -> HB-RIA | F87: Riad Samsara | G87: Maison d'hôtes · riad (cat. maison d'hôtes) | H87: BG1 · Moins de 300 € | I87: N°6, Derb El Aarsa, Tarzout, Médina (près Bab El Khemis) | J87: Médina | K87: 3 | L87: OUI | M87: 80 | N87: NA | O87: NA | P87: NA | Q87: NA | R87: NA | S87: NA | T87: +212 6 36 04 85 59 | U87: À compléter | V87: non trouvé | W87: tél/email non trouvés (formulaire) — même propriétaire que Douar Samra (Imlil) | X87: fr.riad-samsara.net | Y87: à compléter | Z87: NA | AA87: Importé de HEBERGEMENT. Quartier : Médina · Site : fr.riad-samsara.net [Ancien statut: À compléter] | AB87: ST-PRE · PREMIUM | AC87: AMB-ZEN · ZEN & BIEN-ÊTRE | AD87: KD-KFR · KIDS FRIENDLY | AE87: LVL-1 · 🔔 UNE CLOCHE | AF87: À qualifier (labels / distinctions) | AG87: OR-ROM · ROMANTIQUE | AH87: PUB-CPL · Couple | AI87: ACC-PUB · ACC-PRV | AJ87: Couple
A88: MARRAKECH | B88: HEBERGEMENT | C88: H028 | D88: HOTEL & RESORT | E88: {=IFERROR(INDEX(REF_CODES!$B$8:$B$13,MATCH($D88,REF_CODES!$C$8:$C$13,0)),"")} -> HB-HOT | F88: Palais Namaskar | G88: 5 ETOILES | H88: BG3 · 500 – 800 € | I88: Route de Bab Atlas 88/69, Province Syba | J88: Palmeraie | K88: 41 | L88: OUI | M88: 600 | N88: 900 | O88: 1400 | P88: NA | Q88: NA | R88: NA | S88: NA | T88: +212 524 29 98 00 | U88: À compléter | V88: non trouvé | W88: Mme Oumaima Cherkaoui | X88: https://www.palaisnamaskar.com | Y88: @palaisnamaskar | Z88: https://facebook.com/PalaisNamaskar | AA88: Coord. complétée(s) depuis annuaire : tél | AB88: ST-ULT · ULTRA EXCLUSIF | AC88: AMB-ROM · ROMANTIQUE | AD88: KD-CLB · KIDS CLUB | AE88: LVL-3 · 🔔🔔🔔 TROIS CLOCHES | AF88: À qualifier (labels / distinctions) | AG88: OR-ROM · ROMANTIQUE | AH88: PUB-CPL · Couple | AI88: ACC-PUB · ACC-PRV | AJ88: Mariage, séminaire, privatisation
A89: MARRAKECH | B89: HEBERGEMENT | C89: H054 | D89: HOTEL & RESORT | E89: {=IFERROR(INDEX(REF_CODES!$B$8:$B$13,MATCH($D89,REF_CODES!$C$8:$C$13,0)),"")} -> HB-HOT | F89: Kenzi Menara Palace | G89: 5 ETOILES | H89: BG1 · Moins de 300 € | I89: Zone de l'Agdal, Avenue Mohamed VI | J89: Agdal | K89: 236 | L89: OUI | M89: 180 | N89: 280 | O89: 400 | P89: NA | Q89: NA | R89: NA | S89: NA | T89: +212 524 459 900 / +212 524 459 999 | U89: À compléter | V89: menarapalace@kenzi-hotels.com | W89: Mme Touria | X89: https://www.kenzi-hotels.com | Y89: @kenzihotels | Z89: NA | AA89: Coord. complétée(s) depuis annuaire : tél | AB89: ST-ULT · ULTRA EXCLUSIF | AC89: AMB-ROM · ROMANTIQUE | AD89: KD-CLB · KIDS CLUB | AE89: LVL-3 · 🔔🔔🔔 TROIS CLOCHES | AF89: À qualifier (labels / distinctions) | AG89: OR-PRO · PROFESSIONNEL | AH89: PUB-GRP · Groupe | AI89: ACC-PUB · ACC-PRV | AJ89: Mariage, séminaire, privatisation
A90: MARRAKECH | B90: HEBERGEMENT | C90: H163 | D90: HOTEL & RESORT | E90: {=IFERROR(INDEX(REF_CODES!$B$8:$B$13,MATCH($D90,REF_CODES!$C$8:$C$13,0)),"")} -> HB-HOT | F90: Savoy Le Grand Hotel | G90: 5 ETOILES | H90: BG1 · Moins de 300 € | I90: Avenue Prince My Rachid | J90: Hivernage | K90: 444 | L90: OUI | M90: 200 | N90: 320 | O90: 450 | P90: NA | Q90: NA | R90: NA | S90: NA | T90: +212 524 351 000 | U90: À compléter | V90: contact@savoylegrandhotelmarrakech.com | W90: à compléter | X90: https://www.savoylegrandhotelmarrakech.com | Y90: à compléter | Z90: NA | AA90: Importé de HEBERGEMENT. Quartier : Hivernage · Site : https://www.savoylegrandhotelmarrakech.com | Coord. complétée(s) depuis annuaire : tél [Ancien statut: Importé] | AB90: ST-ULT · ULTRA EXCLUSIF | AC90: AMB-ROM · ROMANTIQUE | AD90: KD-CLB · KIDS CLUB | AE90: LVL-3 · 🔔🔔🔔 TROIS CLOCHES | AF90: À qualifier (labels / distinctions) | AG90: OR-PRO · PROFESSIONNEL | AH90: PUB-GRP · Groupe | AI90: ACC-PUB · ACC-PRV | AJ90: Mariage, séminaire, privatisation
A91: MARRAKECH | B91: HEBERGEMENT | C91: H042 | D91: INCONTOURNABLE | E91: {=IFERROR(INDEX(REF_CODES!$B$8:$B$13,MATCH($D91,REF_CODES!$C$8:$C$13,0)),"")} -> HB-INC | F91: Mövenpick Mansour Eddahbi | G91: 5 ETOILES | H91: BG1 · Moins de 300 € | I91: Bd Mohamed VI | J91: Hivernage | K91: non trouvé | L91: OUI | M91: 160 | N91: 250 | O91: 380 | P91: NA | Q91: NA | R91: NA | S91: NA | T91: +212 524 33 91 00 | U91: À compléter | V91: hotel.marrakech.reservations@movenpick.com | W91: Mme Oumaima | X91: https://movenpick.accor.com | Y91: @movenpickmarrakech | Z91: NA | AA91: Coord. complétée(s) depuis annuaire : tél | AB91: ST-ULT · ULTRA EXCLUSIF | AC91: AMB-ROM · ROMANTIQUE | AD91: KD-KFR · KIDS FRIENDLY | AE91: LVL-3 · 🔔🔔🔔 TROIS CLOCHES | AF91: À qualifier (labels / distinctions) | AG91: OR-ROM · ROMANTIQUE | AH91: PUB-CPL · Couple | AI91: ACC-PUB · ACC-PRV | AJ91: Mariage, séminaire, privatisation
A92: MARRAKECH | B92: HEBERGEMENT | C92: H164 | D92: HOTEL & RESORT | E92: {=IFERROR(INDEX(REF_CODES!$B$8:$B$13,MATCH($D92,REF_CODES!$C$8:$C$13,0)),"")} -> HB-HOT | F92: Pestana CR7 Marrakech | G92: 4 ETOILES | H92: BG1 · Moins de 300 € | I92: M Avenue, Av. de la Ménara | J92: Hivernage | K92: 174 | L92: OUI | M92: 150 | N92: 220 | O92: 350 | P92: NA | Q92: NA | R92: NA | S92: NA | T92: +212 5 24 33 36 00 | U92: À compléter | V92: non trouvé | W92: à compléter | X92: https://www.pestana.com/fr/hotel/pestana-cr7-marrakech | Y92: à compléter | Z92: NA | AA92: Importé de HEBERGEMENT. Quartier : Hivernage · Site : https://www.pestana.com/fr/hotel/pestana-cr7-marrakech [Ancien statut: À compléter] | AB92: ST-SIG · SIGNATURE | AC92: AMB-ROM · ROMANTIQUE | AD92: KD-CLB · KIDS CLUB | AE92: LVL-2 · 🔔🔔 DEUX CLOCHES | AF92: À qualifier (labels / distinctions) | AG92: OR-PRO · PROFESSIONNEL | AH92: PUB-GRP · Groupe | AI92: ACC-PUB · ACC-PRV | AJ92: Mariage, séminaire, privatisation
A93: MARRAKECH | B93: HEBERGEMENT | C93: H165 | D93: NATURE & HORIZON | E93: {=IFERROR(INDEX(REF_CODES!$B$8:$B$13,MATCH($D93,REF_CODES!$C$8:$C$13,0)),"")} -> HB-NAT | F93: White Camel Agafay | G93: À confirmer (catégorie / classement) | H93: BG3 · 500 – 800 € | I93: Désert d'Agafay (30-45 min de Marrakech) | J93: Agafay | K93: 51 | L93: OUI | M93: 559 | N93: NA | O93: NA | P93: NA | Q93: NA | R93: NA | S93: NA | T93: +212 660 389 756 / +212 661 776 766 | U93: +212 660389756 (à confirmer) | V93: contact@thewhitecamel.ma | W93: 51 lodges, tentes et suites — piscine, spa, restaurants | X93: thewhitecamel.com | Y93: à compléter | Z93: NA | AA93: Importé de HEBERGEMENT. Quartier : Agafay · Site : thewhitecamel.com | Coord. complétée(s) depuis annuaire : tél [Ancien statut: Importé] | Fusion doublons : Canyon Lodge Agafay (H187) | AB93: ST-PRE · PREMIUM | AC93: AMB-ZEN · ZEN & BIEN-ÊTRE | AD93: KD-KFR · KIDS FRIENDLY | AE93: LVL-2 · 🔔🔔 DEUX CLOCHES | AF93: À qualifier (labels / distinctions) | AG93: OR-ZEN · ZEN & BIEN-ÊTRE | AH93: PUB-CPL · Couple | AI93: ACC-PUB · ACC-PRV | AJ93: Dîner désert, team building
A94: MARRAKECH | B94: HEBERGEMENT | C94: H070 | D94: NATURE & HORIZON | E94: {=IFERROR(INDEX(REF_CODES!$B$8:$B$13,MATCH($D94,REF_CODES!$C$8:$C$13,0)),"")} -> HB-NAT | F94: Scarabeo Camp | G94: À confirmer (catégorie / classement) | H94: BG1 · Moins de 300 € | I94: Désert d'Agafay | J94: Agafay | K94: 15 | L94: OUI | M94: 200 | N94: NA | O94: NA | P94: NA | Q94: NA | R94: NA | S94: NA | T94: +212 524 43 36 88 / +212 524 43 36 88 (bureau) ; GSM terrain +212 662 800 823 | U94: +212 662800823 (à confirmer) | V94: reservation@scarabeo-camp.com | W94: Mme Manal | X94: https://www.scarabeocamp.com | Y94: @scarabeocamp | Z94: NA | AA94: Coord. complétée(s) depuis annuaire : tél | Fusion doublons : Stone Desert Camp (H216) | AB94: ST-PRE · PREMIUM | AC94: AMB-ZEN · ZEN & BIEN-ÊTRE | AD94: KD-KFR · KIDS FRIENDLY | AE94: LVL-2 · 🔔🔔 DEUX CLOCHES | AF94: À qualifier (labels / distinctions) | AG94: OR-ZEN · ZEN & BIEN-ÊTRE | AH94: PUB-CPL · Couple | AI94: ACC-PUB · ACC-PRV | AJ94: Dîner désert, team building
A95: MARRAKECH | B95: HEBERGEMENT | C95: H049 | D95: NATURE & HORIZON | E95: {=IFERROR(INDEX(REF_CODES!$B$8:$B$13,MATCH($D95,REF_CODES!$C$8:$C$13,0)),"")} -> HB-NAT | F95: Agafay Desert Camp | G95: À confirmer (catégorie / classement) | H95: BG2 · 300 – 500 € | I95: non trouvée | J95: Agafay | K95: non trouvé | L95: OUI | M95: 300 | N95: 450 | O95: 700 | P95: NA | Q95: NA | R95: NA | S95: NA | T95: +212 661 23 45 67 | U95: +212 661234567 (à confirmer) | V95: non trouvé | W95: Direction | X95: non trouvé | Y95: @agafaydesertluxury | Z95: NA | AA95: Coord. complétée(s) depuis annuaire : email, tél | AB95: ST-PRE · PREMIUM | AC95: AMB-ZEN · ZEN & BIEN-ÊTRE | AD95: KD-KFR · KIDS FRIENDLY | AE95: LVL-2 · 🔔🔔 DEUX CLOCHES | AF95: À qualifier (labels / distinctions) | AG95: OR-ZEN · ZEN & BIEN-ÊTRE | AH95: PUB-CPL · Couple | AI95: ACC-PUB · ACC-PRV | AJ95: Dîner désert, team building
A96: MARRAKECH | B96: HEBERGEMENT | C96: H166 | D96: NATURE & HORIZON | E96: {=IFERROR(INDEX(REF_CODES!$B$8:$B$13,MATCH($D96,REF_CODES!$C$8:$C$13,0)),"")} -> HB-NAT | F96: Caravan Agafay | G96: À confirmer (catégorie / classement) | H96: BG1 · Moins de 300 € | I96: KM 23 Route d'Agafay, Commune Rurale Agafay | J96: Agafay | K96: 40 | L96: OUI | M96: 250 | N96: NA | O96: NA | P96: NA | Q96: NA | R96: NA | S96: NA | T96: +212 6 61 59 11 50 | U96: À compléter | V96: guestexperience@caravanagafay.com | W96: tél non trouvé — 20 lodges-tentes + Explorer Tents, 2 piscines, spa, restaurant Olivar | X96: ourhabitas.com/caravan-agafay | Y96: à compléter | Z96: NA | AA96: Importé de HEBERGEMENT. Quartier : Agafay · Site : ourhabitas.com/caravan-agafay | Coord. complétée(s) depuis annuaire : email [Ancien statut: À compléter] | AB96: ST-PRE · PREMIUM | AC96: AMB-ZEN · ZEN & BIEN-ÊTRE | AD96: KD-KFR · KIDS FRIENDLY | AE96: LVL-2 · 🔔🔔 DEUX CLOCHES | AF96: À qualifier (labels / distinctions) | AG96: OR-ZEN · ZEN & BIEN-ÊTRE | AH96: PUB-CPL · Couple | AI96: ACC-PUB · ACC-PRV | AJ96: Dîner désert, team building
A97: MARRAKECH | B97: HEBERGEMENT | C97: H167 | D97: NATURE & HORIZON | E97: {=IFERROR(INDEX(REF_CODES!$B$8:$B$13,MATCH($D97,REF_CODES!$C$8:$C$13,0)),"")} -> HB-NAT | F97: Terre des Etoiles | G97: À confirmer (catégorie / classement) | H97: BG1 · Moins de 300 € | I97: Km 25, Commune d'Agafay, Kaïda d'Aït Imour | J97: Agafay | K97: 13 | L97: OUI | M97: 280 | N97: 400 | O97: 600 | P97: NA | Q97: NA | R97: NA | S97: NA | T97: +212 661 591 150 | U97: +212 661591150 (à confirmer) | V97: contact@terredesetoiles.net | W97: à compléter | X97: https://www.terredesetoiles.net | Y97: à compléter | Z97: NA | AA97: Importé de HEBERGEMENT. Quartier : Agafay · Site : https://www.terredesetoiles.net | Coord. complétée(s) depuis annuaire : tél [Ancien statut: Importé] | AB97: ST-PRE · PREMIUM | AC97: AMB-ZEN · ZEN & BIEN-ÊTRE | AD97: KD-KFR · KIDS FRIENDLY | AE97: LVL-2 · 🔔🔔 DEUX CLOCHES | AF97: À qualifier (labels / distinctions) | AG97: OR-ZEN · ZEN & BIEN-ÊTRE | AH97: PUB-CPL · Couple | AI97: ACC-PUB · ACC-PRV | AJ97: Dîner désert, team building
